Workbook

Sheet Annual
A1: Year | B1: 2020 | C1: 2021 | D1: 2022 | E1: 2023 | F1: 2024 | G1: 2024 | H1: =COUNTA($B1:G1)-1 -> 5 | I1: Calendar Years
B2: Value (L) | C2: Value (L) | D2: Value (L) | E2: Value (L) | F2: Value (L) | G2: Value (L) | H2: CAGR | I2: TOTAL
A3: NET WORTH
A4: Equity | B4: =Quarterly!B4 -> 45.920595 | C4: =Quarterly!$F4 -> 85.270469 | D4: =Quarterly!$J4 -> 104.01465 | E4: =Quarterly!$N4 -> 168.52674 | F4: =Quarterly!$R4 -> 233.86821 | G4: =Quarterly!$V4 -> 253.19622 | H4: =((G4/B4)^(1/$H$1)-1) -> 0.40698654
A5: Debt | B5: =Quarterly!B5 -> 32.53 | C5: =Quarterly!$F5 -> 40.56374 | D5: =Quarterly!$J5 -> 49.11703 | E5: =Quarterly!$N5 -> 58.18654 | F5: =Quarterly!$R5 -> 69.28894 | G5: =Quarterly!$V5 -> 81.86324 | H5: =((G5/B5)^(1/$H$1)-1) -> 0.20271014
A6: Gold | B6: =Quarterly!B6 -> 1 | C6: =Quarterly!$F6 -> 1.182 | D6: =Quarterly!$J6 -> 1.296137 | E6: =Quarterly!$N6 -> 1.559774 | F6: =Quarterly!$R6 -> 2.0347905 | G6: =Quarterly!$V6 -> 4.949544 | H6: =((G6/B6)^(1/$H$1)-1) -> 0.37693373
A7: Alternate | B7: =Quarterly!B7 -> 0 | C7: =Quarterly!$F7 -> 0 | D7: =Quarterly!$J7 -> 0 | E7: =Quarterly!$N7 -> 0 | F7: =Quarterly!$R7 -> 0 | G7: =Quarterly!$V7 -> 0 | H7: 0
A8: Liquid | B8: =Quarterly!B8 -> 4.65 | C8: =Quarterly!$F8 -> 2.8575657 | D8: =Quarterly!$J8 -> 1.5 | E8: =Quarterly!$N8 -> 2 | F8: =Quarterly!$R8 -> 0 | G8: =Quarterly!$V8 -> 0 | H8: =((G8/B8)^(1/$H$1)-1) -> -1
A9: Total | B9: =SUM(B4:B8) -> 84.100595 | C9: =SUM(C4:C8) -> 129.87377 | D9: =SUM(D4:D8) -> 155.92782 | E9: =SUM(E4:E8) -> 230.27305 | F9: =SUM(F4:F8) -> 305.19194 | G9: =SUM(G4:G8) -> 340.00901 | H9: =((G9/B9)^(1/$H$1)-1) -> 0.32232519
A11: CONTRIBUTION
A12: Equity | B12: =B4/B$9 -> 0.54601986 | C12: =C4/C$9 -> 0.65656418 | D12: =D4/D$9 -> 0.66706924 | E12: =E4/E$9 -> 0.7318561 | F12: =F4/F$9 -> 0.76629877 | G12: =G4/G$9 -> 0.74467505
A13: Debt | B13: =B5/B$9 -> 0.38679869 | C13: =C5/C$9 -> 0.31233203 | D13: =D5/D$9 -> 0.31499851 | E13: =E5/E$9 -> 0.25268497 | F13: =F5/F$9 -> 0.22703398 | G13: =G5/G$9 -> 0.24076786
A14: Gold | B14: =B6/B$9 -> 0.011890522 | C14: =C6/C$9 -> 0.0091011446 | D14: =D6/D$9 -> 0.0083124167 | E14: =E6/E$9 -> 0.0067735845 | F14: =F6/F$9 -> 0.0066672485 | G14: =G6/G$9 -> 0.014557097
A15: Alternate | B15: =B7/$B$9 -> 0 | C15: =C7/$B$9 -> 0 | D15: =D7/$B$9 -> 0 | E15: =E7/$B$9 -> 0 | F15: =F7/$B$9 -> 0 | G15: =G7/$B$9 -> 0
A16: Liquid | B16: =B8/B$9 -> 0.055290929 | C16: =C8/C$9 -> 0.022002638 | D16: =D8/D$9 -> 0.0096198357 | E16: =E8/E$9 -> 0.008685341 | F16: =F8/F$9 -> 0 | G16: =G8/G$9 -> 0
A17: Total | B17: =SUM(B12:B16) -> 1 | C17: =SUM(C12:C16) -> 1 | D17: =SUM(D12:D16) -> 1 | E17: =SUM(E12:E16) -> 1 | F17: =SUM(F12:F16) -> 1 | G17: =SUM(G12:G16) -> 1
A19: NEW INVESTMENT
A20: Equity | B20: 0 | C20: =SUM(Quarterly!$C20:$F20) -> 19.892195 | D20: =SUM(Quarterly!$G20:$J20) -> 19.851831 | E20: =SUM(Quarterly!$K20:$N20) -> 23.791935 | F20: =SUM(Quarterly!$O20:$R20) -> 31.473662 | G20: =SUM(Quarterly!$S20:$V20) -> 11.798125 | I20: =SUM(B20:G20) -> 106.80775
A21: Debt | B21: 0 | C21: =SUM(Quarterly!$C21:$F21) -> 4.77074 | D21: =SUM(Quarterly!$G21:$J21) -> 5.37619 | E21: =SUM(Quarterly!$K21:$N21) -> 5.77774 | F21: =SUM(Quarterly!$O21:$R21) -> 6.03276 | G21: =SUM(Quarterly!$S21:$V21) -> 6.8308 | I21: =SUM(B21:G21) -> 28.78823
A22: Gold | B22: 0 | C22: =SUM(Quarterly!$C22:$F22) -> 0.2475 | D22: =SUM(Quarterly!$G22:$J22) -> 0.00516 | E22: =SUM(Quarterly!$K22:$N22) -> 0 | F22: =SUM(Quarterly!$O22:$R22) -> 0 | G22: =SUM(Quarterly!$S22:$V22) -> 1 | I22: =SUM(B22:G22) -> 1.25266
A23: Alternate | B23: 0 | C23: =SUM(Quarterly!$C23:$F23) -> -0.19 | D23: =SUM(Quarterly!$G23:$J23) -> 0 | E23: =SUM(Quarterly!$K23:$N23) -> 0 | F23: =SUM(Quarterly!$O23:$R23) -> 0 | G23: =SUM(Quarterly!$S23:$V23) -> 0 | I23: =SUM(B23:G23) -> -0.19
A24: Liquid | B24: 0 | C24: =SUM(Quarterly!$C24:$F24) -> -1.7924343 | D24: =SUM(Quarterly!$G24:$J24) -> -1.3575657 | E24: =SUM(Quarterly!$K24:$N24) -> 0.5 | F24: =SUM(Quarterly!$O24:$R24) -> -2 | G24: =SUM(Quarterly!$S24:$V24) -> 0 | I24: =SUM(B24:G24) -> -4.65
A25: Total | B25: 0 | C25: =SUM(C20:C24) -> 22.928001 | D25: =SUM(D20:D24) -> 23.875615 | E25: =SUM(E20:E24) -> 30.069675 | F25: =SUM(F20:F24) -> 35.506422 | G25: =SUM(G20:G24) -> 19.628925 | I25: =SUM(B25:G25) -> 132.00864
A27: RETURNS
A28: Equity | B28: 0 | C28: =SUM(Quarterly!$C28:$F28) -> 19.457679 | D28: =SUM(Quarterly!$G28:$J28) -> -1.1076481 | E28: =SUM(Quarterly!$K28:$N28) -> 40.720154 | F28: =SUM(Quarterly!$O28:$R28) -> 33.867808 | G28: =SUM(Quarterly!$S28:$V28) -> 7.5298882 | I28: =SUM(B28:G28) -> 100.46788
A29: Debt | B29: 0 | C29: =SUM(Quarterly!$C29:$F29) -> 3.263 | D29: =SUM(Quarterly!$G29:$J29) -> 3.1771 | E29: =SUM(Quarterly!$K29:$N29) -> 3.29177 | F29: =SUM(Quarterly!$O29:$R29) -> 5.069526 | G29: =SUM(Quarterly!$S29:$V29) -> 5.73255 | I29: =SUM(B29:G29) -> 20.533946
A30: Gold | B30: 0 | C30: =SUM(Quarterly!$C30:$F30) -> -0.0655 | D30: =SUM(Quarterly!$G30:$J30) -> 0.108977 | E30: =SUM(Quarterly!$K30:$N30) -> 0.263637 | F30: =SUM(Quarterly!$O30:$R30) -> 0.4750165 | G30: =SUM(Quarterly!$S30:$V30) -> 1.9147535 | I30: =SUM(B30:G30) -> 2.696884
A31: Alternate | B31: 0 | C31: =SUM(Quarterly!$C31:$F31) -> 0.29485 | D31: =SUM(Quarterly!$G31:$J31) -> 0 | E31: =SUM(Quarterly!$K31:$N31) -> 0 | F31: =SUM(Quarterly!$O31:$R31) -> 0 | G31: =SUM(Quarterly!$S31:$V31) -> 0 | I31: =SUM(B31:G31) -> 0.29485
A32: Liquid | B32: 0 | C32: =SUM(Quarterly!$C32:$F32) -> 0 | D32: =SUM(Quarterly!$G32:$J32) -> 0 | E32: =SUM(Quarterly!$K32:$N32) -> 0 | F32: =SUM(Quarterly!$O32:$R32) -> 0 | G32: =SUM(Quarterly!$S32:$V32) -> 0 | I32: =SUM(B32:G32) -> 0
A33: Total | B33: 0 | C33: =SUM(C28:C32) -> 22.950029 | D33: =SUM(D28:D32) -> 2.1784289 | E33: =SUM(E28:E32) -> 44.275561 | F33: =SUM(F28:F32) -> 39.41235 | G33: =SUM(G28:G32) -> 15.177192 | I33: =SUM(B33:G33) -> 123.99356
A35: NET CHANGE
A36: Equity | B36: =SUMIF(Breakup!$B$58:$L$68,Annual!$A36,Breakup!C$58:C$68) -> 0 | C36: =C20+C28 -> 39.349874 | D36: =D20+D28 -> 18.744182 | E36: =E20+E28 -> 64.512089 | F36: =F20+F28 -> 65.34147 | G36: =G20+G28 -> 19.328013 | I36: =SUM(B36:G36) -> 207.27563
A37: Debt | B37: =SUMIF(Breakup!$B$58:$L$68,Annual!$A37,Breakup!C$58:C$68) -> 0 | C37: =C21+C29 -> 8.03374 | D37: =D21+D29 -> 8.55329 | E37: =E21+E29 -> 9.06951 | F37: =F21+F29 -> 11.102286 | G37: =G21+G29 -> 12.56335 | I37: =SUM(B37:G37) -> 49.322176
A38: Gold | B38: =SUMIF(Breakup!$B$58:$L$68,Annual!$A38,Breakup!C$58:C$68) -> 0 | C38: =C22+C30 -> 0.182 | D38: =D22+D30 -> 0.114137 | E38: =E22+E30 -> 0.263637 | F38: =F22+F30 -> 0.4750165 | G38: =G22+G30 -> 2.9147535 | I38: =SUM(B38:G38) -> 3.949544
A39: Alternate | B39: =SUMIF(Breakup!$B$58:$L$68,Annual!$A39,Breakup!C$58:C$68) -> 0 | C39: =C23+C31 -> 0.10485 | D39: =D23+D31 -> 0 | E39: =E23+E31 -> 0 | F39: =F23+F31 -> 0 | G39: =G23+G31 -> 0 | I39: =SUM(B39:G39) -> 0.10485
A40: Liquid | B40: =SUMIF(Breakup!$B$58:$L$68,Annual!$A40,Breakup!C$58:C$68) -> 0 | C40: =C24+C32 -> -1.7924343 | D40: =D24+D32 -> -1.3575657 | E40: =E24+E32 -> 0.5 | F40: =F24+F32 -> -2 | G40: =G24+G32 -> 0 | I40: =SUM(B40:G40) -> -4.65
A41: Total | B41: =SUM(B36:B40) -> 0 | C41: =C25+C33 -> 45.87803 | D41: =D25+D33 -> 26.054044 | E41: =E25+E33 -> 74.345236 | F41: =F25+F33 -> 74.918772 | G41: =G25+G33 -> 34.806117 | I41: =SUM(B41:G41) -> 256.0022
A42: % Change | C42: =C41/B9 -> 0.54551374 | D42: =D41/C9 -> 0.20061051 | E42: =E41/C9 -> 0.57244225 | F42: =F41/C9 -> 0.57685836 | G42: =G41/D9 -> 0.22321942
A44: % RETURNS
A45: Equity | C45: =C28/B4 -> 0.42372446 | D45: =D28/C4 -> -0.012989821 | E45: =E28/D4 -> 0.39148479 | F45: =F28/D4 -> 0.32560613 | G45: =G28/E4 -> 0.044680673
A46: Debt | C46: =C29/B5 -> 0.10030741 | D46: =D29/C5 -> 0.078323646 | E46: =E29/D5 -> 0.067018914 | F46: =F29/D5 -> 0.1032132 | G46: =G29/E5 -> 0.098520208
A47: Gold | C47: =C30/B6 -> -0.0655 | D47: =D30/C6 -> 0.092197124 | E47: =E30/D6 -> 0.20340211 | F47: =F30/D6 -> 0.36648634 | G47: =G30/E6 -> 1.2275839
A48: Alternate
A49: Liquid | C49: =C32/B8 -> 0 | D49: =D32/C8 -> 0 | E49: =E32/D8 -> 0 | F49: =F32/D8 -> 0 | G49: =G32/E8 -> 0
A50: Total | C50: =C33/B9 -> 0.27288783 | D50: =D33/C9 -> 0.016773431 | E50: =E33/D9 -> 0.28394908 | F50: =F33/D9 -> 0.25276022 | G50: =G33/E9 -> 0.065909542

Sheet Quarterly
A1: Quarter | B1: 2020-Q4 | C1: 2021-Q1 | D1: 2021-Q2 | E1: 2021-Q3 | F1: 2021-Q4 | G1: 2022-Q1 | H1: 2022-Q2 | I1: 2022-Q3 | J1: 2022-Q4 | K1: 2023-Q1 | L1: 2023-Q2 | M1: 2023-Q3 | N1: 2023-Q4 | O1: 2024-Q1 | P1: 2024-Q2 | Q1: 2024-Q3 | R1: 2024-Q4 | S1: 2025-Q1 | T1: 2025-Q2 | U1: 2025-Q3 | V1: 2025-Q4 | W1: 2026-Q1 | X1: =COUNTA(B1:W1)-1 -> 21 | Y1: Calendar Quarters
B2: Value (L) | C2: Value (L) | D2: Value (L) | E2: Value (L) | F2: Value (L) | G2: Value (L) | H2: Value (L) | I2: Value (L) | J2: Value (L) | K2: Value (L) | L2: Value (L) | M2: Value (L) | N2: Value (L) | O2: Value (L) | P2: Value (L) | Q2: Value (L) | R2: Value (L) | S2: Value (L) | T2: Value (L) | U2: Value (L) | V2: Value (L) | W2: Value (L) | X2: CAGR | Y2: TOTAL | Z2: Average
A3: NET WORTH
A4: Equity | B4: =Monthly!B4 -> 45.920595 | C4: =Monthly!E4 -> 55.636562 | D4: =Monthly!H4 -> 64.627927 | E4: =Monthly!K4 -> 78.201752 | F4: =Monthly!N4 -> 85.270469 | G4: =Monthly!Q4 -> 88.963405 | H4: =Monthly!T4 -> 82.702511 | I4: =Monthly!$W4 -> 96.137323 | J4: =Monthly!$Z4 -> 104.01465 | K4: =Monthly!$AC4 -> 108.818 | L4: =Monthly!$AF4 -> 131.07883 | M4: =Monthly!$AI4 -> 147.99221 | N4: =Monthly!$AL4 -> 168.52674 | O4: =Monthly!$AO4 -> 188.05701 | P4: =Monthly!$AR4 -> 212.83646 | Q4: =Monthly!$AU4 -> 237.05244 | R4: =Monthly!$AX4 -> 233.86821 | S4: =Monthly!$BA4 -> 207.93476 | T4: =Monthly!$BD4 -> 243.49772 | U4: =Monthly!$BG4 -> 242.45864 | V4: =Monthly!$BJ4 -> 253.19622 | W4: =Monthly!$BM4 -> 226.98142 | X4: =((W4/B4)^(4/$X$1)-1) -> 0.35577368
A5: Debt | B5: =Monthly!B5 -> 32.53 | C5: =Monthly!E5 -> 36.019 | D5: =Monthly!H5 -> 37.34856 | E5: =Monthly!K5 -> 39.71884 | F5: =Monthly!N5 -> 40.56374 | G5: =Monthly!Q5 -> 44.31114 | H5: =Monthly!T5 -> 45.29654 | I5: =Monthly!$W5 -> 47.860834 | J5: =Monthly!$Z5 -> 49.11703 | K5: =Monthly!$AC5 -> 53.19227 | L5: =Monthly!$AF5 -> 54.226046 | M5: =Monthly!$AI5 -> 57.09389 | N5: =Monthly!$AL5 -> 58.18654 | O5: =Monthly!$AO5 -> 64.072264 | P5: =Monthly!$AR5 -> 65.21269 | Q5: =Monthly!$AU5 -> 68.03128 | R5: =Monthly!$AX5 -> 69.28894 | S5: =Monthly!$BA5 -> 77.71356 | T5: =Monthly!$BD5 -> 78.99227 | U5: =Monthly!$BG5 -> 80.222692 | V5: =Monthly!$BJ5 -> 81.86324 | W5: =Monthly!$BM5 -> 88.6149 | X5: =((W5/B5)^(4/$X$1)-1) -> 0.21031819
A6: Gold | B6: =Monthly!B6 -> 1 | C6: =Monthly!E6 -> 1.1650255 | D6: =Monthly!H6 -> 1.1951 | E6: =Monthly!K6 -> 1.17335 | F6: =Monthly!N6 -> 1.182 | G6: =Monthly!Q6 -> 1.18455 | H6: =Monthly!T6 -> 1.211 | I6: =Monthly!$W6 -> 1.2162 | J6: =Monthly!$Z6 -> 1.296137 | K6: =Monthly!$AC6 -> 1.382417 | L6: =Monthly!$AF6 -> 1.473594 | M6: =Monthly!$AI6 -> 1.468757 | N6: =Monthly!$AL6 -> 1.559774 | O6: =Monthly!$AO6 -> 1.676741 | P6: =Monthly!$AR6 -> 1.86114 | Q6: =Monthly!$AU6 -> 1.983838 | R6: =Monthly!$AX6 -> 2.0347905 | S6: =Monthly!$BA6 -> 2.190049 | T6: =Monthly!$BD6 -> 2.447904 | U6: =Monthly!$BG6 -> 4.3079155 | V6: =Monthly!$BJ6 -> 4.949544 | W6: =Monthly!$BM6 -> 5.054594 | X6: =((W6/B6)^(4/$X$1)-1) -> 0.36155592
A7: Alternate | B7: =Monthly!B7 -> 0 | C7: =Monthly!E7 -> 0 | D7: =Monthly!H7 -> 0 | E7: =Monthly!K7 -> 0.54 | F7: =Monthly!N7 -> 0 | G7: =Monthly!Q7 -> 0 | H7: =Monthly!T7 -> 0 | I7: =Monthly!$W7 -> 0 | J7: =Monthly!$Z7 -> 0 | K7: =Monthly!$AC7 -> 0 | L7: =Monthly!$AF7 -> 0 | M7: =Monthly!$AI7 -> 0 | N7: =Monthly!$AL7 -> 0 | O7: =Monthly!$AO7 -> 0 | P7: =Monthly!$AR7 -> 0 | Q7: =Monthly!$AU7 -> 0 | R7: =Monthly!$AX7 -> 0 | S7: =Monthly!$BA7 -> 0 | T7: =Monthly!$BD7 -> 0 | U7: =Monthly!$BG7 -> 0 | V7: =Monthly!$BJ7 -> 0 | W7: =Monthly!$BM7 -> 0 | X7: -
A8: Liquid | B8: =Monthly!B8 -> 4.65 | C8: =Monthly!E8 -> 1.0035016 | D8: =Monthly!H8 -> 3.5291139 | E8: =Monthly!K8 -> 4.3487874 | F8: =Monthly!N8 -> 2.8575657 | G8: =Monthly!Q8 -> 1.347861 | H8: =Monthly!T8 -> 0 | I8: =Monthly!$W8 -> 2.5 | J8: =Monthly!$Z8 -> 1.5 | K8: =Monthly!$AC8 -> 3 | L8: =Monthly!$AF8 -> 0 | M8: =Monthly!$AI8 -> 0 | N8: =Monthly!$AL8 -> 2 | O8: =Monthly!$AO8 -> 2.0134634 | P8: =Monthly!$AR8 -> 0 | Q8: =Monthly!$AU8 -> 3.0407111 | R8: =Monthly!$AX8 -> 0 | S8: =Monthly!$BA8 -> 9 | T8: =Monthly!$BD8 -> 0 | U8: =Monthly!$BG8 -> 0 | V8: =Monthly!$BJ8 -> 0 | W8: =Monthly!$BM8 -> 0
A9: Total | B9: =SUM(B4:B8) -> 84.100595 | C9: =SUM(C4:C8) -> 93.824089 | D9: =SUM(D4:D8) -> 106.7007 | E9: =SUM(E4:E8) -> 123.98273 | F9: =SUM(F4:F8) -> 129.87377 | G9: =SUM(G4:G8) -> 135.80696 | H9: =SUM(H4:H8) -> 129.21005 | I9: =SUM(I4:I8) -> 147.71436 | ... W9: =SUM(W4:W8) -> 320.65091 | X9: =((W9/B9)^(4/$X$1)-1) -> 0.2903607
A11: CONTRIBUTION
A12: Equity | B12: =B4/B$9 -> 0.54601986 | C12: =C4/C$9 -> 0.59298803 | D12: =D4/D$9 -> 0.60569356 | E12: =E4/E$9 -> 0.63074714 | F12: =F4/F$9 -> 0.65656418 | G12: =G4/G$9 -> 0.65507252 | H12: =H4/H$9 -> 0.64006252 | I12: =I4/I$9 -> 0.65083263 | ... W12: =W4/W$9 -> 0.70787704
A13: Debt | B13: =B5/B$9 -> 0.38679869 | C13: =C5/C$9 -> 0.38389928 | D13: =D5/D$9 -> 0.35003106 | E13: =E5/E$9 -> 0.32035784 | F13: =F5/F$9 -> 0.31233203 | G13: =G5/G$9 -> 0.32628034 | H13: =H5/H$9 -> 0.35056514 | I13: =I5/I$9 -> 0.32400936 | ... W13: =W5/W$9 -> 0.27635942
A14: Gold | B14: =B6/B$9 -> 0.011890522 | C14: =C6/C$9 -> 0.012417126 | D14: =D6/D$9 -> 0.011200489 | E14: =E6/E$9 -> 0.0094638181 | F14: =F6/F$9 -> 0.0091011446 | G14: =G6/G$9 -> 0.0087223073 | H14: =H6/H$9 -> 0.0093723359 | I14: =I6/I$9 -> 0.0082334583 | ... W14: =W6/W$9 -> 0.015763542
A15: Alternate | B15: =B7/$B$9 -> 0 | C15: =C7/$B$9 -> 0 | D15: =D7/$B$9 -> 0 | E15: =E7/$B$9 -> 0.0064208821 | F15: =F7/$B$9 -> 0 | G15: =G7/$B$9 -> 0 | H15: =H7/$B$9 -> 0 | I15: =I7/$B$9 -> 0 | ... K15: =K7/$B$9 -> 0 | L15: =L7/L$9 -> 0 | M15: =M7/M$9 -> 0 | N15: =N7/N$9 -> 0 | O15: =O7/O$9 -> 0 | P15: =P7/P$9 -> 0 | Q15: =Q7/Q$9 -> 0 | R15: =R7/R$9 -> 0 | S15: =S7/S$9 -> 0 | ... W15: =W7/W$9 -> 0
A16: Liquid | B16: =B8/B$9 -> 0.055290929 | C16: =C8/C$9 -> 0.010695565 | D16: =D8/D$9 -> 0.033074889 | E16: =E8/E$9 -> 0.035075752 | F16: =F8/F$9 -> 0.022002638 | G16: =G8/G$9 -> 0.0099248304 | H16: =H8/H$9 -> 0 | I16: =I8/I$9 -> 0.016924557 | ... W16: =W8/W$9 -> 0
A17: Total | B17: =SUM(B12:B16) -> 1 | C17: =SUM(C12:C16) -> 1 | D17: =SUM(D12:D16) -> 1 | E17: =SUM(E12:E16) -> 1.0020654 | F17: =SUM(F12:F16) -> 1 | G17: =SUM(G12:G16) -> 1 | H17: =SUM(H12:H16) -> 1 | I17: =SUM(I12:I16) -> 1 | ... W17: =SUM(W12:W16) -> 1
A19: NEW INVESTMENT
A20: Equity | B20: 0 | C20: =Monthly!C20+Monthly!D20+Monthly!E20 -> 4.2563708 | D20: =Monthly!F20+Monthly!G20+Monthly!H20 -> 2.6 | E20: =Monthly!K20+Monthly!I20+Monthly!J20 -> 6.1903996 | F20: =Monthly!M20+Monthly!L20+Monthly!N20 -> 6.8454247 | G20: =Monthly!Q20+Monthly!O20+Monthly!P20 -> 5.4704209 | H20: =Monthly!T20+Monthly!R20+Monthly!S20 -> 1.9750152 | I20: =Monthly!$W20+Monthly!$U20+Monthly!$V20 -> 4.9833422 | J20: =Monthly!$X20+Monthly!$Y20+Monthly!$Z20 -> 7.4230522 | K20: =Monthly!$AA20+Monthly!$AB20+Monthly!$AC20 -> 7.1736018 | L20: =Monthly!$AD20+Monthly!$AE20+Monthly!$AF20 -> 5.9398419 | M20: =Monthly!$AG20+Monthly!$AH20+Monthly!$AI20 -> 8.2797045 | N20: =Monthly!$AJ20+Monthly!$AK20+Monthly!$AL20 -> 2.3987867 | O20: =Monthly!$AM20+Monthly!$AN20+Monthly!$AO20 -> 8.2010547 | P20: =Monthly!$AP20+Monthly!$AQ20+Monthly!$AR20 -> 6.4789379 | Q20: =Monthly!$AS20+Monthly!$AT20+Monthly!$AU20 -> 8.516083 | R20: =Monthly!$AV20+Monthly!$AW20+Monthly!$AX20 -> 8.2775865 | S20: =Monthly!$AY20+Monthly!$AZ20+Monthly!$BA20 -> -3.2658037 | T20: =Monthly!$BB20+Monthly!$BC20+Monthly!$BD20 -> 8.6095711 | U20: =Monthly!$BE20+Monthly!$BF20+Monthly!$BG20 -> 1.4188489 | V20: =Monthly!$BH20+Monthly!$BI20+Monthly!$BJ20 -> 5.0355088 | W20: =SUM(Monthly!$BK20:$BM20) -> 2.5816775 | Y20: =SUM(B20:W20) -> 109.38943 | Z20: =Y20/$X$1 -> 5.2090203
A21: Debt | B21: 0 | C21: =Monthly!C21+Monthly!D21+Monthly!E21 -> 0.9 | D21: =Monthly!F21+Monthly!G21+Monthly!H21 -> 0.69596 | E21: =Monthly!K21+Monthly!I21+Monthly!J21 -> 2.34888 | F21: =Monthly!M21+Monthly!L21+Monthly!N21 -> 0.8259 | G21: =Monthly!Q21+Monthly!O21+Monthly!P21 -> 0.8364 | H21: =Monthly!T21+Monthly!R21+Monthly!S21 -> 0.8259 | I21: =Monthly!$W21+Monthly!$U21+Monthly!$V21 -> 2.495294 | J21: =Monthly!$X21+Monthly!$Y21+Monthly!$Z21 -> 1.218596 | K21: =Monthly!$AA21+Monthly!$AB21+Monthly!$AC21 -> 0.937 | L21: =Monthly!$AD21+Monthly!$AE21+Monthly!$AF21 -> 0.9555 | M21: =Monthly!$AG21+Monthly!$AH21+Monthly!$AI21 -> 2.8305 | N21: =Monthly!$AJ21+Monthly!$AK21+Monthly!$AL21 -> 1.05474 | O21: =Monthly!$AM21+Monthly!$AN21+Monthly!$AO21 -> 1.05474 | P21: =Monthly!$AP21+Monthly!$AQ21+Monthly!$AR21 -> 1.05474 | Q21: =Monthly!$AS21+Monthly!$AT21+Monthly!$AU21 -> 2.70474 | R21: =Monthly!$AV21+Monthly!$AW21+Monthly!$AX21 -> 1.21854 | S21: =Monthly!$AY21+Monthly!$AZ21+Monthly!$BA21 -> 2.71854 | T21: =Monthly!$BB21+Monthly!$BC21+Monthly!$BD21 -> 1.21854 | U21: =Monthly!$BE21+Monthly!$BF21+Monthly!$BG21 -> 1.21854 | V21: =Monthly!$BH21+Monthly!$BI21+Monthly!$BJ21 -> 1.67518 | W21: =SUM(Monthly!$BK21:$BM21) -> 1.42518 | Y21: =SUM(B21:W21) -> 30.21341 | Z21: =Y21/$X$1 -> 1.4387338
A22: Gold | B22: 0 | C22: =Monthly!C22+Monthly!D22+Monthly!E22 -> 0.2475 | D22: =Monthly!F22+Monthly!G22+Monthly!H22 -> 0 | E22: =Monthly!K22+Monthly!I22+Monthly!J22 -> 0 | F22: =Monthly!M22+Monthly!L22+Monthly!N22 -> 0 | G22: =Monthly!Q22+Monthly!O22+Monthly!P22 -> -0.0197 | H22: =Monthly!T22+Monthly!R22+Monthly!S22 -> 0.02645 | I22: =Monthly!$W22+Monthly!$U22+Monthly!$V22 -> -0.00159 | J22: =Monthly!$X22+Monthly!$Y22+Monthly!$Z22 -> 0 | K22: =Monthly!$AA22+Monthly!$AB22+Monthly!$AC22 -> 0 | L22: =Monthly!$AD22+Monthly!$AE22+Monthly!$AF22 -> 0 | M22: =Monthly!$AG22+Monthly!$AH22+Monthly!$AI22 -> 0 | N22: =Monthly!$AJ22+Monthly!$AK22+Monthly!$AL22 -> 0 | O22: =Monthly!$AM22+Monthly!$AN22+Monthly!$AO22 -> 0 | P22: =Monthly!$AP22+Monthly!$AQ22+Monthly!$AR22 -> 0 | Q22: =Monthly!$AS22+Monthly!$AT22+Monthly!$AU22 -> 0 | R22: =Monthly!$AV22+Monthly!$AW22+Monthly!$AX22 -> 0 | S22: =Monthly!$AY22+Monthly!$AZ22+Monthly!$BA22 -> 0 | T22: =Monthly!$BB22+Monthly!$BC22+Monthly!$BD22 -> 0 | U22: =Monthly!$BE22+Monthly!$BF22+Monthly!$BG22 -> 1 | V22: =Monthly!$BH22+Monthly!$BI22+Monthly!$BJ22 -> 0 | W22: =SUM(Monthly!$BK22:$BM22) -> 0 | Y22: =SUM(B22:W22) -> 1.25266 | Z22: =Y22/$X$1 -> 0.059650476
A23: Alternate | B23: 0 | C23: =Monthly!C23+Monthly!D23+Monthly!E23 -> 0 | D23: =Monthly!F23+Monthly!G23+Monthly!H23 -> 0 | E23: =Monthly!K23+Monthly!I23+Monthly!J23 -> 0.54 | F23: =Monthly!M23+Monthly!L23+Monthly!N23 -> -0.73 | G23: =Monthly!Q23+Monthly!O23+Monthly!P23 -> 0 | H23: =Monthly!T23+Monthly!R23+Monthly!S23 -> 0 | I23: =Monthly!$W23+Monthly!$U23+Monthly!$V23 -> 0 | J23: =Monthly!$X23+Monthly!$Y23+Monthly!$Z23 -> 0 | K23: =Monthly!$AA23+Monthly!$AB23+Monthly!$AC23 -> 0 | L23: =Monthly!$AD23+Monthly!$AE23+Monthly!$AF23 -> 0 | M23: =Monthly!$AG23+Monthly!$AH23+Monthly!$AI23 -> 0 | N23: =Monthly!$AJ23+Monthly!$AK23+Monthly!$AL23 -> 0 | O23: =Monthly!$AM23+Monthly!$AN23+Monthly!$AO23 -> 0 | P23: =Monthly!$AP23+Monthly!$AQ23+Monthly!$AR23 -> 0 | Q23: =Monthly!$AS23+Monthly!$AT23+Monthly!$AU23 -> 0 | R23: =Monthly!$AV23+Monthly!$AW23+Monthly!$AX23 -> 0 | S23: =Monthly!$AY23+Monthly!$AZ23+Monthly!$BA23 -> 0 | T23: =Monthly!$BB23+Monthly!$BC23+Monthly!$BD23 -> 0 | U23: =Monthly!$BE23+Monthly!$BF23+Monthly!$BG23 -> 0 | V23: =Monthly!$BH23+Monthly!$BI23+Monthly!$BJ23 -> 0 | W23: =SUM(Monthly!$BK23:$BM23) -> 0 | Y23: =SUM(B23:W23) -> -0.19 | Z23: =Y23/$X$1 -> -0.009047619
A24: Liquid | B24: 0 | C24: =Monthly!C24+Monthly!D24+Monthly!E24 -> -3.6464984 | D24: =Monthly!F24+Monthly!G24+Monthly!H24 -> 2.5256122 | E24: =Monthly!K24+Monthly!I24+Monthly!J24 -> 0.81967358 | F24: =Monthly!M24+Monthly!L24+Monthly!N24 -> -1.4912217 | G24: =Monthly!Q24+Monthly!O24+Monthly!P24 -> -1.5097047 | H24: =Monthly!T24+Monthly!R24+Monthly!S24 -> -1.347861 | I24: =Monthly!$W24+Monthly!$U24+Monthly!$V24 -> 2.5 | J24: =Monthly!$X24+Monthly!$Y24+Monthly!$Z24 -> -1 | K24: =Monthly!$AA24+Monthly!$AB24+Monthly!$AC24 -> 1.5 | L24: =Monthly!$AD24+Monthly!$AE24+Monthly!$AF24 -> -3 | M24: =Monthly!$AG24+Monthly!$AH24+Monthly!$AI24 -> 0 | N24: =Monthly!$AJ24+Monthly!$AK24+Monthly!$AL24 -> 2 | O24: =Monthly!$AM24+Monthly!$AN24+Monthly!$AO24 -> 0.013463446 | P24: =Monthly!$AP24+Monthly!$AQ24+Monthly!$AR24 -> -2.0134634 | Q24: =Monthly!$AS24+Monthly!$AT24+Monthly!$AU24 -> 3.0407111 | R24: =Monthly!$AV24+Monthly!$AW24+Monthly!$AX24 -> -3.0407111 | S24: =Monthly!$AY24+Monthly!$AZ24+Monthly!$BA24 -> 9 | T24: =Monthly!$BB24+Monthly!$BC24+Monthly!$BD24 -> -9 | U24: =Monthly!$BE24+Monthly!$BF24+Monthly!$BG24 -> 0 | V24: =Monthly!$BH24+Monthly!$BI24+Monthly!$BJ24 -> 0 | W24: =SUM(Monthly!$BK24:$BM24) -> 0 | Y24: =SUM(B24:W24) -> -4.65 | Z24: =Y24/$X$1 -> -0.22142857
A25: Total | B25: =SUM(B20:B24) -> 0 | C25: =SUM(C20:C24) -> 1.7573724 | D25: =SUM(D20:D24) -> 5.8215722 | E25: =SUM(E20:E24) -> 9.8989531 | F25: =SUM(F20:F24) -> 5.4501029 | G25: =SUM(G20:G24) -> 4.7774162 | H25: =SUM(H20:H24) -> 1.4795042 | I25: =SUM(I20:I24) -> 9.9770462 | ... W25: =SUM(W20:W24) -> 4.0068575 | Y25: =SUM(B25:W25) -> 136.0155 | Z25: =Y25/$X$1 -> 6.4769283
A27: RETURNS
A28: Equity | B28: 0 | C28: =Monthly!C28+Monthly!D28+Monthly!E28 -> 5.459596 | D28: =Monthly!F28+Monthly!G28+Monthly!H28 -> 6.3913656 | E28: =Monthly!K28+Monthly!I28+Monthly!J28 -> 7.3834255 | F28: =Monthly!M28+Monthly!L28+Monthly!N28 -> 0.2232921 | G28: =Monthly!Q28+Monthly!O28+Monthly!P28 -> -1.7774849 | H28: =Monthly!T28+Monthly!R28+Monthly!S28 -> -8.2359098 | I28: =Monthly!$W28+Monthly!$U28+Monthly!$V28 -> 8.4514702 | J28: =Monthly!$X28+Monthly!$Y28+Monthly!$Z28 -> 0.45427629 | K28: =Monthly!$AA28+Monthly!$AB28+Monthly!$AC28 -> -2.3702547 | L28: =Monthly!$AD28+Monthly!$AE28+Monthly!$AF28 -> 16.32099 | M28: =Monthly!$AG28+Monthly!$AH28+Monthly!$AI28 -> 8.6336759 | N28: =Monthly!$AJ28+Monthly!$AK28+Monthly!$AL28 -> 18.135743 | O28: =Monthly!$AM28+Monthly!$AN28+Monthly!$AO28 -> 11.329213 | P28: =Monthly!$AP28+Monthly!$AQ28+Monthly!$AR28 -> 18.300515 | Q28: =Monthly!$AS28+Monthly!$AT28+Monthly!$AU28 -> 15.699895 | R28: =Monthly!$AV28+Monthly!$AW28+Monthly!$AX28 -> -11.461816 | S28: =Monthly!$AY28+Monthly!$AZ28+Monthly!$BA28 -> -22.66765 | T28: =Monthly!$BB28+Monthly!$BC28+Monthly!$BD28 -> 26.953391 | U28: =Monthly!$BE28+Monthly!$BF28+Monthly!$BG28 -> -2.4579275 | V28: =Monthly!$BH28+Monthly!$BI28+Monthly!$BJ28 -> 5.7020745 | W28: =SUM(Monthly!$BK28:$BM28) -> -28.796484 | Y28: =SUM(B28:W28) -> 71.671397 | Z28: =Y28/$X$1 -> 3.4129237
A29: Debt | B29: 0 | C29: =Monthly!C29+Monthly!D29+Monthly!E29 -> 2.589 | D29: =Monthly!F29+Monthly!G29+Monthly!H29 -> 0.6336 | E29: =Monthly!K29+Monthly!I29+Monthly!J29 -> 0.0214 | F29: =Monthly!M29+Monthly!L29+Monthly!N29 -> 0.019 | G29: =Monthly!Q29+Monthly!O29+Monthly!P29 -> 2.911 | H29: =Monthly!T29+Monthly!R29+Monthly!S29 -> 0.1595 | I29: =Monthly!$W29+Monthly!$U29+Monthly!$V29 -> 0.069 | J29: =Monthly!$X29+Monthly!$Y29+Monthly!$Z29 -> 0.0376 | K29: =Monthly!$AA29+Monthly!$AB29+Monthly!$AC29 -> 3.13824 | L29: =Monthly!$AD29+Monthly!$AE29+Monthly!$AF29 -> 0.078276 | M29: =Monthly!$AG29+Monthly!$AH29+Monthly!$AI29 -> 0.037344 | N29: =Monthly!$AJ29+Monthly!$AK29+Monthly!$AL29 -> 0.03791 | O29: =Monthly!$AM29+Monthly!$AN29+Monthly!$AO29 -> 4.830984 | P29: =Monthly!$AP29+Monthly!$AQ29+Monthly!$AR29 -> 0.087476 | Q29: =Monthly!$AS29+Monthly!$AT29+Monthly!$AU29 -> 0.111946 | R29: =Monthly!$AV29+Monthly!$AW29+Monthly!$AX29 -> 0.03912 | S29: =Monthly!$AY29+Monthly!$AZ29+Monthly!$BA29 -> 5.70608 | T29: =Monthly!$BB29+Monthly!$BC29+Monthly!$BD29 -> 0.060122 | U29: =Monthly!$BE29+Monthly!$BF29+Monthly!$BG29 -> 0.02373 | V29: =Monthly!$BH29+Monthly!$BI29+Monthly!$BJ29 -> -0.057382 | W29: =SUM(Monthly!$BK29:$BM29) -> 5.33513 | Y29: =SUM(B29:W29) -> 25.869076 | Z29: =Y29/$X$1 -> 1.2318608
A30: Gold | B30: 0 | C30: =Monthly!C30+Monthly!D30+Monthly!E30 -> -0.0824745 | D30: =Monthly!F30+Monthly!G30+Monthly!H30 -> 0.0300745 | E30: =Monthly!K30+Monthly!I30+Monthly!J30 -> -0.02175 | F30: =Monthly!M30+Monthly!L30+Monthly!N30 -> 0.00865 | G30: =Monthly!Q30+Monthly!O30+Monthly!P30 -> 0.02225 | H30: =Monthly!T30+Monthly!R30+Monthly!S30 -> 0 | I30: =Monthly!$W30+Monthly!$U30+Monthly!$V30 -> 0.00679 | J30: =Monthly!$X30+Monthly!$Y30+Monthly!$Z30 -> 0.079937 | K30: =Monthly!$AA30+Monthly!$AB30+Monthly!$AC30 -> 0.08628 | L30: =Monthly!$AD30+Monthly!$AE30+Monthly!$AF30 -> 0.091177 | M30: =Monthly!$AG30+Monthly!$AH30+Monthly!$AI30 -> -0.004837 | N30: =Monthly!$AJ30+Monthly!$AK30+Monthly!$AL30 -> 0.091017 | O30: =Monthly!$AM30+Monthly!$AN30+Monthly!$AO30 -> 0.116967 | P30: =Monthly!$AP30+Monthly!$AQ30+Monthly!$AR30 -> 0.184399 | Q30: =Monthly!$AS30+Monthly!$AT30+Monthly!$AU30 -> 0.122698 | R30: =Monthly!$AV30+Monthly!$AW30+Monthly!$AX30 -> 0.0509525 | S30: =Monthly!$AY30+Monthly!$AZ30+Monthly!$BA30 -> 0.1552585 | T30: =Monthly!$BB30+Monthly!$BC30+Monthly!$BD30 -> 0.257855 | U30: =Monthly!$BE30+Monthly!$BF30+Monthly!$BG30 -> 0.8600115 | V30: =Monthly!$BH30+Monthly!$BI30+Monthly!$BJ30 -> 0.6416285 | W30: =SUM(Monthly!$BK30:$BM30) -> 0.10505 | Y30: =SUM(B30:W30) -> 2.801934 | Z30: =Y30/$X$1 -> 0.13342543
A31: Alternate | B31: 0 | C31: =Monthly!C31+Monthly!D31+Monthly!E31 -> 0 | D31: =Monthly!F31+Monthly!G31+Monthly!H31 -> 0 | E31: =Monthly!K31+Monthly!I31+Monthly!J31 -> 0.10485 | F31: =Monthly!M31+Monthly!L31+Monthly!N31 -> 0.19 | G31: =Monthly!Q31+Monthly!O31+Monthly!P31 -> 0 | H31: =Monthly!T31+Monthly!R31+Monthly!S31 -> 0 | I31: =Monthly!$W31+Monthly!$U31+Monthly!$V31 -> 0 | J31: =Monthly!$X31+Monthly!$Y31+Monthly!$Z31 -> 0 | K31: =Monthly!$AA31+Monthly!$AB31+Monthly!$AC31 -> 0 | L31: =Monthly!$AD31+Monthly!$AE31+Monthly!$AF31 -> 0 | M31: =Monthly!$AG31+Monthly!$AH31+Monthly!$AI31 -> 0 | N31: =Monthly!$AJ31+Monthly!$AK31+Monthly!$AL31 -> 0 | O31: =Monthly!$AM31+Monthly!$AN31+Monthly!$AO31 -> 0 | P31: =Monthly!$AP31+Monthly!$AQ31+Monthly!$AR31 -> 0 | Q31: =Monthly!$AS31+Monthly!$AT31+Monthly!$AU31 -> 0 | R31: =Monthly!$AV31+Monthly!$AW31+Monthly!$AX31 -> 0 | S31: =Monthly!$AY31+Monthly!$AZ31+Monthly!$BA31 -> 0 | T31: =Monthly!$BB31+Monthly!$BC31+Monthly!$BD31 -> 0 | U31: =Monthly!$BE31+Monthly!$BF31+Monthly!$BG31 -> 0 | V31: =Monthly!$BH31+Monthly!$BI31+Monthly!$BJ31 -> 0 | W31: =SUM(Monthly!$BK31:$BM31) -> 0 | Y31: =SUM(B31:W31) -> 0.29485 | Z31: =Y31/$X$1 -> 0.014040476
A32: Liquid | B32: 0 | C32: =Monthly!C32+Monthly!D32+Monthly!E32 -> 0 | D32: =Monthly!F32+Monthly!G32+Monthly!H32 -> 0 | E32: =Monthly!K32+Monthly!I32+Monthly!J32 -> 0 | F32: =Monthly!M32+Monthly!L32+Monthly!N32 -> 0 | G32: =Monthly!Q32+Monthly!O32+Monthly!P32 -> 0 | H32: =Monthly!T32+Monthly!R32+Monthly!S32 -> 0 | I32: =Monthly!$W32+Monthly!$U32+Monthly!$V32 -> 0 | J32: =Monthly!$X32+Monthly!$Y32+Monthly!$Z32 -> 0 | K32: =Monthly!$AA32+Monthly!$AB32+Monthly!$AC32 -> 0 | L32: =Monthly!$AD32+Monthly!$AE32+Monthly!$AF32 -> 0 | M32: =Monthly!$AG32+Monthly!$AH32+Monthly!$AI32 -> 0 | N32: =Monthly!$AJ32+Monthly!$AK32+Monthly!$AL32 -> 0 | O32: =Monthly!$AM32+Monthly!$AN32+Monthly!$AO32 -> 0 | P32: =Monthly!$AP32+Monthly!$AQ32+Monthly!$AR32 -> 0 | Q32: =Monthly!$AS32+Monthly!$AT32+Monthly!$AU32 -> 0 | R32: =Monthly!$AV32+Monthly!$AW32+Monthly!$AX32 -> 0 | S32: =Monthly!$AY32+Monthly!$AZ32+Monthly!$BA32 -> 0 | T32: =Monthly!$BB32+Monthly!$BC32+Monthly!$BD32 -> 0 | U32: =Monthly!$BE32+Monthly!$BF32+Monthly!$BG32 -> 0 | V32: =Monthly!$BH32+Monthly!$BI32+Monthly!$BJ32 -> 0 | W32: =SUM(Monthly!$BK32:$BM32) -> 0 | Y32: =SUM(B32:W32) -> 0 | Z32: =Y32/$X$1 -> 0
A33: Total | B33: =SUM(B28:B32) -> 0 | C33: =SUM(C28:C32) -> 7.9661215 | D33: =SUM(D28:D32) -> 7.0550401 | E33: =SUM(E28:E32) -> 7.4879255 | F33: =SUM(F28:F32) -> 0.4409421 | G33: =SUM(G28:G32) -> 1.1557651 | H33: =SUM(H28:H32) -> -8.0764098 | I33: =SUM(I28:I32) -> 8.5272602 | ... W33: =SUM(W28:W32) -> -23.356304 | Y33: =SUM(B33:W33) -> 100.63726 | Z33: =Y33/$X$1 -> 4.7922503
A35: NET CHANGE
A36: Equity | B36: =SUMIF(Breakup!$B$58:$L$68,Quarterly!$A36,Breakup!C$58:C$68) -> 0 | C36: =C20+C28 -> 9.7159668 | D36: =D20+D28 -> 8.9913656 | E36: =E20+E28 -> 13.573825 | F36: =F20+F28 -> 7.0687168 | G36: =G20+G28 -> 3.692936 | H36: =H20+H28 -> -6.2608945 | I36: =I20+I28 -> 13.434812 | J36: =J20+J28 -> 7.8773285 | ... W36: =W20+W28 -> -26.214806 | Y36: =SUM(B36:W36) -> 181.06082 | Z36: =Y36/$X$1 -> 8.6219439
A37: Debt | B37: =SUMIF(Breakup!$B$58:$L$68,Quarterly!$A37,Breakup!C$58:C$68) -> 0 | C37: =C21+C29 -> 3.489 | D37: =D21+D29 -> 1.32956 | E37: =E21+E29 -> 2.37028 | F37: =F21+F29 -> 0.8449 | G37: =G21+G29 -> 3.7474 | H37: =H21+H29 -> 0.9854 | I37: =I21+I29 -> 2.564294 | J37: =J21+J29 -> 1.256196 | ... W37: =W21+W29 -> 6.76031 | Y37: =SUM(B37:W37) -> 56.082486 | Z37: =Y37/$X$1 -> 2.6705946
A38: Gold | B38: =SUMIF(Breakup!$B$58:$L$68,Quarterly!$A38,Breakup!C$58:C$68) -> 0 | C38: =C22+C30 -> 0.1650255 | D38: =D22+D30 -> 0.0300745 | E38: =E22+E30 -> -0.02175 | F38: =F22+F30 -> 0.00865 | G38: =G22+G30 -> 0.00255 | H38: =H22+H30 -> 0.02645 | I38: =I22+I30 -> 0.0052 | J38: =J22+J30 -> 0.079937 | ... W38: =W22+W30 -> 0.10505 | Y38: =SUM(B38:W38) -> 4.054594 | Z38: =Y38/$X$1 -> 0.1930759
A39: Alternate | B39: =SUMIF(Breakup!$B$58:$L$68,Quarterly!$A39,Breakup!C$58:C$68) -> 0 | C39: =C23+C31 -> 0 | D39: =D23+D31 -> 0 | E39: =E23+E31 -> 0.64485 | F39: =F23+F31 -> -0.54 | G39: =G23+G31 -> 0 | H39: =H23+H31 -> 0 | I39: =I23+I31 -> 0 | J39: =J23+J31 -> 0 | ... W39: =W23+W31 -> 0 | Y39: =SUM(B39:W39) -> 0.10485 | Z39: =Y39/$X$1 -> 0.0049928571
A40: Liquid | B40: =SUMIF(Breakup!$B$58:$L$68,Quarterly!$A40,Breakup!C$58:C$68) -> 0 | C40: =C24+C32 -> -3.6464984 | D40: =D24+D32 -> 2.5256122 | E40: =E24+E32 -> 0.81967358 | F40: =F24+F32 -> -1.4912217 | G40: =G24+G32 -> -1.5097047 | H40: =H24+H32 -> -1.347861 | I40: =I24+I32 -> 2.5 | J40: =J24+J32 -> -1 | ... W40: =W24+W32 -> 0 | Y40: =SUM(B40:W40) -> -4.65 | Z40: =Y40/$X$1 -> -0.22142857
A41: Total | B41: =SUM(B36:B40) -> 0 | C41: =C25+C33 -> 9.7234939 | D41: =D25+D33 -> 12.876612 | E41: =E25+E33 -> 17.386879 | F41: =F25+F33 -> 5.891045 | G41: =G25+G33 -> 5.9331813 | H41: =H25+H33 -> -6.5969055 | I41: =I25+I33 -> 18.504306 | J41: =J25+J33 -> 8.2134615 | ... W41: =W25+W33 -> -19.349446 | Y41: =SUM(B41:W41) -> 236.65275 | Z41: =Y41/$X$1 -> 11.269179
A42: % Change | C42: =C41/B9 -> 0.11561742 | D42: =D41/C9 -> 0.13724207 | E42: =E41/D9 -> 0.16294999 | F42: =F41/E9 -> 0.047515045 | G42: =G41/F9 -> 0.045684214 | H42: =H41/G9 -> -0.048575608 | I42: =I41/H9 -> 0.14321104 | J42: =J41/I9 -> 0.055603678 | ... W42: =W41/V9 -> -0.056908629
A44: % RETURNS
A45: Equity | C45: =C28/(B4) -> 0.1188921 | D45: =D28/(C4) -> 0.11487708 | E45: =E28/(D4) -> 0.11424512 | F45: =F28/(E4) -> 0.0028553337 | G45: =G28/(F4) -> -0.020845258 | H45: =H28/(G4) -> -0.092576377 | I45: =I28/(H4) -> 0.10219122 | J45: =J28/(I4) -> 0.0047252855 | ... W45: =W28/(V4) -> -0.11373189 | X45: =AVERAGE(C45:W45)*4 -> 0.14901256
A46: Debt | C46: =C29/(B5) -> 0.079588073 | D46: =D29/(C5) -> 0.017590716 | E46: =E29/(D5) -> 0.00057298059 | F46: =F29/(E5) -> 0.00047836241 | G46: =G29/(F5) -> 0.0717636 | H46: =H29/(G5) -> 0.0035995463 | I46: =I29/(H5) -> 0.0015232952 | J46: =J29/(I5) -> 0.00078561105 | ... W46: =W29/(V5) -> 0.065171254 | X46: =AVERAGE(C46:W46)*4 -> 0.090892235
A47: Gold | C47: =C30/(B6) -> -0.0824745 | D47: =D30/(C6) -> 0.025814456 | E47: =E30/(D6) -> -0.018199314 | F47: =F30/(E6) -> 0.0073720544 | G47: =G30/(F6) -> 0.018824027 | H47: =H30/(G6) -> 0 | I47: =I30/(H6) -> 0.0056069364 | J47: =J30/(I6) -> 0.065726854 | ... W47: =W30/(V6) -> 0.021224177 | X47: =AVERAGE(C47:W47)*4 -> 0.22971161
A48: Alternate | C48: 0 | D48: 0 | E48: 0 | F48: =F31/(E7) -> 0.35185185 | G48: 0 | H48: 0 | I48: 0 | J48: 0 | K48: 0 | L48: 0 | M48: 0 | X48: 0
A49: Liquid | C49: =C32/(B8) -> 0 | D49: =D32/(C8) -> 0 | E49: =E32/(D8) -> 0 | F49: =F32/(E8) -> 0 | G49: =G32/(F8) -> 0 | H49: 0 | I49: 0 | J49: 0 | K49: =K32/(J8) -> 0 | L49: =L32/(K8) -> 0 | M49: 0 | X49: 0
A50: Total | C50: =C33/(B9) -> 0.094721346 | D50: =D33/(C9) -> 0.075194337 | E50: =E33/(D9) -> 0.07017691 | F50: =F33/(E9) -> 0.00355648 | G50: =G33/(F9) -> 0.0088991416 | H50: =H33/(G9) -> -0.05946978 | I50: =I33/(H9) -> 0.065995332 | J50: =J33/(I9) -> 0.0038710746 | ... X50: =X33/(W9) -> 0

Sheet Monthly
A1: Month | B1: 2021-01 | C1: 2021-02 | D1: 2021-03 | E1: 2021-04 | F1: 2021-05 | G1: 2021-06 | H1: 2021-07 | I1: 2021-08 | J1: 2021-09 | K1: 2021-10 | L1: 2021-11 | M1: 2021-12 | N1: 2022-01 | O1: 2022-02 | P1: 2022-03 | Q1: 2022-04 | R1: 2022-05 | S1: 2022-06 | T1: 2022-07 | U1: 2022-08 | V1: 2022-09 | W1: 2022-10 | X1: 2022-11 | Y1: 2022-12 | Z1: 2023-01 | AA1: 2023-02 | AB1: 2023-03 | AC1: 2023-04 | AD1: 2023-05 | AE1: 2023-06 | AF1: 2023-07 | AG1: 2023-08 | AH1: 2023-09 | AI1: 2023-10 | AJ1: 2023-11 | AK1: 2023-12 | AL1: 2024-01 | AM1: 2024-02 | AN1: 2024-03 | AO1: 2024-04 | AP1: 2024-05 | AQ1: 2024-06 | AR1: 2024-07 | AS1: 2024-08 | AT1: 2024-09 | AU1: 2024-10 | AV1: 2024-11 | AW1: 2024-12 | AX1: 2025-01 | AY1: 2025-02 | AZ1: 2025-03 | BA1: 2025-04 | BB1: 2025-05 | BC1: 2025-06 | BD1: 2025-07 | BE1: 2025-08 | BF1: 2025-09 | BG1: 2025-10 | BH1: 2025-11 | BI1: 2025-12 | BJ1: 2026-01 | BK1: 2026-02 | BL1: 2026-03 | BM1: 2026-04 | BN1: 2026-05 | BO1: =COUNTA($B1:BN1)-1 -> 64
B2: Value (L) | C2: Value (L) | D2: Value (L) | E2: Value (L) | F2: Value (L) | G2: Value (L) | H2: Value (L) | I2: Value (L) | J2: Value (L) | K2: Value (L) | L2: Value (L) | M2: Value (L) | N2: Value (L) | O2: Value (L) | P2: Value (L) | Q2: Value (L) | R2: Value (L) | S2: Value (L) | T2: Value (L) | U2: Value (L) | V2: Value (L) | W2: Value (L) | X2: Value (L) | Y2: Value (L) | Z2: Value (L) | AA2: Value (L) | AB2: Value (L) | AC2: Value (L) | AD2: Value (L) | AE2: Value (L) | AF2: Value (L) | AG2: Value (L) | AH2: Value (L) | AI2: Value (L) | AJ2: Value (L) | AK2: Value (L) | AL2: Value (L) | AM2: Value (L) | AN2: Value (L) | AO2: Value (L) | AP2: Value (L) | AQ2: Value (L) | AR2: Value (L) | AS2: Value (L) | AT2: Value (L) | AU2: Value (L) | AV2: Value (L) | AW2: Value (L) | AX2: Value (L) | AY2: Value (L) | AZ2: Value (L) | BA2: Value (L) | BB2: Value (L) | BC2: Value (L) | BD2: Value (L) | BE2: Value (L) | BF2: Value (L) | BG2: Value (L) | BH2: Value (L) | BI2: Value (L) | BJ2: Value (L) | BK2: Value (L) | BL2: Value (L) | BM2: Value (L) | BN2: Value (L) | BO2: CAGR | BP2: TOTAL | BQ2: AVERAGE
A3: NET WORTH
A4: Equity | B4: =SUMIF(Breakup!$B$4:$C$14,Monthly!$A4,Breakup!$C$4:$C$14) -> 45.920595 | C4: =SUMIF(Breakup!$B$4:D$14,Monthly!$A4,Breakup!D$4:D$14) -> 49.854466 | D4: =SUMIF(Breakup!$B$4:E$14,Monthly!$A4,Breakup!E$4:E$14) -> 54.495787 | E4: =SUMIF(Breakup!$B$4:F$14,Monthly!$A4,Breakup!F$4:F$14) -> 55.636562 | F4: =SUMIF(Breakup!$B$4:G$14,Monthly!$A4,Breakup!G$4:G$14) -> 54.207659 | G4: =SUMIF(Breakup!$B$4:H$14,Monthly!$A4,Breakup!H$4:H$14) -> 60.628057 | H4: =SUMIF(Breakup!$B$4:$L$14,Monthly!$A4,Breakup!$I$4:$I$14) -> 64.627927 | I4: =SUMIF(Breakup!$B$4:$L$14,Monthly!$A4,Breakup!$J$4:$J$14) -> 68.497238 | J4: =SUMIF(Breakup!$B$4:$L$14,Monthly!$A4,Breakup!$K$4:$K$14) -> 74.895077 | K4: =SUMIF(Breakup!$B$4:$L$14,Monthly!$A4,Breakup!L$4:L$14) -> 78.201752 | L4: =SUMIF(Breakup!$B$4:M$14,Monthly!$A4,Breakup!M$4:M$14) -> 80.991219 | M4: =SUMIF(Breakup!$B$4:N$14,Monthly!$A4,Breakup!N$4:N$14) -> 82.479767 | N4: =SUMIF(Breakup!$B$4:O$14,Monthly!$A4,Breakup!O$4:O$14) -> 85.270469 | O4: =SUMIF(Breakup!$B$4:P$14,Monthly!$A4,Breakup!P$4:P$14) -> 87.990961 | P4: =SUMIF(Breakup!$B$4:Q$14,Monthly!$A4,Breakup!Q$4:Q$14) -> 81.655621 | Q4: =SUMIF(Breakup!$B$4:R$14,Monthly!$A4,Breakup!R$4:R$14) -> 88.963405 | R4: =SUMIF(Breakup!$B$4:S$14,Monthly!$A4,Breakup!S$4:S$14) -> 88.984977 | S4: =SUMIF(Breakup!$B$4:T$14,Monthly!$A4,Breakup!T$4:T$14) -> 85.39092 | ... BN4: =SUMIF(Breakup!$B$4:BO$14,Monthly!$A4,Breakup!BO$4:BO$14) -> 252.65671 | BO4: =((BN4/B4)^(12/$BO$1)-1) -> 0.37672793
A5: Debt | B5: =SUMIF(Breakup!$B$4:$C$14,Monthly!$A5,Breakup!$C$4:$C$14) -> 32.53 | C5: =SUMIF(Breakup!$B$4:D$14,Monthly!$A5,Breakup!D$4:D$14) -> 32.998 | D5: =SUMIF(Breakup!$B$4:E$14,Monthly!$A5,Breakup!E$4:E$14) -> 33.43 | E5: =SUMIF(Breakup!$B$4:F$14,Monthly!$A5,Breakup!F$4:F$14) -> 36.019 | F5: =SUMIF(Breakup!$B$4:G$14,Monthly!$A5,Breakup!G$4:G$14) -> 36.8784 | G5: =SUMIF(Breakup!$B$4:H$14,Monthly!$A5,Breakup!H$4:H$14) -> 37.1199 | H5: =SUMIF(Breakup!$B$4:$L$14,Monthly!$A5,Breakup!$I$4:$I$14) -> 37.34856 | I5: =SUMIF(Breakup!$B$4:$L$14,Monthly!$A5,Breakup!$J$4:$J$14) -> 37.58785 | J5: =SUMIF(Breakup!$B$4:$L$14,Monthly!$A5,Breakup!$K$4:$K$14) -> 37.8518 | K5: =SUMIF(Breakup!$B$4:$L$14,Monthly!$A5,Breakup!L$4:L$14) -> 39.71884 | L5: =SUMIF(Breakup!$B$4:M$14,Monthly!$A5,Breakup!M$4:M$14) -> 39.98014 | M5: =SUMIF(Breakup!$B$4:N$14,Monthly!$A5,Breakup!N$4:N$14) -> 40.27544 | N5: =SUMIF(Breakup!$B$4:O$14,Monthly!$A5,Breakup!O$4:O$14) -> 40.56374 | O5: =SUMIF(Breakup!$B$4:P$14,Monthly!$A5,Breakup!P$4:P$14) -> 40.81904 | P5: =SUMIF(Breakup!$B$4:Q$14,Monthly!$A5,Breakup!Q$4:Q$14) -> 41.10534 | Q5: =SUMIF(Breakup!$B$4:R$14,Monthly!$A5,Breakup!R$4:R$14) -> 44.31114 | R5: =SUMIF(Breakup!$B$4:S$14,Monthly!$A5,Breakup!S$4:S$14) -> 44.76894 | S5: =SUMIF(Breakup!$B$4:T$14,Monthly!$A5,Breakup!T$4:T$14) -> 45.00424 | ... BN5: =SUMIF(Breakup!$B$4:BO$14,Monthly!$A5,Breakup!BO$4:BO$14) -> 89.82086 | BO5: =((BN5/B5)^(12/$BO$1)-1) -> 0.209776
A6: Gold | B6: =SUMIF(Breakup!$B$4:$C$14,Monthly!$A6,Breakup!$C$4:$C$14) -> 1 | C6: =SUMIF(Breakup!$B$4:D$14,Monthly!$A6,Breakup!D$4:D$14) -> 1.226364 | D6: =SUMIF(Breakup!$B$4:E$14,Monthly!$A6,Breakup!E$4:E$14) -> 1.179125 | E6: =SUMIF(Breakup!$B$4:F$14,Monthly!$A6,Breakup!F$4:F$14) -> 1.1650255 | F6: =SUMIF(Breakup!$B$4:G$14,Monthly!$A6,Breakup!G$4:G$14) -> 1.19255 | G6: =SUMIF(Breakup!$B$4:H$14,Monthly!$A6,Breakup!H$4:H$14) -> 1.2122535 | H6: =SUMIF(Breakup!$B$4:$L$14,Monthly!$A6,Breakup!$I$4:$I$14) -> 1.1951 | I6: =SUMIF(Breakup!$B$4:$L$14,Monthly!$A6,Breakup!$J$4:$J$14) -> 1.1909635 | J6: =SUMIF(Breakup!$B$4:$L$14,Monthly!$A6,Breakup!$K$4:$K$14) -> 1.177498 | K6: =SUMIF(Breakup!$B$4:$L$14,Monthly!$A6,Breakup!L$4:L$14) -> 1.17335 | L6: =SUMIF(Breakup!$B$4:M$14,Monthly!$A6,Breakup!M$4:M$14) -> 1.1836 | M6: =SUMIF(Breakup!$B$4:N$14,Monthly!$A6,Breakup!N$4:N$14) -> 1.187 | N6: =SUMIF(Breakup!$B$4:O$14,Monthly!$A6,Breakup!O$4:O$14) -> 1.182 | O6: =SUMIF(Breakup!$B$4:P$14,Monthly!$A6,Breakup!P$4:P$14) -> 1.17315 | P6: =SUMIF(Breakup!$B$4:Q$14,Monthly!$A6,Breakup!Q$4:Q$14) -> 1.20425 | Q6: =SUMIF(Breakup!$B$4:R$14,Monthly!$A6,Breakup!R$4:R$14) -> 1.18455 | R6: =SUMIF(Breakup!$B$4:S$14,Monthly!$A6,Breakup!S$4:S$14) -> 1.2309 | S6: =SUMIF(Breakup!$B$4:T$14,Monthly!$A6,Breakup!T$4:T$14) -> 1.1956 | ... BN6: =SUMIF(Breakup!$B$4:BO$14,Monthly!$A6,Breakup!BO$4:BO$14) -> 5.1860555 | BO6: =((BN6/B6)^(12/$BO$1)-1) -> 0.3615449
A7: Alternate | B7: =SUMIF(Breakup!$B$4:$C$14,Monthly!$A7,Breakup!$C$4:$C$14) -> 0 | C7: =SUMIF(Breakup!$B$4:D$14,Monthly!$A7,Breakup!D$4:D$14) -> 0 | D7: =SUMIF(Breakup!$B$4:E$14,Monthly!$A7,Breakup!E$4:E$14) -> 0 | E7: =SUMIF(Breakup!$B$4:F$14,Monthly!$A7,Breakup!F$4:F$14) -> 0 | F7: =SUMIF(Breakup!$B$4:G$14,Monthly!$A7,Breakup!G$4:G$14) -> 0 | G7: =SUMIF(Breakup!$B$4:H$14,Monthly!$A7,Breakup!H$4:H$14) -> 0 | H7: =SUMIF(Breakup!$B$4:$L$14,Monthly!$A7,Breakup!$I$4:$I$14) -> 0 | I7: =SUMIF(Breakup!$B$4:$L$14,Monthly!$A7,Breakup!$J$4:$J$14) -> 0 | J7: =SUMIF(Breakup!$B$4:$L$14,Monthly!$A7,Breakup!$K$4:$K$14) -> 0.10485 | K7: =SUMIF(Breakup!$B$4:$L$14,Monthly!$A7,Breakup!L$4:L$14) -> 0.54 | L7: =SUMIF(Breakup!$B$4:M$14,Monthly!$A7,Breakup!M$4:M$14) -> 0.73 | M7: =SUMIF(Breakup!$B$4:N$14,Monthly!$A7,Breakup!N$4:N$14) -> 0 | N7: =SUMIF(Breakup!$B$4:O$14,Monthly!$A7,Breakup!O$4:O$14) -> 0 | O7: =SUMIF(Breakup!$B$4:P$14,Monthly!$A7,Breakup!P$4:P$14) -> 0 | P7: =SUMIF(Breakup!$B$4:Q$14,Monthly!$A7,Breakup!Q$4:Q$14) -> 0 | Q7: =SUMIF(Breakup!$B$4:R$14,Monthly!$A7,Breakup!R$4:R$14) -> 0 | R7: =SUMIF(Breakup!$B$4:S$14,Monthly!$A7,Breakup!S$4:S$14) -> 0 | S7: =SUMIF(Breakup!$B$4:T$14,Monthly!$A7,Breakup!T$4:T$14) -> 0 | ... BN7: =SUMIF(Breakup!$B$4:BO$14,Monthly!$A7,Breakup!BO$4:BO$14) -> 0
A8: Liquid | B8: =SUMIF(Breakup!$B$4:$C$14,Monthly!$A8,Breakup!$C$4:$C$14) -> 4.65 | C8: =SUMIF(Breakup!$B$4:D$14,Monthly!$A8,Breakup!D$4:D$14) -> 3.2 | D8: =SUMIF(Breakup!$B$4:E$14,Monthly!$A8,Breakup!E$4:E$14) -> 1 | E8: =SUMIF(Breakup!$B$4:F$14,Monthly!$A8,Breakup!F$4:F$14) -> 1.0035016 | F8: =SUMIF(Breakup!$B$4:G$14,Monthly!$A8,Breakup!G$4:G$14) -> 3.5108187 | G8: =SUMIF(Breakup!$B$4:H$14,Monthly!$A8,Breakup!H$4:H$14) -> 3.5198853 | H8: =SUMIF(Breakup!$B$4:$L$14,Monthly!$A8,Breakup!$I$4:$I$14) -> 3.5291139 | I8: =SUMIF(Breakup!$B$4:$L$14,Monthly!$A8,Breakup!$J$4:$J$14) -> 2.538389 | J8: =SUMIF(Breakup!$B$4:$L$14,Monthly!$A8,Breakup!$K$4:$K$14) -> 2.0454896 | K8: =SUMIF(Breakup!$B$4:$L$14,Monthly!$A8,Breakup!L$4:L$14) -> 4.3487874 | L8: =SUMIF(Breakup!$B$4:M$14,Monthly!$A8,Breakup!M$4:M$14) -> 3.3509365 | M8: =SUMIF(Breakup!$B$4:N$14,Monthly!$A8,Breakup!N$4:N$14) -> 2.3510604 | N8: =SUMIF(Breakup!$B$4:O$14,Monthly!$A8,Breakup!O$4:O$14) -> 2.8575657 | O8: =SUMIF(Breakup!$B$4:P$14,Monthly!$A8,Breakup!P$4:P$14) -> 2.3574783 | P8: =SUMIF(Breakup!$B$4:Q$14,Monthly!$A8,Breakup!Q$4:Q$14) -> 1.3439699 | Q8: =SUMIF(Breakup!$B$4:R$14,Monthly!$A8,Breakup!R$4:R$14) -> 1.347861 | R8: =SUMIF(Breakup!$B$4:S$14,Monthly!$A8,Breakup!S$4:S$14) -> 1.3516378 | S8: =SUMIF(Breakup!$B$4:T$14,Monthly!$A8,Breakup!T$4:T$14) -> 3.2196e-05 | ... BN8: =SUMIF(Breakup!$B$4:BO$14,Monthly!$A8,Breakup!BO$4:BO$14) -> 0
A9: Total | B9: =SUM(B4:B8) -> 84.100595 | C9: =SUM(C4:C8) -> 87.27883 | D9: =SUM(D4:D8) -> 90.104912 | E9: =SUM(E4:E8) -> 93.824089 | F9: =SUM(F4:F8) -> 95.789428 | G9: =SUM(G4:G8) -> 102.4801 | H9: =SUM(H4:H8) -> 106.7007 | I9: =SUM(I4:I8) -> 109.81444 | ... BN9: =SUM(BN4:BN8) -> 347.66362 | BO9: =((BN9/B9)^(12/$BO$1)-1) -> 0.30487087
A11: CONTRIBUTION
A12: Equity | B12: =B4/B$9 -> 0.54601986 | C12: =C4/C$9 -> 0.57120915 | D12: =D4/D$9 -> 0.60480373 | E12: =E4/E$9 -> 0.59298803 | F12: =F4/F$9 -> 0.5659044 | G12: =G4/G$9 -> 0.59160812 | H12: =H4/H$9 -> 0.60569356 | I12: =I4/I$9 -> 0.62375438 | ... BN12: =BN4/BN$9 -> 0.72672748
A13: Debt | B13: =B5/B$9 -> 0.38679869 | C13: =C5/C$9 -> 0.37807564 | D13: =D5/D$9 -> 0.37101196 | E13: =E5/E$9 -> 0.38389928 | F13: =F5/F$9 -> 0.38499447 | G13: =G5/G$9 -> 0.3622157 | H13: =H5/H$9 -> 0.35003106 | I13: =I5/I$9 -> 0.34228513 | ... BN13: =BN5/BN$9 -> 0.25835565
A14: Gold | B14: =B6/B$9 -> 0.011890522 | C14: =C6/C$9 -> 0.014051105 | D14: =D6/D$9 -> 0.013086135 | E14: =E6/E$9 -> 0.012417126 | F14: =F6/F$9 -> 0.012449704 | G14: =G6/G$9 -> 0.01182916 | H14: =H6/H$9 -> 0.011200489 | I14: =I6/I$9 -> 0.010845236 | ... BN14: =BN6/BN$9 -> 0.014916877
A15: Alternate | B15: =B7/B$9 -> 0 | C15: =C7/C$9 -> 0 | D15: =D7/D$9 -> 0 | E15: =E7/E$9 -> 0 | F15: =F7/F$9 -> 0 | G15: =G7/G$9 -> 0 | H15: =H7/H$9 -> 0 | I15: =I7/I$9 -> 0 | ... BN15: =BN7/BN$9 -> 0
A16: Liquid | B16: =B8/B$9 -> 0.055290929 | C16: =C8/C$9 -> 0.036664103 | D16: =D8/D$9 -> 0.011098174 | E16: =E8/E$9 -> 0.010695565 | F16: =F8/F$9 -> 0.036651422 | G16: =G8/G$9 -> 0.034347014 | H16: =H8/H$9 -> 0.033074889 | I16: =I8/I$9 -> 0.023115257 | ... BN16: =BN8/BN$9 -> 0
A17: Total | B17: =SUM(B12:B16) -> 1 | C17: =SUM(C12:C16) -> 1 | D17: =SUM(D12:D16) -> 1 | E17: =SUM(E12:E16) -> 1 | F17: =SUM(F12:F16) -> 1 | G17: =SUM(G12:G16) -> 1 | H17: =SUM(H12:H16) -> 1 | I17: =SUM(I12:I16) -> 1 | ... BN17: =SUM(BN12:BN16) -> 1
A19: NEW INVESTMENT
A20: Equity | B20: =SUMIF(Breakup!$B$30:$L$40,Monthly!$A20,Breakup!C$30:C$40) -> 0 | C20: =SUMIF(Breakup!$B$30:$L$40,Monthly!$A20,Breakup!D$30:D$40) -> 1.8463708 | D20: =SUMIF(Breakup!$B$30:$L$40,Monthly!$A20,Breakup!E$30:E$40) -> 0.41 | E20: =SUMIF(Breakup!$B$30:$L$40,Monthly!$A20,Breakup!F$30:F$40) -> 2 | F20: =SUMIF(Breakup!$B$30:$L$40,Monthly!$A20,Breakup!G$30:G$40) -> -1.73 | G20: =SUMIF(Breakup!$B$30:$L$40,Monthly!$A20,Breakup!H$30:H$40) -> 1.9 | H20: =SUMIF(Breakup!$B$30:$L$40,Monthly!$A20,Breakup!I$30:I$40) -> 2.43 | I20: =SUMIF(Breakup!$B$30:$L$40,Monthly!$A20,Breakup!J$30:J$40) -> 1.6 | ... K20: =SUMIF(Breakup!$B$30:$L$40,Monthly!$A20,Breakup!L$30:L$40) -> 2.1903996 | L20: =SUMIF(Breakup!$B$30:M$40,Monthly!$A20,Breakup!M$30:M$40) -> 2.0379246 | M20: =SUMIF(Breakup!$B$30:N$40,Monthly!$A20,Breakup!N$30:N$40) -> 2.7206581 | N20: =SUMIF(Breakup!$B$30:O$40,Monthly!$A20,Breakup!O$30:O$40) -> 2.086842 | O20: =SUMIF(Breakup!$B$30:P$40,Monthly!$A20,Breakup!P$30:P$40) -> 2.3892298 | P20: =SUMIF(Breakup!$B$30:Q$40,Monthly!$A20,Breakup!Q$30:Q$40) -> 1.2756248 | Q20: =SUMIF(Breakup!$B$30:R$40,Monthly!$A20,Breakup!R$30:R$40) -> 1.8055663 | R20: =SUMIF(Breakup!$B$30:S$40,Monthly!$A20,Breakup!S$30:S$40) -> 1.2465006 | S20: =SUMIF(Breakup!$B$30:T$40,Monthly!$A20,Breakup!T$30:T$40) -> 0.43181348 | ... U20: =SUMIF(Breakup!$B$30:V$40,Monthly!$A20,Breakup!V$30:V$40) -> 0.84336885 | V20: =SUMIF(Breakup!$B$30:BO$40,Monthly!$A20,Breakup!W$30:W$40) -> 1.34439 | W20: =SUMIF(Breakup!$B$30:BP$40,Monthly!$A20,Breakup!X$30:X$40) -> 2.7955833 | X20: =SUMIF(Breakup!$B$30:Y$40,Monthly!$A20,Breakup!Y$30:Y$40) -> 3.1684778 | Y20: =SUMIF(Breakup!$B$30:Z$40,Monthly!$A20,Breakup!Z$30:Z$40) -> 3.1684778 | Z20: =SUMIF(Breakup!$B$30:AA$40,Monthly!$A20,Breakup!AA$30:AA$40) -> 1.0860967 | AA20: =SUMIF(Breakup!$B$30:AB$40,Monthly!$A20,Breakup!AB$30:AB$40) -> 3.0482444 | AB20: =SUMIF(Breakup!$B$30:AC$40,Monthly!$A20,Breakup!AC$30:AC$40) -> 3.0482444 | AC20: =SUMIF(Breakup!$B$30:AD$40,Monthly!$A20,Breakup!AD$30:AD$40) -> 1.0771129 | AD20: =SUMIF(Breakup!$B$30:AE$40,Monthly!$A20,Breakup!AE$30:AE$40) -> 2.6104181 | AE20: =SUMIF(Breakup!$B$30:AF$40,Monthly!$A20,Breakup!AF$30:AF$40) -> 0.46110399 | ... BN20: =SUMIF(Breakup!$B$30:BO$40,Monthly!$A20,Breakup!BO$30:BO$40) -> 0.050001218 | BP20: =SUM(B20:BN20) -> 109.43943 | BQ20: =BP20/$BO$1 -> 1.709991
A21: Debt | B21: =SUMIF(Breakup!$B$30:$L$40,Monthly!$A21,Breakup!C$30:C$40) -> 0 | C21: =SUMIF(Breakup!$B$30:$L$40,Monthly!$A21,Breakup!D$30:D$40) -> 0.23 | D21: =SUMIF(Breakup!$B$30:$L$40,Monthly!$A21,Breakup!E$30:E$40) -> 0.47 | E21: =SUMIF(Breakup!$B$30:$L$40,Monthly!$A21,Breakup!F$30:F$40) -> 0.2 | F21: =SUMIF(Breakup!$B$30:$L$40,Monthly!$A21,Breakup!G$30:G$40) -> 0.23 | G21: =SUMIF(Breakup!$B$30:$L$40,Monthly!$A21,Breakup!H$30:H$40) -> 0.233 | H21: =SUMIF(Breakup!$B$30:$L$40,Monthly!$A21,Breakup!I$30:I$40) -> 0.23296 | I21: =SUMIF(Breakup!$B$30:$L$40,Monthly!$A21,Breakup!J$30:J$40) -> 0.23296 | ... K21: =SUMIF(Breakup!$B$30:$L$40,Monthly!$A21,Breakup!L$30:L$40) -> 1.88296 | L21: =SUMIF(Breakup!$B$30:M$40,Monthly!$A21,Breakup!M$30:M$40) -> 0.2753 | M21: =SUMIF(Breakup!$B$30:N$40,Monthly!$A21,Breakup!N$30:N$40) -> 0.2753 | N21: =SUMIF(Breakup!$B$30:O$40,Monthly!$A21,Breakup!O$30:O$40) -> 0.2753 | O21: =SUMIF(Breakup!$B$30:P$40,Monthly!$A21,Breakup!P$30:P$40) -> 0.2753 | P21: =SUMIF(Breakup!$B$30:Q$40,Monthly!$A21,Breakup!Q$30:Q$40) -> 0.2753 | Q21: =SUMIF(Breakup!$B$30:R$40,Monthly!$A21,Breakup!R$30:R$40) -> 0.2858 | R21: =SUMIF(Breakup!$B$30:S$40,Monthly!$A21,Breakup!S$30:S$40) -> 0.2753 | S21: =SUMIF(Breakup!$B$30:T$40,Monthly!$A21,Breakup!T$30:T$40) -> 0.2753 | ... U21: =SUMIF(Breakup!$B$30:V$40,Monthly!$A21,Breakup!V$30:V$40) -> 0.298304 | V21: =SUMIF(Breakup!$B$30:BO$40,Monthly!$A21,Breakup!W$30:W$40) -> 1.925446 | W21: =SUMIF(Breakup!$B$30:BP$40,Monthly!$A21,Breakup!X$30:X$40) -> 0.271544 | X21: =SUMIF(Breakup!$B$30:Y$40,Monthly!$A21,Breakup!Y$30:Y$40) -> 0.281408 | Y21: =SUMIF(Breakup!$B$30:Z$40,Monthly!$A21,Breakup!Z$30:Z$40) -> 0.618688 | Z21: =SUMIF(Breakup!$B$30:AA$40,Monthly!$A21,Breakup!AA$30:AA$40) -> 0.3185 | AA21: =SUMIF(Breakup!$B$30:AB$40,Monthly!$A21,Breakup!AB$30:AB$40) -> 0.3185 | AB21: =SUMIF(Breakup!$B$30:AC$40,Monthly!$A21,Breakup!AC$30:AC$40) -> 0.3185 | AC21: =SUMIF(Breakup!$B$30:AD$40,Monthly!$A21,Breakup!AD$30:AD$40) -> 0.3 | AD21: =SUMIF(Breakup!$B$30:AE$40,Monthly!$A21,Breakup!AE$30:AE$40) -> 0.3185 | AE21: =SUMIF(Breakup!$B$30:AF$40,Monthly!$A21,Breakup!AF$30:AF$40) -> 0.3185 | ... BN21: =SUMIF(Breakup!$B$30:BO$40,Monthly!$A21,Breakup!BO$30:BO$40) -> 0.47506 | BP21: =SUM(B21:BN21) -> 30.68847 | BQ21: =BP21/$BO$1 -> 0.47950734
A22: Gold | B22: =SUMIF(Breakup!$B$30:$L$40,Monthly!$A22,Breakup!C$30:C$40) -> 0 | C22: =SUMIF(Breakup!$B$30:$L$40,Monthly!$A22,Breakup!D$30:D$40) -> 0.2475 | D22: =SUMIF(Breakup!$B$30:$L$40,Monthly!$A22,Breakup!E$30:E$40) -> 0 | E22: =SUMIF(Breakup!$B$30:$L$40,Monthly!$A22,Breakup!F$30:F$40) -> 0 | F22: =SUMIF(Breakup!$B$30:$L$40,Monthly!$A22,Breakup!G$30:G$40) -> 0 | G22: =SUMIF(Breakup!$B$30:$L$40,Monthly!$A22,Breakup!H$30:H$40) -> 0 | H22: =SUMIF(Breakup!$B$30:$L$40,Monthly!$A22,Breakup!I$30:I$40) -> 0 | I22: =SUMIF(Breakup!$B$30:$L$40,Monthly!$A22,Breakup!J$30:J$40) -> 0 | ... K22: =SUMIF(Breakup!$B$30:$L$40,Monthly!$A22,Breakup!L$30:L$40) -> 0 | L22: =SUMIF(Breakup!$B$30:M$40,Monthly!$A22,Breakup!M$30:M$40) -> 0 | M22: =SUMIF(Breakup!$B$30:N$40,Monthly!$A22,Breakup!N$30:N$40) -> 0 | N22: =SUMIF(Breakup!$B$30:O$40,Monthly!$A22,Breakup!O$30:O$40) -> 0 | O22: =SUMIF(Breakup!$B$30:P$40,Monthly!$A22,Breakup!P$30:P$40) -> 0 | P22: =SUMIF(Breakup!$B$30:Q$40,Monthly!$A22,Breakup!Q$30:Q$40) -> 0 | Q22: =SUMIF(Breakup!$B$30:R$40,Monthly!$A22,Breakup!R$30:R$40) -> -0.0197 | R22: =SUMIF(Breakup!$B$30:S$40,Monthly!$A22,Breakup!S$30:S$40) -> 0.04635 | S22: =SUMIF(Breakup!$B$30:T$40,Monthly!$A22,Breakup!T$30:T$40) -> -0.0353 | ... U22: =SUMIF(Breakup!$B$30:V$40,Monthly!$A22,Breakup!V$30:V$40) -> -0.00159 | V22: =SUMIF(Breakup!$B$30:BO$40,Monthly!$A22,Breakup!W$30:W$40) -> 0 | W22: =SUMIF(Breakup!$B$30:BP$40,Monthly!$A22,Breakup!X$30:X$40) -> 0 | X22: =SUMIF(Breakup!$B$30:Y$40,Monthly!$A22,Breakup!Y$30:Y$40) -> 0 | Y22: =SUMIF(Breakup!$B$30:Z$40,Monthly!$A22,Breakup!Z$30:Z$40) -> 0 | Z22: =SUMIF(Breakup!$B$30:AA$40,Monthly!$A22,Breakup!AA$30:AA$40) -> 0 | AA22: =SUMIF(Breakup!$B$30:AB$40,Monthly!$A22,Breakup!AB$30:AB$40) -> 0 | AB22: =SUMIF(Breakup!$B$30:AC$40,Monthly!$A22,Breakup!AC$30:AC$40) -> 0 | AC22: =SUMIF(Breakup!$B$30:AD$40,Monthly!$A22,Breakup!AD$30:AD$40) -> 0 | AD22: =SUMIF(Breakup!$B$30:AE$40,Monthly!$A22,Breakup!AE$30:AE$40) -> 0 | AE22: =SUMIF(Breakup!$B$30:AF$40,Monthly!$A22,Breakup!AF$30:AF$40) -> 0 | ... BN22: =SUMIF(Breakup!$B$30:BO$40,Monthly!$A22,Breakup!BO$30:BO$40) -> 0 | BP22: =SUM(B22:BN22) -> 1.25266 | BQ22: =BP22/$BO$1 -> 0.019572813
A23: Alternate | B23: =SUMIF(Breakup!$B$30:$L$40,Monthly!$A23,Breakup!C$30:C$40) -> 0 | C23: =SUMIF(Breakup!$B$30:$L$40,Monthly!$A23,Breakup!D$30:D$40) -> 0 | D23: =SUMIF(Breakup!$B$30:$L$40,Monthly!$A23,Breakup!E$30:E$40) -> 0 | E23: =SUMIF(Breakup!$B$30:$L$40,Monthly!$A23,Breakup!F$30:F$40) -> 0 | F23: =SUMIF(Breakup!$B$30:$L$40,Monthly!$A23,Breakup!G$30:G$40) -> 0 | G23: =SUMIF(Breakup!$B$30:$L$40,Monthly!$A23,Breakup!H$30:H$40) -> 0 | H23: =SUMIF(Breakup!$B$30:$L$40,Monthly!$A23,Breakup!I$30:I$40) -> 0 | I23: =SUMIF(Breakup!$B$30:$L$40,Monthly!$A23,Breakup!J$30:J$40) -> 0 | ... K23: =SUMIF(Breakup!$B$30:$L$40,Monthly!$A23,Breakup!L$30:L$40) -> 0.43515 | L23: =SUMIF(Breakup!$B$30:M$40,Monthly!$A23,Breakup!M$30:M$40) -> 0 | M23: =SUMIF(Breakup!$B$30:N$40,Monthly!$A23,Breakup!N$30:N$40) -> -0.73 | N23: =SUMIF(Breakup!$B$30:O$40,Monthly!$A23,Breakup!O$30:O$40) -> 0 | O23: =SUMIF(Breakup!$B$30:P$40,Monthly!$A23,Breakup!P$30:P$40) -> 0 | P23: =SUMIF(Breakup!$B$30:Q$40,Monthly!$A23,Breakup!Q$30:Q$40) -> 0 | Q23: =SUMIF(Breakup!$B$30:R$40,Monthly!$A23,Breakup!R$30:R$40) -> 0 | R23: =SUMIF(Breakup!$B$30:S$40,Monthly!$A23,Breakup!S$30:S$40) -> 0 | S23: =SUMIF(Breakup!$B$30:T$40,Monthly!$A23,Breakup!T$30:T$40) -> 0 | ... U23: =SUMIF(Breakup!$B$30:V$40,Monthly!$A23,Breakup!V$30:V$40) -> 0 | V23: =SUMIF(Breakup!$B$30:BO$40,Monthly!$A23,Breakup!W$30:W$40) -> 0 | W23: =SUMIF(Breakup!$B$30:BP$40,Monthly!$A23,Breakup!X$30:X$40) -> 0 | X23: =SUMIF(Breakup!$B$30:Y$40,Monthly!$A23,Breakup!Y$30:Y$40) -> 0 | Y23: =SUMIF(Breakup!$B$30:Z$40,Monthly!$A23,Breakup!Z$30:Z$40) -> 0 | Z23: =SUMIF(Breakup!$B$30:AA$40,Monthly!$A23,Breakup!AA$30:AA$40) -> 0 | AA23: =SUMIF(Breakup!$B$30:AB$40,Monthly!$A23,Breakup!AB$30:AB$40) -> 0 | AB23: =SUMIF(Breakup!$B$30:AC$40,Monthly!$A23,Breakup!AC$30:AC$40) -> 0 | AC23: =SUMIF(Breakup!$B$30:AD$40,Monthly!$A23,Breakup!AD$30:AD$40) -> 0 | AD23: =SUMIF(Breakup!$B$30:AE$40,Monthly!$A23,Breakup!AE$30:AE$40) -> 0 | AE23: =SUMIF(Breakup!$B$30:AF$40,Monthly!$A23,Breakup!AF$30:AF$40) -> 0 | ... BN23: =SUMIF(Breakup!$B$30:BO$40,Monthly!$A23,Breakup!BO$30:BO$40) -> 0 | BP23: =SUM(B23:BN23) -> -0.19 | BQ23: =BP23/$BO$1 -> -0.00296875
A24: Liquid | B24: =SUMIF(Breakup!$B$30:$L$40,Monthly!$A24,Breakup!C$30:C$40) -> 0 | C24: =SUMIF(Breakup!$B$30:$L$40,Monthly!$A24,Breakup!D$30:D$40) -> -1.45 | D24: =SUMIF(Breakup!$B$30:$L$40,Monthly!$A24,Breakup!E$30:E$40) -> -2.2 | E24: =SUMIF(Breakup!$B$30:$L$40,Monthly!$A24,Breakup!F$30:F$40) -> 0.003501614 | F24: =SUMIF(Breakup!$B$30:$L$40,Monthly!$A24,Breakup!G$30:G$40) -> 2.5073171 | G24: =SUMIF(Breakup!$B$30:$L$40,Monthly!$A24,Breakup!H$30:H$40) -> 0.009066541 | H24: =SUMIF(Breakup!$B$30:$L$40,Monthly!$A24,Breakup!I$30:I$40) -> 0.009228589 | I24: =SUMIF(Breakup!$B$30:$L$40,Monthly!$A24,Breakup!J$30:J$40) -> -0.99072487 | ... K24: =SUMIF(Breakup!$B$30:$L$40,Monthly!$A24,Breakup!L$30:L$40) -> 2.3032978 | L24: =SUMIF(Breakup!$B$30:M$40,Monthly!$A24,Breakup!M$30:M$40) -> -0.99785091 | M24: =SUMIF(Breakup!$B$30:N$40,Monthly!$A24,Breakup!N$30:N$40) -> -0.99987614 | N24: =SUMIF(Breakup!$B$30:O$40,Monthly!$A24,Breakup!O$30:O$40) -> 0.50650531 | O24: =SUMIF(Breakup!$B$30:P$40,Monthly!$A24,Breakup!P$30:P$40) -> -0.50008737 | P24: =SUMIF(Breakup!$B$30:Q$40,Monthly!$A24,Breakup!Q$30:Q$40) -> -1.0135085 | Q24: =SUMIF(Breakup!$B$30:R$40,Monthly!$A24,Breakup!R$30:R$40) -> 0.003891126 | R24: =SUMIF(Breakup!$B$30:S$40,Monthly!$A24,Breakup!S$30:S$40) -> 0.003776786 | S24: =SUMIF(Breakup!$B$30:T$40,Monthly!$A24,Breakup!T$30:T$40) -> -1.3516056 | ... U24: =SUMIF(Breakup!$B$30:V$40,Monthly!$A24,Breakup!V$30:V$40) -> 0 | V24: =SUMIF(Breakup!$B$30:BO$40,Monthly!$A24,Breakup!W$30:W$40) -> 4 | W24: =SUMIF(Breakup!$B$30:BP$40,Monthly!$A24,Breakup!X$30:X$40) -> -1.5 | X24: =SUMIF(Breakup!$B$30:Y$40,Monthly!$A24,Breakup!Y$30:Y$40) -> -2.5 | Y24: =SUMIF(Breakup!$B$30:Z$40,Monthly!$A24,Breakup!Z$30:Z$40) -> 0 | Z24: =SUMIF(Breakup!$B$30:AA$40,Monthly!$A24,Breakup!AA$30:AA$40) -> 1.5 | AA24: =SUMIF(Breakup!$B$30:AB$40,Monthly!$A24,Breakup!AB$30:AB$40) -> 0 | AB24: =SUMIF(Breakup!$B$30:AC$40,Monthly!$A24,Breakup!AC$30:AC$40) -> 0 | AC24: =SUMIF(Breakup!$B$30:AD$40,Monthly!$A24,Breakup!AD$30:AD$40) -> 1.5 | AD24: =SUMIF(Breakup!$B$30:AE$40,Monthly!$A24,Breakup!AE$30:AE$40) -> -1 | AE24: =SUMIF(Breakup!$B$30:AF$40,Monthly!$A24,Breakup!AF$30:AF$40) -> -1 | ... BN24: =SUMIF(Breakup!$B$30:BO$40,Monthly!$A24,Breakup!BO$30:BO$40) -> 0 | BP24: =SUM(B24:BN24) -> -4.65 | BQ24: =BP24/$BO$1 -> -0.07265625
A25: Total | B25: =SUM(B20:B24) -> 0 | C25: =SUM(C20:C24) -> 0.87387083 | D25: =SUM(D20:D24) -> -1.32 | E25: =SUM(E20:E24) -> 2.2035016 | F25: =SUM(F20:F24) -> 1.0073171 | G25: =SUM(G20:G24) -> 2.1420665 | H25: =SUM(H20:H24) -> 2.6721886 | I25: =SUM(I20:I24) -> 0.84223513 | ... BN25: =SUM(BN20:BN24) -> 0.52506122 | BP25: =SUM(B25:BN25) -> 136.54056 | BQ25: =BP25/$BO$1 -> 2.1334462
A27: RETURNS
A28: Equity | B28: =SUMIF(Breakup!$B$44:$L$54,Monthly!$A28,Breakup!C$44:C$54) -> 0 | C28: =SUMIF(Breakup!$B$44:$L$54,Monthly!$A28,Breakup!D$44:D$54) -> 2.0875006 | D28: =SUMIF(Breakup!$B$44:$L$54,Monthly!$A28,Breakup!E$44:E$54) -> 4.2313206 | E28: =SUMIF(Breakup!$B$44:$L$54,Monthly!$A28,Breakup!F$44:F$54) -> -0.85922524 | F28: =SUMIF(Breakup!$B$44:$L$54,Monthly!$A28,Breakup!G$44:G$54) -> 0.30109744 | G28: =SUMIF(Breakup!$B$44:$L$54,Monthly!$A28,Breakup!H$44:H$54) -> 4.5203984 | H28: =SUMIF(Breakup!$B$44:$L$54,Monthly!$A28,Breakup!I$44:I$54) -> 1.5698698 | I28: =SUMIF(Breakup!$B$44:$L$54,Monthly!$A28,Breakup!J$44:J$54) -> 2.2693108 | ... K28: =SUMIF(Breakup!$B$44:$L$54,Monthly!$A28,Breakup!L$44:L$54) -> 1.1162761 | L28: =SUMIF(Breakup!$B$44:M$54,Monthly!$A28,Breakup!M$44:M$54) -> 0.75154214 | M28: =SUMIF(Breakup!$B$44:N$54,Monthly!$A28,Breakup!N$44:N$54) -> -1.2321105 | N28: =SUMIF(Breakup!$B$44:O$54,Monthly!$A28,Breakup!O$44:O$54) -> 0.70386042 | O28: =SUMIF(Breakup!$B$44:P$54,Monthly!$A28,Breakup!P$44:P$54) -> 0.33126205 | P28: =SUMIF(Breakup!$B$44:Q$54,Monthly!$A28,Breakup!Q$44:Q$54) -> -7.6109648 | Q28: =SUMIF(Breakup!$B$44:R$54,Monthly!$A28,Breakup!R$44:R$54) -> 5.5022179 | R28: =SUMIF(Breakup!$B$44:S$54,Monthly!$A28,Breakup!S$44:S$54) -> -1.2249286 | S28: =SUMIF(Breakup!$B$44:T$54,Monthly!$A28,Breakup!T$44:T$54) -> -4.0258704 | ... U28: =SUMIF(Breakup!$B$44:V$54,Monthly!$A28,Breakup!V$44:V$54) -> 8.1110414 | V28: =SUMIF(Breakup!$B$44:BO$54,Monthly!$A28,Breakup!W$44:W$54) -> 2.4134784 | W28: =SUMIF(Breakup!$B$44:BP$54,Monthly!$A28,Breakup!X$44:X$54) -> -2.0730496 | X28: =SUMIF(Breakup!$B$44:Y$54,Monthly!$A28,Breakup!Y$44:Y$54) -> 3.4267467 | Y28: =SUMIF(Breakup!$B$44:Z$54,Monthly!$A28,Breakup!Z$44:Z$54) -> 0.27717154 | Z28: =SUMIF(Breakup!$B$44:AA$54,Monthly!$A28,Breakup!AA$44:AA$54) -> -3.2496419 | AA28: =SUMIF(Breakup!$B$44:AB$54,Monthly!$A28,Breakup!AB$44:AB$54) -> -0.37346527 | AB28: =SUMIF(Breakup!$B$44:AC$54,Monthly!$A28,Breakup!AC$44:AC$54) -> -0.90731354 | AC28: =SUMIF(Breakup!$B$44:AD$54,Monthly!$A28,Breakup!AD$44:AD$54) -> -1.0894759 | AD28: =SUMIF(Breakup!$B$44:AE$54,Monthly!$A28,Breakup!AE$44:AE$54) -> 5.2529259 | AE28: =SUMIF(Breakup!$B$44:AF$54,Monthly!$A28,Breakup!AF$44:AF$54) -> 6.381625 | ... BN28: =SUMIF(Breakup!$B$44:BO$54,Monthly!$A28,Breakup!BO$44:BO$54) -> 25.625288 | BP28: =SUM(B28:BN28) -> 97.296686 | BQ28: =BP28/$BO$1 -> 1.5202607
A29: Debt | B29: =SUMIF(Breakup!$B$44:$L$54,Monthly!$A29,Breakup!C$44:C$54) -> 0 | C29: =SUMIF(Breakup!$B$44:$L$54,Monthly!$A29,Breakup!D$44:D$54) -> 0.238 | D29: =SUMIF(Breakup!$B$44:$L$54,Monthly!$A29,Breakup!E$44:E$54) -> -0.038 | E29: =SUMIF(Breakup!$B$44:$L$54,Monthly!$A29,Breakup!F$44:F$54) -> 2.389 | F29: =SUMIF(Breakup!$B$44:$L$54,Monthly!$A29,Breakup!G$44:G$54) -> 0.6294 | G29: =SUMIF(Breakup!$B$44:$L$54,Monthly!$A29,Breakup!H$44:H$54) -> 0.0085 | H29: =SUMIF(Breakup!$B$44:$L$54,Monthly!$A29,Breakup!I$44:I$54) -> -0.0043 | I29: =SUMIF(Breakup!$B$44:$L$54,Monthly!$A29,Breakup!J$44:J$54) -> 0.00633 | ... K29: =SUMIF(Breakup!$B$44:$L$54,Monthly!$A29,Breakup!L$44:L$54) -> -0.01592 | L29: =SUMIF(Breakup!$B$44:M$54,Monthly!$A29,Breakup!M$44:M$54) -> -0.014 | M29: =SUMIF(Breakup!$B$44:N$54,Monthly!$A29,Breakup!N$44:N$54) -> 0.02 | N29: =SUMIF(Breakup!$B$44:O$54,Monthly!$A29,Breakup!O$44:O$54) -> 0.013 | O29: =SUMIF(Breakup!$B$44:P$54,Monthly!$A29,Breakup!P$44:P$54) -> -0.02 | P29: =SUMIF(Breakup!$B$44:Q$54,Monthly!$A29,Breakup!Q$44:Q$54) -> 0.011 | Q29: =SUMIF(Breakup!$B$44:R$54,Monthly!$A29,Breakup!R$44:R$54) -> 2.92 | R29: =SUMIF(Breakup!$B$44:S$54,Monthly!$A29,Breakup!S$44:S$54) -> 0.1825 | S29: =SUMIF(Breakup!$B$44:T$54,Monthly!$A29,Breakup!T$44:T$54) -> -0.04 | ... U29: =SUMIF(Breakup!$B$44:V$54,Monthly!$A29,Breakup!V$44:V$54) -> 0.026 | V29: =SUMIF(Breakup!$B$44:BO$54,Monthly!$A29,Breakup!W$44:W$54) -> 0.005 | W29: =SUMIF(Breakup!$B$44:BP$54,Monthly!$A29,Breakup!X$44:X$54) -> 0.038 | X29: =SUMIF(Breakup!$B$44:Y$54,Monthly!$A29,Breakup!Y$44:Y$54) -> -0.009 | Y29: =SUMIF(Breakup!$B$44:Z$54,Monthly!$A29,Breakup!Z$44:Z$54) -> 0.04 | Z29: =SUMIF(Breakup!$B$44:AA$54,Monthly!$A29,Breakup!AA$44:AA$54) -> 0.0066 | AA29: =SUMIF(Breakup!$B$44:AB$54,Monthly!$A29,Breakup!AB$44:AB$54) -> 0.02301 | AB29: =SUMIF(Breakup!$B$44:AC$54,Monthly!$A29,Breakup!AC$44:AC$54) -> 0.001782 | AC29: =SUMIF(Breakup!$B$44:AD$54,Monthly!$A29,Breakup!AD$44:AD$54) -> 3.113448 | AD29: =SUMIF(Breakup!$B$44:AE$54,Monthly!$A29,Breakup!AE$44:AE$54) -> 0.039002 | AE29: =SUMIF(Breakup!$B$44:AF$54,Monthly!$A29,Breakup!AF$44:AF$54) -> 0.038998 | ... BN29: =SUMIF(Breakup!$B$44:BO$54,Monthly!$A29,Breakup!BO$44:BO$54) -> 0.7326 | BP29: =SUM(B29:BN29) -> 26.601676 | BQ29: =BP29/$BO$1 -> 0.41565119
A30: Gold | B30: =SUMIF(Breakup!$B$44:$L$54,Monthly!$A30,Breakup!C$44:C$54) -> 0 | C30: =SUMIF(Breakup!$B$44:$L$54,Monthly!$A30,Breakup!D$44:D$54) -> -0.021136 | D30: =SUMIF(Breakup!$B$44:$L$54,Monthly!$A30,Breakup!E$44:E$54) -> -0.047239 | E30: =SUMIF(Breakup!$B$44:$L$54,Monthly!$A30,Breakup!F$44:F$54) -> -0.0140995 | F30: =SUMIF(Breakup!$B$44:$L$54,Monthly!$A30,Breakup!G$44:G$54) -> 0.0275245 | G30: =SUMIF(Breakup!$B$44:$L$54,Monthly!$A30,Breakup!H$44:H$54) -> 0.0197035 | H30: =SUMIF(Breakup!$B$44:$L$54,Monthly!$A30,Breakup!I$44:I$54) -> -0.0171535 | I30: =SUMIF(Breakup!$B$44:$L$54,Monthly!$A30,Breakup!J$44:J$54) -> -0.0041365 | ... K30: =SUMIF(Breakup!$B$44:$L$54,Monthly!$A30,Breakup!L$44:L$54) -> -0.004148 | L30: =SUMIF(Breakup!$B$44:M$54,Monthly!$A30,Breakup!M$44:M$54) -> 0.01025 | M30: =SUMIF(Breakup!$B$44:N$54,Monthly!$A30,Breakup!N$44:N$54) -> 0.0034 | N30: =SUMIF(Breakup!$B$44:O$54,Monthly!$A30,Breakup!O$44:O$54) -> -0.005 | O30: =SUMIF(Breakup!$B$44:P$54,Monthly!$A30,Breakup!P$44:P$54) -> -0.00885 | P30: =SUMIF(Breakup!$B$44:Q$54,Monthly!$A30,Breakup!Q$44:Q$54) -> 0.0311 | Q30: =SUMIF(Breakup!$B$44:R$54,Monthly!$A30,Breakup!R$44:R$54) -> 0 | R30: =SUMIF(Breakup!$B$44:S$54,Monthly!$A30,Breakup!S$44:S$54) -> 0 | S30: =SUMIF(Breakup!$B$44:T$54,Monthly!$A30,Breakup!T$44:T$54) -> 0 | ... U30: =SUMIF(Breakup!$B$44:V$54,Monthly!$A30,Breakup!V$44:V$54) -> 0 | V30: =SUMIF(Breakup!$B$44:BO$54,Monthly!$A30,Breakup!W$44:W$54) -> 0.027802 | W30: =SUMIF(Breakup!$B$44:BP$54,Monthly!$A30,Breakup!X$44:X$54) -> -0.021012 | X30: =SUMIF(Breakup!$B$44:Y$54,Monthly!$A30,Breakup!Y$44:Y$54) -> 0.0093 | Y30: =SUMIF(Breakup!$B$44:Z$54,Monthly!$A30,Breakup!Z$44:Z$54) -> 0.018642 | Z30: =SUMIF(Breakup!$B$44:AA$54,Monthly!$A30,Breakup!AA$44:AA$54) -> 0.051995 | AA30: =SUMIF(Breakup!$B$44:AB$54,Monthly!$A30,Breakup!AB$44:AB$54) -> 0.0367725 | AB30: =SUMIF(Breakup!$B$44:AC$54,Monthly!$A30,Breakup!AC$44:AC$54) -> -0.0130245 | AC30: =SUMIF(Breakup!$B$44:AD$54,Monthly!$A30,Breakup!AD$44:AD$54) -> 0.062532 | AD30: =SUMIF(Breakup!$B$44:AE$54,Monthly!$A30,Breakup!AE$44:AE$54) -> 0.055668 | AE30: =SUMIF(Breakup!$B$44:AF$54,Monthly!$A30,Breakup!AF$44:AF$54) -> 0.0549655 | ... BN30: =SUMIF(Breakup!$B$44:BO$54,Monthly!$A30,Breakup!BO$44:BO$54) -> 0.1314615 | BP30: =SUM(B30:BN30) -> 2.9333955 | BQ30: =BP30/$BO$1 -> 0.045834305
A31: Alternate | B31: =SUMIF(Breakup!$B$30:$L$40,Monthly!$A31,Breakup!C$30:C$40) -> 0 | C31: =SUMIF(Breakup!$B$30:$L$40,Monthly!$A31,Breakup!D$30:D$40) -> 0 | D31: =SUMIF(Breakup!$B$30:$L$40,Monthly!$A31,Breakup!E$30:E$40) -> 0 | E31: =SUMIF(Breakup!$B$30:$L$40,Monthly!$A31,Breakup!F$30:F$40) -> 0 | F31: =SUMIF(Breakup!$B$30:$L$40,Monthly!$A31,Breakup!G$30:G$40) -> 0 | G31: =SUMIF(Breakup!$B$30:$L$40,Monthly!$A31,Breakup!H$30:H$40) -> 0 | H31: =SUMIF(Breakup!$B$30:$L$40,Monthly!$A31,Breakup!I$30:I$40) -> 0 | I31: =SUMIF(Breakup!$B$30:$L$40,Monthly!$A31,Breakup!J$30:J$40) -> 0 | J31: =SUMIF(Breakup!$B$30:$L$40,Monthly!$A31,Breakup!K$30:K$40) -> 0.10485 | K31: =SUMIF(Breakup!$B$44:$L$54,Monthly!$A31,Breakup!L$44:L$54) -> 0 | L31: =SUMIF(Breakup!$B$44:M$54,Monthly!$A31,Breakup!M$44:M$54) -> 0.19 | M31: =SUMIF(Breakup!$B$44:N$54,Monthly!$A31,Breakup!N$44:N$54) -> 0 | N31: =SUMIF(Breakup!$B$44:O$54,Monthly!$A31,Breakup!O$44:O$54) -> 0 | O31: =SUMIF(Breakup!$B$44:P$54,Monthly!$A31,Breakup!P$44:P$54) -> 0 | P31: =SUMIF(Breakup!$B$44:Q$54,Monthly!$A31,Breakup!Q$44:Q$54) -> 0 | Q31: =SUMIF(Breakup!$B$44:R$54,Monthly!$A31,Breakup!R$44:R$54) -> 0 | R31: =SUMIF(Breakup!$B$44:S$54,Monthly!$A31,Breakup!S$44:S$54) -> 0 | S31: =SUMIF(Breakup!$B$44:T$54,Monthly!$A31,Breakup!T$44:T$54) -> 0 | ... U31: =SUMIF(Breakup!$B$44:V$54,Monthly!$A31,Breakup!V$44:V$54) -> 0 | V31: =SUMIF(Breakup!$B$44:BO$54,Monthly!$A31,Breakup!W$44:W$54) -> 0 | W31: =SUMIF(Breakup!$B$44:BP$54,Monthly!$A31,Breakup!X$44:X$54) -> 0 | X31: =SUMIF(Breakup!$B$44:Y$54,Monthly!$A31,Breakup!Y$44:Y$54) -> 0 | Y31: =SUMIF(Breakup!$B$44:Z$54,Monthly!$A31,Breakup!Z$44:Z$54) -> 0 | Z31: =SUMIF(Breakup!$B$44:AA$54,Monthly!$A31,Breakup!AA$44:AA$54) -> 0 | AA31: =SUMIF(Breakup!$B$44:AB$54,Monthly!$A31,Breakup!AB$44:AB$54) -> 0 | AB31: =SUMIF(Breakup!$B$44:AC$54,Monthly!$A31,Breakup!AC$44:AC$54) -> 0 | AC31: =SUMIF(Breakup!$B$44:AD$54,Monthly!$A31,Breakup!AD$44:AD$54) -> 0 | AD31: =SUMIF(Breakup!$B$44:AE$54,Monthly!$A31,Breakup!AE$44:AE$54) -> 0 | AE31: =SUMIF(Breakup!$B$44:AF$54,Monthly!$A31,Breakup!AF$44:AF$54) -> 0 | ... BN31: =SUMIF(Breakup!$B$44:BO$54,Monthly!$A31,Breakup!BO$44:BO$54) -> 0 | BP31: =SUM(B31:BN31) -> 0.29485 | BQ31: =BP31/$BO$1 -> 0.0046070312
A32: Liquid | B32: =SUMIF(Breakup!$B$44:$L$54,Monthly!$A32,Breakup!C$44:C$54) -> 0 | C32: =SUMIF(Breakup!$B$44:$L$54,Monthly!$A32,Breakup!D$44:D$54) -> 0 | D32: =SUMIF(Breakup!$B$44:$L$54,Monthly!$A32,Breakup!E$44:E$54) -> 0 | E32: =SUMIF(Breakup!$B$44:$L$54,Monthly!$A32,Breakup!F$44:F$54) -> 0 | F32: =SUMIF(Breakup!$B$44:$L$54,Monthly!$A32,Breakup!G$44:G$54) -> 0 | G32: =SUMIF(Breakup!$B$44:$L$54,Monthly!$A32,Breakup!H$44:H$54) -> 0 | H32: =SUMIF(Breakup!$B$44:$L$54,Monthly!$A32,Breakup!I$44:I$54) -> 0 | I32: =SUMIF(Breakup!$B$44:$L$54,Monthly!$A32,Breakup!J$44:J$54) -> 0 | ... K32: =SUMIF(Breakup!$B$44:$L$54,Monthly!$A32,Breakup!L$44:L$54) -> 0 | L32: =SUMIF(Breakup!$B$44:M$54,Monthly!$A32,Breakup!M$44:M$54) -> 0 | M32: =SUMIF(Breakup!$B$44:N$54,Monthly!$A32,Breakup!N$44:N$54) -> 0 | N32: =SUMIF(Breakup!$B$44:O$54,Monthly!$A32,Breakup!O$44:O$54) -> 0 | O32: =SUMIF(Breakup!$B$44:P$54,Monthly!$A32,Breakup!P$44:P$54) -> 0 | P32: =SUMIF(Breakup!$B$44:Q$54,Monthly!$A32,Breakup!Q$44:Q$54) -> 0 | Q32: =SUMIF(Breakup!$B$44:R$54,Monthly!$A32,Breakup!R$44:R$54) -> 0 | R32: =SUMIF(Breakup!$B$44:S$54,Monthly!$A32,Breakup!S$44:S$54) -> 0 | S32: =SUMIF(Breakup!$B$44:T$54,Monthly!$A32,Breakup!T$44:T$54) -> 0 | ... U32: =SUMIF(Breakup!$B$44:V$54,Monthly!$A32,Breakup!V$44:V$54) -> 0 | V32: =SUMIF(Breakup!$B$44:BO$54,Monthly!$A32,Breakup!W$44:W$54) -> 0 | W32: =SUMIF(Breakup!$B$44:BP$54,Monthly!$A32,Breakup!X$44:X$54) -> 0 | X32: =SUMIF(Breakup!$B$44:Y$54,Monthly!$A32,Breakup!Y$44:Y$54) -> 0 | Y32: =SUMIF(Breakup!$B$44:Z$54,Monthly!$A32,Breakup!Z$44:Z$54) -> 0 | Z32: =SUMIF(Breakup!$B$44:AA$54,Monthly!$A32,Breakup!AA$44:AA$54) -> 0 | AA32: =SUMIF(Breakup!$B$44:AB$54,Monthly!$A32,Breakup!AB$44:AB$54) -> 0 | AB32: =SUMIF(Breakup!$B$44:AC$54,Monthly!$A32,Breakup!AC$44:AC$54) -> 0 | AC32: =SUMIF(Breakup!$B$44:AD$54,Monthly!$A32,Breakup!AD$44:AD$54) -> 0 | AD32: =SUMIF(Breakup!$B$44:AE$54,Monthly!$A32,Breakup!AE$44:AE$54) -> 0 | AE32: =SUMIF(Breakup!$B$44:AF$54,Monthly!$A32,Breakup!AF$44:AF$54) -> 0 | ... BN32: =SUMIF(Breakup!$B$44:BO$54,Monthly!$A32,Breakup!BO$44:BO$54) -> 0 | BP32: =SUM(B32:BN32) -> 0 | BQ32: =BP32/$BO$1 -> 0
A33: Total | B33: =SUM(B28:B32) -> 0 | C33: =SUM(C28:C32) -> 2.3043646 | D33: =SUM(D28:D32) -> 4.1460816 | E33: =SUM(E28:E32) -> 1.5156753 | F33: =SUM(F28:F32) -> 0.95802194 | G33: =SUM(G28:G32) -> 4.5486019 | H33: =SUM(H28:H32) -> 1.5484163 | I33: =SUM(I28:I32) -> 2.2715043 | ... BN33: =SUM(BN28:BN32) -> 26.48935 | BP33: =SUM(B33:BN33) -> 127.12661 | BQ33: =BP33/$BO$1 -> 1.9863532
A35: NET CHANGE
A36: Equity | B36: =SUMIF(Breakup!$B$58:$L$68,Monthly!$A36,Breakup!C$58:C$68) -> 0 | C36: =C20+C28 -> 3.9338714 | D36: =D20+D28 -> 4.6413206 | E36: =E20+E28 -> 1.1407748 | F36: =F20+F28 -> -1.4289026 | G36: =G20+G28 -> 6.4203984 | H36: =H20+H28 -> 3.9998698 | I36: =I20+I28 -> 3.8693108 | J36: =J20+J28 -> 6.3978386 | ... BN36: =BN20+BN28 -> 25.67529 | BP36: =SUM(B36:BN36) -> 206.73611 | BQ36: =BP36/$BO$1 -> 3.2302518
A37: Debt | B37: =SUMIF(Breakup!$B$58:$L$68,Monthly!$A37,Breakup!C$58:C$68) -> 0 | C37: =C21+C29 -> 0.468 | D37: =D21+D29 -> 0.432 | E37: =E21+E29 -> 2.589 | F37: =F21+F29 -> 0.8594 | G37: =G21+G29 -> 0.2415 | H37: =H21+H29 -> 0.22866 | I37: =I21+I29 -> 0.23929 | J37: =J21+J29 -> 0.26395 | ... BN37: =BN21+BN29 -> 1.20766 | BP37: =SUM(B37:BN37) -> 57.290146 | BQ37: =BP37/$BO$1 -> 0.89515853
A38: Gold | B38: =SUMIF(Breakup!$B$58:$L$68,Monthly!$A38,Breakup!C$58:C$68) -> 0 | C38: =C22+C30 -> 0.226364 | D38: =D22+D30 -> -0.047239 | E38: =E22+E30 -> -0.0140995 | F38: =F22+F30 -> 0.0275245 | G38: =G22+G30 -> 0.0197035 | H38: =H22+H30 -> -0.0171535 | I38: =I22+I30 -> -0.0041365 | J38: =J22+J30 -> -0.0134655 | ... BN38: =BN22+BN30 -> 0.1314615 | BP38: =SUM(B38:BN38) -> 4.1860555 | BQ38: =BP38/$BO$1 -> 0.065407117
A39: Alternate | B39: =SUMIF(Breakup!$B$58:$L$68,Monthly!$A39,Breakup!C$58:C$68) -> 0 | C39: =C23+C31 -> 0 | D39: =D23+D31 -> 0 | E39: =E23+E31 -> 0 | F39: =F23+F31 -> 0 | G39: =G23+G31 -> 0 | H39: =H23+H31 -> 0 | I39: =I23+I31 -> 0 | J39: =J23+J31 -> 0.2097 | ... BN39: =BN23+BN31 -> 0 | BP39: =SUM(B39:BN39) -> 0.10485 | BQ39: =BP39/$BO$1 -> 0.0016382812
A40: Liquid | B40: =SUMIF(Breakup!$B$58:$L$68,Monthly!$A40,Breakup!C$58:C$68) -> 0 | C40: =C24+C32 -> -1.45 | D40: =D24+D32 -> -2.2 | E40: =E24+E32 -> 0.003501614 | F40: =F24+F32 -> 2.5073171 | G40: =G24+G32 -> 0.009066541 | H40: =H24+H32 -> 0.009228589 | I40: =I24+I32 -> -0.99072487 | J40: =J24+J32 -> -0.49289939 | ... BN40: =BN24+BN32 -> 0 | BP40: =SUM(B40:BN40) -> -4.65 | BQ40: =BP40/$BO$1 -> -0.07265625
A41: Total | B41: =SUM(B36:B40) -> 0 | C41: =C25+C33 -> 3.1782354 | D41: =D25+D33 -> 2.8260816 | E41: =E25+E33 -> 3.7191769 | F41: =F25+F33 -> 1.9653391 | G41: =G25+G33 -> 6.6906684 | H41: =H25+H33 -> 4.2206049 | I41: =I25+I33 -> 3.1137395 | J41: =J25+J33 -> 6.3651237 | ... BN41: =BN25+BN33 -> 27.014411 | BP41: =SUM(B41:BN41) -> 263.66716 | BQ41: =BP41/$BO$1 -> 4.1197994
A42: % Change | C42: =C41/B9 -> 0.037790879 | D42: =D41/C9 -> 0.032379921 | E42: =E41/D9 -> 0.041276073 | F42: =F41/E9 -> 0.020947063 | G42: =G41/F9 -> 0.069847671 | H42: =H41/G9 -> 0.041184631 | I42: =I41/H9 -> 0.029181996 | J42: =J41/I9 -> 0.057962538 | ... AU42: =AU41/AT9 -> 0.022709386 | AV42: =AV41/AT9 -> -0.040756293 | AW42: =AW41/AT9 -> 0.0069467226 | AX42: =AX41/AT9 -> 0.01759596 | AY42: =AY41/AU9 -> -0.040212876 | AZ42: =AZ41/AT9 -> -0.045763451 | BA42: =BA41/AT9 -> 0.05934019 | BB42: =BB41/AT9 -> 0.025972372 | BC42: =BC41/AT9 -> 0.039318042 | BD42: =BD41/AT9 -> 0.02737916 | BE42: =BE41/AT9 -> 0.0016755291 | BF42: =BF41/AT9 -> -0.0035937955 | BG42: =BG41/AT9 -> 0.0087225255 | BH42: =BH41/AT9 -> 0.034743844 | BI42: =BI41/AT9 -> 0.0030684386 | BJ42: =BJ41/AT9 -> 0.005050695 | BK42: =BK41/AT9 -> -0.013074898 | BL42: =BL41/AT9 -> -0.0056468828 | BM42: =BM41/AT9 -> -0.045090966 | BN42: =BN41/AU9 -> 0.087112837
A44: % RETURNS
A45: Equity | C45: =C28/(B4) -> 0.045458919 | D45: =D28/(C4) -> 0.084873452 | E45: =E28/(D4) -> -0.01576682 | F45: =F28/(E4) -> 0.0054118629 | G45: =G28/(F4) -> 0.0833904 | H45: =H28/(G4) -> 0.025893454 | I45: =I28/(H4) -> 0.035113471 | J45: =J28/(I4) -> 0.05836496 | ... BN45: =BN28/(BM4) -> 0.11289598 | BO45: =AVERAGE(C45:BN45)*12 -> 0.1614032 | BQ45: =AVERAGE(C45:BN45) -> 0.013450267
A46: Debt | C46: =C29/(B5) -> 0.0073163234 | D46: =D29/(C5) -> -0.0011515849 | E46: =E29/(D5) -> 0.071462758 | F46: =F29/(E5) -> 0.017474111 | G46: =G29/(F5) -> 0.00023048722 | H46: =H29/(G5) -> -0.00011584083 | I46: =I29/(H5) -> 0.00016948445 | J46: =J29/(I5) -> 0.00082446855 | ... BN46: =BN29/(BM5) -> 0.0082672327 | BO46: =AVERAGE(C46:BN46)*12 -> 0.089756395 | BQ46: =AVERAGE(C46:BN46) -> 0.0074796996
A47: Gold | C47: =C30/(B6) -> -0.021136 | D47: =D30/(C6) -> -0.038519559 | E47: =E30/(D6) -> -0.011957596 | F47: =F30/(E6) -> 0.023625663 | G47: =G30/(F6) -> 0.016522158 | H47: =H30/(G6) -> -0.014150093 | I47: =I30/(H6) -> -0.0034612166 | J47: =J30/(I6) -> -0.011306392 | ... BN47: =BN30/(BM6) -> 0.02600832 | BO47: =AVERAGE(C47:BN47)*12 -> 0.21354631 | BQ47: =AVERAGE(C47:BN47) -> 0.017795526
A48: Alternate | C48: - | D48: - | E48: - | F48: - | G48: - | H48: - | I48: - | J48: - | K48: =K31/(J7) -> 0 | L48: =L31/(K7) -> 0.35185185 | M48: =M31/(L7) -> 0 | BQ48: =AVERAGE(C48:BN48) -> 0.11728395
A49: Liquid
A50: Total | C50: =C33/(B9) -> 0.027400099 | D50: =D33/(C9) -> 0.047503863 | E50: =E33/(D9) -> 0.016821228 | F50: =F33/(E9) -> 0.010210831 | G50: =G33/(F9) -> 0.047485427 | H50: =H33/(G9) -> 0.015109435 | I50: =I33/(H9) -> 0.021288561 | J50: =J33/(I9) -> 0.037519775 | ... BN50: =BN33/(BM9) -> 0.082611179 | BO50: =AVERAGE(C50:BN50)*12 -> 0.13359962 | BQ50: =AVERAGE(C50:BN50) -> 0.011133302
A52: Annualized Investments
A53: Equity | N53: =SUM(C20:N20) -> 19.892195 | O53: =SUM(D20:O20) -> 20.435054 | P53: =SUM(E20:P20) -> 21.300679 | Q53: =SUM(F20:Q20) -> 21.106245 | R53: =SUM(G20:R20) -> 24.082746 | S53: =SUM(H20:S20) -> 22.614559 | T53: =SUM(I20:T20) -> 20.48126 | U53: =SUM(J20:U20) -> 19.724629 | ... BN53: =SUM(BC20:BN20) -> 14.567823 | BQ53: =AVERAGE(C53:BN53) -> 22.00072
A54: Debt | N54: =SUM(C21:N21) -> 4.77074 | O54: =SUM(D21:O21) -> 4.81604 | P54: =SUM(E21:P21) -> 4.62134 | Q54: =SUM(F21:Q21) -> 4.70714 | R54: =SUM(G21:R21) -> 4.75244 | S54: =SUM(H21:S21) -> 4.79474 | T54: =SUM(I21:T21) -> 4.83708 | U54: =SUM(J21:U21) -> 4.902424 | ... BN54: =SUM(BC21:BN21) -> 5.60632 | BQ54: =AVERAGE(C54:BN54) -> 5.9221943
A55: Gold | N55: =SUM(C22:N22) -> 0.2475 | O55: =SUM(D22:O22) -> 0 | P55: =SUM(E22:P22) -> 0 | Q55: =SUM(F22:Q22) -> -0.0197 | R55: =SUM(G22:R22) -> 0.02665 | S55: =SUM(H22:S22) -> -0.00865 | T55: =SUM(I22:T22) -> 0.00675 | U55: =SUM(J22:U22) -> 0.00516 | ... BN55: =SUM(BC22:BN22) -> 1 | BQ55: =AVERAGE(C55:BN55) -> 0.19451736
A56: Alternate | N56: =SUM(C23:N23) -> -0.19 | O56: =SUM(D23:O23) -> -0.19 | P56: =SUM(E23:P23) -> -0.19 | Q56: =SUM(F23:Q23) -> -0.19 | R56: =SUM(G23:R23) -> -0.19 | S56: =SUM(H23:S23) -> -0.19 | T56: =SUM(I23:T23) -> -0.19 | U56: =SUM(J23:U23) -> -0.19 | ... AY56: =SUM(AN23:AY23) -> 0 | AZ56: =SUM(AM23:AZ23) -> 0 | BA56: =SUM(AM23:BA23) -> 0 | BB56: =SUM(AQ23:BB23) -> 0 | BC56: =SUM(AR23:BC23) -> 0 | BD56: =SUM(AS23:BD23) -> 0 | BE56: =SUM(AT23:BE23) -> 0 | BF56: =SUM(AU23:BF23) -> 0 | BG56: =SUM(AV23:BG23) -> 0 | BH56: =SUM(AW23:BH23) -> 0 | BI56: =SUM(AX23:BI23) -> 0 | ... BN56: =SUM(BC23:BN23) -> 0 | BQ56: =AVERAGE(C56:BN56) -> -0.061789623
A57: Liquid | N57: =SUM(C24:N24) -> -1.7924343 | O57: =SUM(D24:O24) -> -0.84252167 | P57: =SUM(E24:P24) -> 0.34396988 | Q57: =SUM(F24:Q24) -> 0.34435939 | R57: =SUM(G24:R24) -> -2.1591809 | S57: =SUM(H24:S24) -> -3.5198531 | T57: =SUM(I24:T24) -> -3.5291139 | U57: =SUM(J24:U24) -> -2.538389 | ... BN57: =SUM(BC24:BN24) -> -6.0001144 | BQ57: =AVERAGE(C57:BN57) -> -0.50258014
A58: Total | N58: =SUM(N53:N57) -> 22.928001 | O58: =SUM(O53:O57) -> 24.218572 | P58: =SUM(P53:P57) -> 26.075989 | Q58: =SUM(Q53:Q57) -> 25.948044 | R58: =SUM(R53:R57) -> 26.512655 | S58: =SUM(S53:S57) -> 23.690796 | T58: =SUM(T53:T57) -> 21.605976 | U58: =SUM(U53:U57) -> 21.903824 | ... BN58: =SUM(BN53:BN57) -> 15.174028 | BQ58: =AVERAGE(C58:BN58) -> 27.553062
A60: Annualized Returns
A61: Equity | N61: =SUM(C28:N28) -> 19.457679 | O61: =SUM(D28:O28) -> 17.701441 | P61: =SUM(E28:P28) -> 5.8591553 | Q61: =SUM(F28:Q28) -> 12.220598 | R61: =SUM(G28:R28) -> 10.694572 | S61: =SUM(H28:S28) -> 2.1483036 | T61: =SUM(I28:T28) -> -2.406677 | U61: =SUM(J28:U28) -> 3.4350536 | ... BN61: =SUM(BC28:BN28) -> 19.838573 | BQ61: =AVERAGE(C61:BN61) -> 18.707314
A62: Debt | N62: =SUM(C29:N29) -> 3.263 | O62: =SUM(D29:O29) -> 3.005 | P62: =SUM(E29:P29) -> 3.054 | Q62: =SUM(F29:Q29) -> 3.585 | R62: =SUM(G29:R29) -> 3.1381 | S62: =SUM(H29:S29) -> 3.0896 | T62: =SUM(I29:T29) -> 3.1109 | U62: =SUM(J29:U29) -> 3.13057 | ... BN62: =SUM(BC29:BN29) -> 6.031198 | BQ62: =AVERAGE(C62:BN62) -> 4.3231406
A63: Gold | N63: =SUM(C30:N30) -> -0.0655 | O63: =SUM(D30:O30) -> -0.053214 | P63: =SUM(E30:P30) -> 0.025125 | Q63: =SUM(F30:Q30) -> 0.0392245 | R63: =SUM(G30:R30) -> 0.0117 | S63: =SUM(H30:S30) -> -0.0080035 | T63: =SUM(I30:T30) -> 0.00915 | U63: =SUM(J30:U30) -> 0.0132865 | ... BN63: =SUM(BC30:BN30) -> 1.9054555 | BQ63: =AVERAGE(C63:BN63) -> 0.51955664
A64: Alternate | N64: =SUM(C31:N31) -> 0.29485 | O64: =SUM(D31:O31) -> 0.29485 | P64: =SUM(E31:P31) -> 0.29485 | Q64: =SUM(F31:Q31) -> 0.29485 | R64: =SUM(G31:R31) -> 0.29485 | S64: =SUM(H31:S31) -> 0.29485 | T64: =SUM(I31:T31) -> 0.29485 | U64: =SUM(J31:U31) -> 0.29485 | ... AI64: =SUM(X31:AI31) -> 0 | AJ64: =SUM(X31:AJ31) -> 0 | AK64: =SUM(Y31:AK31) -> 0 | AL64: =SUM(AA31:AL31) -> 0 | AM64: =SUM(AB31:AM31) -> 0 | AN64: =SUM(AC31:AN31) -> 0 | AO64: =SUM(AD31:AO31) -> 0 | AP64: =SUM(AE31:AP31) -> 0 | AQ64: =SUM(AF31:AQ31) -> 0 | AR64: =SUM(AG31:AR31) -> 0 | AS64: =SUM(AH31:AS31) -> 0 | ... AU64: =SUM(AJ31:AU31) -> 0 | AV64: =SUM(AJ31:AV31) -> 0 | AW64: =SUM(AK31:AW31) -> 0 | AX64: =SUM(AL31:AX31) -> 0 | AY64: =SUM(AM31:AY31) -> 0 | AZ64: =SUM(AL31:AZ31) -> 0 | BA64: =SUM(AL31:BA31) -> 0 | BB64: =SUM(AQ31:BB31) -> 0 | BC64: =SUM(AR31:BC31) -> 0 | BD64: =SUM(AS31:BD31) -> 0 | BE64: =SUM(AT31:BE31) -> 0 | BF64: =SUM(AU31:BF31) -> 0 | BG64: =SUM(AV31:BG31) -> 0 | BH64: =SUM(AW31:BH31) -> 0 | BI64: =SUM(AX31:BI31) -> 0 | BJ64: =SUM(AX31:BJ31) -> 0 | BK64: =SUM(AX31:BK31) -> 0 | BL64: =SUM(AX31:BL31) -> 0 | BM64: =SUM(BB31:BM31) -> 0 | BN64: =SUM(BC31:BN31) -> 0 | BQ64: =AVERAGE(C64:BN64) -> 0.051675472
A65: Liquid | N65: =SUM(C32:N32) -> 0 | O65: =SUM(D32:O32) -> 0 | P65: =SUM(E32:P32) -> 0 | Q65: =SUM(F32:Q32) -> 0 | R65: =SUM(G32:R32) -> 0 | S65: =SUM(H32:S32) -> 0 | T65: =SUM(I32:T32) -> 0 | U65: =SUM(J32:U32) -> 0 | ... AI65: =SUM(X32:AI32) -> 0 | AJ65: =SUM(X32:AJ32) -> 0 | AK65: =SUM(Y32:AK32) -> 0 | AL65: =SUM(AA32:AL32) -> 0 | AM65: =SUM(AB32:AM32) -> 0 | AN65: =SUM(AC32:AN32) -> 0 | AO65: =SUM(AD32:AO32) -> 0 | AP65: =SUM(AE32:AP32) -> 0 | AQ65: =SUM(AF32:AQ32) -> 0 | AR65: =SUM(AG32:AR32) -> 0 | AS65: =SUM(AH32:AS32) -> 0 | ... AU65: =SUM(AJ32:AU32) -> 0 | AV65: =SUM(AJ32:AV32) -> 0 | AW65: =SUM(AK32:AW32) -> 0 | AX65: =SUM(AL32:AX32) -> 0 | AY65: =SUM(AM32:AY32) -> 0 | AZ65: =SUM(AL32:AZ32) -> 0 | BA65: =SUM(AL32:BA32) -> 0 | BB65: =SUM(AL32:BB32) -> 0 | BC65: =SUM(AR32:BC32) -> 0 | BD65: =SUM(AS32:BD32) -> 0 | BE65: =SUM(AT32:BE32) -> 0 | BF65: =SUM(AU32:BF32) -> 0 | BG65: =SUM(AV32:BG32) -> 0 | BH65: =SUM(AW32:BH32) -> 0 | BI65: =SUM(AX32:BI32) -> 0 | BJ65: =SUM(AX32:BJ32) -> 0 | BK65: =SUM(AX32:BK32) -> 0 | BL65: =SUM(AX32:BL32) -> 0 | BM65: =SUM(BB32:BM32) -> 0 | BN65: =SUM(BC32:BN32) -> 0 | BQ65: =AVERAGE(C65:BN65) -> 0
A66: Total | N66: =SUM(N61:N65) -> 22.950029 | O66: =SUM(O61:O65) -> 20.948077 | P66: =SUM(P61:P65) -> 9.2331303 | Q66: =SUM(Q61:Q65) -> 16.139673 | R66: =SUM(R61:R65) -> 14.139222 | S66: =SUM(S61:S65) -> 5.5247501 | T66: =SUM(T61:T65) -> 1.008223 | U66: =SUM(U61:U65) -> 6.8737601 | ... BN66: =SUM(BN61:BN65) -> 27.775227 | BQ66: =AVERAGE(C66:BN66) -> 23.601687
A68: Annualized Change
A69: Equity | N69: =SUM(C36:N36) -> 39.349874 | O69: =SUM(D36:O36) -> 38.136495 | P69: =SUM(E36:P36) -> 27.159834 | Q69: =SUM(F36:Q36) -> 33.326843 | R69: =SUM(G36:R36) -> 34.777318 | S69: =SUM(H36:S36) -> 24.762863 | T69: =SUM(I36:T36) -> 18.074583 | U69: =SUM(J36:U36) -> 23.159683 | ... AQ69: =SUM(AF36:AQ36) -> 74.000357 | AR69: =AR61+AR53 -> 81.757631 | AS69: =AS61+AS53 -> 84.745596 | AT69: =AT61+AT53 -> 85.900496 | AU69: =AU61+AU53 -> 89.060228 | AV69: =AV61+AV53 -> 77.540209 | AW69: =AW61+AW53 -> 68.927456 | AX69: =AX61+AX53 -> 65.34147 | AY69: =AY61+AY53 -> 44.728264 | ... BD69: =BD61+BD53 -> 30.661257 | BE69: =BE4-AS4 -> 13.351967 | BF69: =BF4-AT4 -> 10.09473 | BG69: =BG4-AU4 -> 5.4062009 | BH69: =BH4-AV4 -> 26.172968 | BI69: =BI4-AW4 -> 24.099173 | BJ69: =BJ4-AX4 -> 19.328013 | BK69: =BK4-AY4 -> 26.814875 | BL69: =BL4-AZ4 -> 39.384879 | BM69: =BM4-AZ4 -> 20.393689 | BN69: =BN4-BA4 -> 44.72195 | BQ69: =AVERAGE(C69:BN69) -> 40.928082
A70: Debt | N70: =SUM(C37:N37) -> 8.03374 | O70: =SUM(D37:O37) -> 7.82104 | P70: =SUM(E37:P37) -> 7.67534 | Q70: =SUM(F37:Q37) -> 8.29214 | R70: =SUM(G37:R37) -> 7.89054 | S70: =SUM(H37:S37) -> 7.88434 | T70: =SUM(I37:T37) -> 7.94798 | U70: =SUM(J37:U37) -> 8.032994 | ... AQ70: =SUM(AF37:AQ37) -> 10.92654 | AR70: =AR62+AR54 -> 10.988434 | AS70: =AS62+AS54 -> 10.806702 | AT70: =AT62+AT54 -> 10.850886 | AU70: =AU62+AU54 -> 10.937276 | AV70: =AV62+AV54 -> 11.002126 | AW70: =AW62+AW54 -> 11.054448 | AX70: =AX62+AX54 -> 11.102286 | AY70: =AY62+AY54 -> 11.123834 | ... BD70: =BD62+BD54 -> 13.777628 | BE70: =BE5-AS5 -> 12.185974 | BF70: =BF5-AT5 -> 12.13519 | BG70: =BG5-AU5 -> 12.191412 | BH70: =BH5-AV5 -> 12.442246 | BI70: =BI5-AW5 -> 12.50863 | BJ70: =BJ5-AX5 -> 12.5743 | BK70: =BK5-AY5 -> 12.59904 | BL70: =BL5-AZ5 -> 12.72096 | BM70: =BM5-AZ5 -> 18.48702 | BN70: =BN5-BA5 -> 12.1073 | BQ70: =AVERAGE(C70:BN70) -> 10.397298
A71: Gold | N71: =SUM(C38:N38) -> 0.182 | O71: =SUM(D38:O38) -> -0.053214 | P71: =SUM(E38:P38) -> 0.025125 | Q71: =SUM(F38:Q38) -> 0.0195245 | R71: =SUM(G38:R38) -> 0.03835 | S71: =SUM(H38:S38) -> -0.0166535 | T71: =SUM(I38:T38) -> 0.0159 | U71: =SUM(J38:U38) -> 0.0184465 | ... AQ71: =SUM(AF38:AQ38) -> 0.3581355 | AR71: =AR63+AR55 -> 0.387546 | AS71: =AS63+AS55 -> 0.411873 | AT71: =AT63+AT55 -> 0.421736 | AU71: =AU63+AU55 -> 0.515081 | AV71: =AV63+AV55 -> 0.5966365 | AW71: =AW63+AW55 -> 0.481944 | AX71: =AX63+AX55 -> 0.4750165 | AY71: =AY63+AY55 -> 0.4965275 | ... BD71: =BD63+BD55 -> 0.586764 | BE71: =BE6-AS6 -> 1.579374 | BF71: =BF6-AT6 -> 1.9168305 | BG71: =BG6-AU6 -> 2.3240775 | BH71: =BH6-AV6 -> 2.212559 | BI71: =BI6-AW6 -> 2.5241685 | BJ71: =BJ6-AX6 -> 2.9147535 | BK71: =BK6-AY6 -> 3.9036365 | BL71: =BL6-AZ6 -> 3.38006 | BM71: =BM6-AZ6 -> 2.925104 | BN71: =BN6-BA6 -> 2.9960065 | BQ71: =AVERAGE(C71:BN71) -> 0.71692513
A72: Alternate | N72: =SUM(C39:N39) -> 0.10485 | O72: =SUM(D39:O39) -> 0.10485 | P72: =SUM(E39:P39) -> 0.10485 | Q72: =SUM(F39:Q39) -> 0.10485 | R72: =SUM(G39:R39) -> 0.10485 | S72: =SUM(H39:S39) -> 0.10485 | T72: =SUM(I39:T39) -> 0.10485 | U72: =SUM(J39:U39) -> 0.10485 | ... AI72: =SUM(X39:AI39) -> 0 | AJ72: =SUM(X39:AJ39) -> 0 | AK72: =SUM(Z39:AK39) -> 0 | AL72: =SUM(AA39:AL39) -> 0 | AM72: =SUM(AB39:AM39) -> 0 | AN72: =SUM(AC39:AN39) -> 0 | AO72: =SUM(AD39:AO39) -> 0 | AP72: =SUM(AE39:AP39) -> 0 | AQ72: =SUM(AF39:AQ39) -> 0 | AR72: =AR64+AR56 -> 0 | AS72: =AS64+AS56 -> 0 | AT72: =AT64+AT56 -> 0 | AU72: =AU64+AU56 -> 0 | AV72: =AV64+AV56 -> 0 | AW72: =AW64+AW56 -> 0 | AX72: =AX64+AX56 -> 0 | AY72: =AY64+AY56 -> 0 | ... BD72: =BD64+BD56 -> 0 | BE72: =BE7-AS7 -> 0 | BF72: =BF7-AT7 -> 0 | BG72: =BG7-AU7 -> 0 | BH72: =BH7-AV7 -> 0 | BI72: =BI7-AW7 -> 0 | BJ72: =BJ7-AX7 -> 0 | BK72: =BK7-AY7 -> 0 | BL72: =BL7-AZ7 -> 0 | BM72: =BM7-AZ7 -> 0 | BN72: =BN7-BA7 -> 0 | BQ72: =AVERAGE(C72:BN72) -> -0.010114151
A73: Liquid | N73: =SUM(C40:N40) -> -1.7924343 | O73: =SUM(D40:O40) -> -0.84252167 | P73: =SUM(E40:P40) -> 0.34396988 | Q73: =SUM(F40:Q40) -> 0.34435939 | R73: =SUM(G40:R40) -> -2.1591809 | S73: =SUM(H40:S40) -> -3.5198531 | T73: =SUM(I40:T40) -> -3.5291139 | U73: =SUM(J40:U40) -> -2.538389 | ... AQ73: =SUM(AF40:AQ40) -> -1 | AR73: =AR65+AR57 -> 0 | AS73: =AS65+AS57 -> 1.004973 | AT73: =AT65+AT57 -> 3.0221236 | AU73: =AU65+AU57 -> 3.0407111 | AV73: =AV65+AV57 -> 1.0422222 | AW73: =AW65+AW57 -> 0.52468656 | AX73: =AX65+AX57 -> -2 | AY73: =AY65+AY57 -> -4 | ... BD73: =BD65+BD57 -> 0 | BE73: =BE8-AS8 -> 0.9949802 | BF73: =BF8-AT8 -> -3.0221236 | BG73: =BG8-AU8 -> -3.0407111 | BH73: =BH8-AV8 -> -1.0422222 | BI73: =BI8-AW8 -> -0.52468656 | BJ73: =BJ8-AX8 -> 0 | BK73: =BK8-AY8 -> 0 | BL73: =BL8-AZ8 -> 0 | BM73: =BM8-AZ8 -> 0 | BN73: =BN8-BA8 -> -9 | BQ73: =AVERAGE(C73:BN73) -> -0.38937043
A74: Total | N74: =SUM(N69:N73) -> 45.87803 | O74: =SUM(O69:O73) -> 45.166649 | P74: =SUM(P69:P73) -> 35.309119 | Q74: =SUM(Q69:Q73) -> 42.087717 | R74: =SUM(R69:R73) -> 40.651877 | S74: =SUM(S69:S73) -> 29.215546 | T74: =SUM(T69:T73) -> 22.614199 | U74: =SUM(U69:U73) -> 28.777584 | ... BI74: =SUM(BI69:BI73) -> 38.607285 | BJ74: =BJ9-AX9 -> 34.817067 | BK74: =BK9-AY9 -> 43.317552 | BL74: =BL9-AZ9 -> 55.485899 | BM74: =BM9-AZ9 -> 41.805813 | BN74: =BN9-BA9 -> 50.825257 | BQ74: =AVERAGE(C74:BN74) -> 51.642821

Sheet Breakup
A1: Instrument | B1: Asset Type | C1: 44197 | D1: 44228 | E1: 44256 | F1: 44290 | G1: 44321 | H1: 44352 | I1: 44381 | J1: 44409 | K1: 44446 | L1: 44471 | M1: 44501 | N1: 44534 | O1: 44563 | P1: 44594 | Q1: 44625 | R1: 44653 | S1: 44682 | T1: 44717 | U1: 44744 | V1: 44774 | W1: 44807 | X1: 44835 | Y1: 44868 | Z1: 44898 | AA1: 44927 | AB1: 44960 | AC1: 44988 | AD1: 45018 | AE1: 45047 | AF1: 45080 | AG1: 45108 | AH1: 45143 | AI1: 45171 | AJ1: 45201 | AK1: 45234 | AL1: 45262 | AM1: 45292 | AN1: 45325 | AO1: 45354 | AP1: 45385 | AQ1: 45413 | AR1: 45446 | AS1: 45474 | AT1: 45506 | AU1: 45536 | AV1: 45567 | AW1: 45598 | AX1: 45627 | AY1: 45661 | AZ1: 45689 | BA1: 45718 | BB1: 45752 | BC1: 45779 | BD1: 45810 | BE1: 45845 | BF1: 45871 | BG1: 45901 | BH1: 45934 | BI1: 45962 | BJ1: 45992 | BK1: 46023 | BL1: 46054 | BM1: 46082 | BN1: 46114 | BO1: 46143 | BP1: Total | BQ1: CAGR | BR1: Average
C2: Value (Lakhs) | D2: Value (Lakhs) | E2: Value (Lakhs) | F2: Value (Lakhs) | G2: Value (Lakhs) | H2: Value (Lakhs) | I2: Value (Lakhs) | J2: Value (Lakhs) | K2: Value (Lakhs) | L2: Value (Lakhs) | M2: Value (Lakhs) | N2: Value (Lakhs) | O2: Value (Lakhs) | P2: Value (Lakhs) | Q2: Value (Lakhs) | R2: Value (Lakhs) | S2: Value (Lakhs) | T2: Value (Lakhs) | U2: Value (Lakhs) | V2: Value (Lakhs) | W2: Value (Lakhs) | X2: Value (Lakhs) | Y2: Value (Lakhs) | Z2: Value (Lakhs) | AA2: Value (Lakhs) | AB2: Value (Lakhs) | AC2: Value (Lakhs) | AD2: Value (Lakhs) | AE2: Value (Lakhs) | AF2: Value (Lakhs) | AG2: Value (Lakhs) | AH2: Value (Lakhs) | AI2: Value (Lakhs) | AJ2: Value (Lakhs) | AK2: Value (Lakhs) | AL2: Value (Lakhs) | AM2: Value (Lakhs) | AN2: Value (Lakhs) | AO2: Value (Lakhs) | AP2: Value (Lakhs) | AQ2: Value (Lakhs) | AR2: Value (Lakhs) | AS2: Value (Lakhs) | AT2: Value (Lakhs) | AU2: Value (Lakhs) | AV2: Value (Lakhs) | AW2: Value (Lakhs) | AX2: Value (Lakhs) | AY2: Value (Lakhs) | AZ2: Value (Lakhs) | BA2: Value (Lakhs) | BB2: Value (Lakhs) | BC2: Value (Lakhs) | BD2: Value (Lakhs) | BE2: Value (Lakhs) | BF2: Value (Lakhs) | BG2: Value (Lakhs) | BH2: Value (Lakhs) | BI2: Value (Lakhs) | BJ2: Value (Lakhs) | BK2: Value (Lakhs) | BL2: Value (Lakhs) | BM2: Value (Lakhs) | BN2: Value (Lakhs) | BO2: Value (Lakhs) | BQ2: =COUNTA($C2:BO2)-1 -> 64
A3: NET WORTH
A4: Stocks | B4: Equity | C4: ='20201227 E'!F72/100000 -> 18.841826 | D4: ='20210131 E'!F72/10^5 -> 19.928775 | E4: ='20210301 E'!F71/10^5 -> 20.107379 | F4: ='20210404 E'!F72/10^5 -> 21.044137 | G4: ='20210505 E'!F72/10^5 -> 22.165356 | H4: ='20210605 E'!F72/10^5 -> 24.364379 | I4: ='20210704 E'!$F82/10^5 -> 26.000709 | J4: ='20210801 E'!$F82/10^5 -> 27.72061 | K4: ='20210907 E'!$F82/10^5 -> 30.030264 | L4: ='20211002 E'!$F85/10^5 -> 32.005484 | M4: ='20211101 E'!$F85/10^5 -> 33.260255 | N4: ='20211204 E'!$F90/10^5 -> 33.827499 | O4: ='20220102 E'!$F90/10^5 -> 35.050812 | P4: ='20220202 E'!$F92/10^5 -> 36.934765 | Q4: ='20220305 E'!$F92/10^5 -> 33.95203 | R4: ='20220402 E'!$F94/10^5 -> 37.30111 | S4: ='20220501 E'!$F94/10^5 -> 37.925964 | T4: ='20220605 E'!$F94/10^5 -> 36.577079 | U4: ='20220702 E'!$F94/10^5 -> 35.422103 | V4: ='20220801 E'!$E104/10^5-V14-V6 -> 39.275389 | W4: ='20220903 E'!$E104/10^5-W14-W6 -> 40.663915 | X4: ='20221001 E'!$E104/10^5-X14-X6 -> 40.369198 | Y4: ='20221103 E'!$E104/10^5-Y14-Y6 -> 42.692985 | Z4: ='20221203 E'!$E104/10^5-Z14-Z6 -> 43.50794 | AA4: ='20230101 E'!$E104/10^5-AA14-AA6 -> 42.945084 | AB4: ='20230203 E'!$E104/10^5-AB14-AB6 -> 43.398321 | AC4: ='20230303 E'!$E104/10^5-AC14-AC6 -> 43.924913 | AD4: ='20230402 E'!$E104/10^5-AD14-AD6 -> 43.956908 | AE4: ='20230501 E'!$E104/10^5-AE14-AE6 -> 47.131961 | AF4: ='20230603 E'!$E104/10^5-AF14-AF6 -> 48.170796 | AG4: ='20230701 E'!$E104/10^5-AG14-AG6 -> 50.875904 | AH4: ='20230805 E'!$E104/10^5-AH14-AH6 -> 54.167471 | AI4: 55.3 | AJ4: ='20231002 E'!$E104/10^5-AJ14-AJ6 -> 57.247037 | AK4: ='20231104 E'!$E104/10^5-AK14-AK6 -> 57.059029 | AL4: ='20231202 E'!$E104/10^5-AL14-AL6 -> 61.72133 | AM4: ='20240101 E'!$E104/10^5-AM14-AM6 -> 64.968428 | AN4: ='20240203 E'!$E104/10^5-AN14-AN6 -> 67.029805 | AO4: ='20240303 E'!$E104/10^5-AO14-AO6 -> 69.949432 | AP4: ='20240403 E'!$E104/10^5-AP14-AP6 -> 71.432995 | AQ4: ='20240501 E'!$E104/10^5-AQ14-AQ6 -> 72.418569 | AR4: ='20240603 E'!$E104/10^5-AR14-AR6 -> 73.053824 | AS4: ='20240701 E'!$E104/10^5-AS14-AS6 -> 78.524933 | AT4: ='20240802 E'!$E104/10^5-AT14-AT6 -> 84.921035 | AU4: ='20240901 E'!$E104/10^5-AU14-AU6 -> 86.36144 | AV4: ='20241002 E'!$E104/10^5-AV14-AV6 -> 87.552213 | AW4: ='20241102 E'!$E104/10^5-AW14-AW6 -> 81.795471 | AX4: ='20241201 E'!$E104/10^5-AX14-AX6 -> 80.913654 | AY4: ='20250104 E'!$E104/10^5-AY14-AY6 -> 81.101257 | AZ4: ='20250201 E'!$E104/10^5-AZ14-AZ6 -> 75.643765 | BA4: ='20250302 E'!$F104/10^5-BA14-BA6 -> 69.665522 | BB4: ='20250405 E'!$F104/10^5-BB14-BB6 -> 63.515731 | BC4: ='20250502 E'!$F104/10^5-BC14-BC6 -> 66.140811 | BD4: ='20250602 E'!$F104/10^5-BD14-BD6 -> 68.636917 | BE4: ='20250707 E'!$F104/10^5-BE14-BE6 -> 71.137838 | BF4: ='20250802 E'!$F104/10^5-BF14-BF6 -> 68.136693 | BG4: ='20250901 E'!$F104/10^5-BG14-BG6 -> 69.489358 | BH4: ='20251004 E'!$F104/10^5-BH14-BH6 -> 65.671932 | BI4: ='20251101 E'!$F104/10^5-BI14-BI6 -> 67.973184 | BJ4: ='20251201 E'!$F104/10^5-BJ14-BJ6 -> 68.802067 | BK4: ='20260101 E'!$F104/10^5-BK14-BK6 -> 68.428467 | BL4: ='20260201 E'!$F104/10^5-BL14-BL6 -> 66.450526 | BM4: ='20260301 E'!$F104/10^5-BM14-BM6 -> 67.047305 | BN4: ='20260402 E'!$F104/10^5-BN14-BN6 -> 60.916095 | BO4: ='20260501 E'!$F104/10^5-BO14-BO6 -> 65.425624 | BQ4: =((BO4/C4)^(12/$BQ$2)-1) -> 0.26289477
A5: Mutual Funds | B5: Equity | C5: ='20201227 MF'!G9/100000 -> 22.528768 | D5: ='20210131 MF'!G10/10^5 -> 23.935691 | E5: ='20210301 MF'!G11/10^5 -> 27.988408 | F5: ='20210404 MF'!G11/10^5-F12 -> 28.733425 | G5: ='20210505 MF'!G12/10^5-G12 -> 26.242303 | H5: ='20210605 MF'!G12/10^5-H12 -> 29.973678 | I5: ='20210704 MF'!$G12/10^5-I12 -> 32.278218 | J5: ='20210801 MF'!$G12/10^5-J12 -> 34.354229 | K5: ='20210907 MF'!$G13/10^5-K12 -> 37.868912 | L5: ='20211002 MF'!$G13/10^5-L12 -> 38.786268 | M5: ='20211101 MF'!$G14/10^5-M12 -> 40.250964 | N5: ='20211204 MF'!$G14/10^5-N12 -> 41.382268 | O5: ='20220102 MF'!$G14/10^5-O12 -> 42.884657 | P5: ='20220202 MF'!$G14/10^5-P12 -> 43.616196 | Q5: ='20220305 MF'!$G14/10^5-Q12 -> 40.833591 | R5: ='20220402 MF'!$G14/10^5-R12 -> 44.522295 | S5: ='20220501 MF'!$G14/10^5-S12 -> 44.045013 | T5: ='20220605 MF'!$G14/10^5-T12 -> 42.023841 | U5: ='20220702 MF'!$G15/10^5-U12 -> 40.760408 | V5: ='20220801 MF'!$G15/10^5-V12 -> 45.271531 | W5: ='20220903 MF'!$G17/10^5 -> 47.060874 | X5: ='20221001 MF'!$G17/10^5 -> 48.258124 | Y5: ='20221103 MF'!$G17/10^5 -> 52.139563 | Z5: ='20221203 MF'!$G18/10^5 -> 54.554256 | AA5: ='20230101 MF'!$G18/10^5 -> 53.199567 | AB5: ='20230203 MF'!$G18/10^5 -> 55.592109 | AC5: ='20230303 MF'!$G18/10^5 -> 57.174449 | AD5: ='20230402 MF'!$G18/10^5 -> 57.221091 | AE5: ='20230501 MF'!$G18/10^5 -> 61.517382 | AF5: ='20230603 MF'!$G18/10^5 -> 67.028276 | AG5: ='20230701 MF'!$G18/10^5 -> 71.572927 | AH5: ='20230805 MF'!$G18/10^5 -> 76.341099 | AI5: ='20230902 MF'!$G18/10^5 -> 79.475351 | AJ5: ='20231002 MF'!$G18/10^5 -> 80.695174 | AK5: ='20231104 MF'!$G18/10^5 -> 81.613045 | AL5: ='20231202 MF'!$G18/10^5 -> 87.28175 | AM5: ='20240101 MF'!$G18/10^5 -> 92.290313 | AN5: ='20240203 MF'!$G18/10^5 -> 97.721712 | AO5: ='20240303 MF'!$G18/10^5 -> 101.9906 | AP5: ='20240403 MF'!$G18/10^5-AP12 -> 105.24401 | AQ5: ='20240501 MF'!$G18/10^5-AQ12 -> 109.03527 | AR5: ='20240603 MF'!$G18/10^5-AR12 -> 112.7996 | AS5: ='20240701 MF'!$G18/10^5-AS12 -> 121.89653 | AT5: ='20240802 MF'!$G18/10^5-AT12 -> 126.99713 | AU5: ='20240901 MF'!$G18/10^5-AU12 -> 130.90441 | AV5: ='20241002 MF'!$G18/10^5-AV12 -> 135.84023 | AW5: ='20241102 MF'!$G18/10^5-AW12 -> 131.56381 | AX5: ='20241201 MF'!$G18/10^5-AX12 -> 134.69568 | AY5: ='20250104 MF'!$G18/10^5-AY12 -> 139.89695 | AZ5: ='20250201 MF'!$G18/10^5-AZ12 -> 132.92801 | BA5: ='20250302 MF'!$G18/10^5-BA12 -> 125.40221 | BB5: ='20250405 MF'!$G22/10^5 -> 132.92903 | BC5: ='20250502 MF'!$G22/10^5-BC12 -> 139.9795 | BD5: ='20250602 MF'!$G22/10^5-BD12 -> 150.16653 | BE5: ='20250707 MF'!$G22/10^5-BE12 -> 159.49988 | BF5: ='20250802 MF'!$G22/10^5-(BF12-3) -> 158.00944 | BG5: ='20250901 MF'!$G22/10^5-(BG12) -> 158.94422 | BH5: ='20251004 MF'!$G22/10^5-(BH12) -> 164.12071 | BI5: ='20251101 MF'!$G22/10^5-(BI12) -> 170.82953 | BJ5: ='20251201 MF'!$G22/10^5-(BJ12) -> 169.95865 | BK5: ='20260101 MF'!$G22/10^5-(BK12) -> 170.99076 | BL5: ='20260201 MF'!$G22/10^5-(BL12) -> 167.84013 | BM5: ='20260301 MF'!$G22/10^5-(BM12) -> 165.3853 | BN5: ='20260402 MF'!$G22/10^5-(BN12) -> 154.06532 | BO5: ='20260501 MF'!$G22/10^5-(BO12) -> 174.94108 | BQ5: =((BO5/C5)^(12/$BQ$2)-1) -> 0.46860142
A6: Gold | B6: Gold | C6: 1 | D6: =(48992.7+49393.7+24250)/10^5 -> 1.226364 | E6: =(47500+47050+4672.5*5)/10^5 -> 1.179125 | F6: =(47102.5+46300+4620.01*5)/10^5 -> 1.1650255 | G6: =0.481303+0.475+0.0472494*5 -> 1.19255 | H6: =0.483451+0.48788+0.0481845*5 -> 1.2122535 | I6: =0.4799+0.2375+0.4777 -> 1.1951 | J6: =0.47949+0.0472947*5+0.475 -> 1.1909635 | K6: =0.4725+0.0467396*5+0.4713 -> 1.177498 | L6: =0.4734+0.04623*5+0.4688 -> 1.17335 | M6: =0.4764+0.04692*5+0.4726 -> 1.1836 | N6: =0.481+0.235+0.471 -> 1.187 | O6: =0.477+0.235+0.47 -> 1.182 | P6: =0.4681+0.04611*5+0.4745 -> 1.17315 | Q6: =0.488+0.04765*5+0.478 -> 1.20425 | R6: =0.4765+0.04721*5+0.472 -> 1.18455 | S6: =0.484+0.0499*5+0.4974 -> 1.2309 | T6: =0.4817+0.0476*5+0.4759 -> 1.1956 | U6: =0.493+0.04798*5+0.4781 -> 1.211 | V6: =SUM('20220801 E'!$E81:$E83)/10^5 -> 1.20941 | W6: =SUM('20220903 E'!$E81:$E83)/10^5 -> 1.237212 | X6: =SUM('20221001 E'!$E79:$E81)/10^5 -> 1.2162 | Y6: =SUM('20221103 E'!$E79:$E81)/10^5 -> 1.2255 | Z6: =SUM('20221203 E'!$E77:$E79)/10^5 -> 1.244142 | AA6: =SUM('20230101 E'!$E80:$E82)/10^5 -> 1.296137 | AB6: =SUM('20230203 E'!$E79:$E81)/10^5 -> 1.3329095 | AC6: =SUM('20230303 E'!$E79:$E81)/10^5 -> 1.319885 | AD6: =SUM('20230402 E'!$E79:$E81)/10^5 -> 1.382417 | AE6: =SUM('20230501 E'!$E79:$E81)/10^5 -> 1.438085 | AF6: =SUM('20230603 E'!$E75:$E77)/10^5 -> 1.4930505 | AG6: =SUM('20230701 E'!$E78:$E80)/10^5 -> 1.473594 | AH6: =SUM('20230805 E'!$E78:$E80)/10^5 -> 1.48084 | AI6: 1.48 | AJ6: =SUM('20231002 E'!$E78:$E80)/10^5 -> 1.468757 | AK6: =SUM('20231104 E'!$E78:$E80)/10^5 -> 1.49145 | AL6: =SUM('20231202 E'!$E78:$E80)/10^5 -> 1.5340975 | AM6: =SUM('20240101 E'!$E72:$E74)/10^5 -> 1.559774 | AN6: =SUM('20240203 E'!$E72:$E74)/10^5 -> 1.5777485 | AO6: =SUM('20240303 E'!$E73:$E75)/10^5 -> 1.5636445 | AP6: =SUM('20240403 E'!$E76:$E78)/10^5 -> 1.676741 | AQ6: =SUM('20240501 E'!$E76:$E78)/10^5 -> 1.774461 | AR6: =SUM('20240603 E'!$E75:$E77)/10^5 -> 1.851186 | AS6: =SUM('20240701 E'!$E75:$E77)/10^5 -> 1.86114 | AT6: =SUM('20240802 E'!$E75:$E77)/10^5 -> 1.892713 | AU6: =SUM('20240901 E'!$E75:$E77)/10^5 -> 1.901736 | AV6: =SUM('20241002 E'!$E78:$E80)/10^5 -> 1.983838 | AW6: =SUM('20241102 E'!$E78:$E80)/10^5 -> 2.0880865 | AX6: =SUM('20241201 E'!$E78:$E80)/10^5 -> 2.0160415 | AY6: =SUM('20250104 E'!$E79:$E81)/10^5 -> 2.0347905 | AZ6: =SUM('20250201 E'!$E79:$E81)/10^5 -> 2.074276 | BA6: =SUM('20250302 E'!$F79:$F81)/10^5 -> 2.12949 | BB6: =SUM('20250405 E'!$F65:$F67)/10^5 -> 2.190049 | BC6: =SUM('20250502 E'!$F65:$F67)/10^5 -> 2.2806 | BD6: =SUM('20250602 E'!$F65:$F67)/10^5 -> 2.363767 | BE6: =SUM('20250707 E'!$F66:$F68)/10^5 -> 2.447904 | BF6: =('20250802 E'!$F32+SUM('20250802 E'!$F67:$F69))/10^5 -> 3.472087 | BG6: =('20250901 E'!$F32+SUM('20250901 E'!$F67:$F69))/10^5 -> 3.8185665 | BH6: =('20251004 E'!$F33+SUM('20251004 E'!$F67:$F69))/10^5 -> 4.3079155 | BI6: =('20251101 E'!$F33+SUM('20251101 E'!$F67:$F69))/10^5 -> 4.3006455 | BJ6: =('20251201 E'!$F33+SUM('20251201 E'!$F67:$F69))/10^5 -> 4.54021 | BK6: =('20260101 E'!$F33+SUM('20260101 E'!$F67:$F69))/10^5 -> 4.949544 | BL6: =('20260201 E'!$F32+SUM('20260201 E'!$F67:$F69))/10^5 -> 5.9779125 | BM6: =('20260301 E'!$F32+SUM('20260301 E'!$F67:$F69))/10^5 -> 5.50955 | BN6: =('20260402 E'!$F33+SUM('20260402 E'!$F67:$F69))/10^5 -> 5.054594 | BO6: =('20260501 E'!$F32+SUM('20260501 E'!$F67:$F69))/10^5 -> 5.1860555 | BQ6: =((BO6/C6)^(12/$BQ$2)-1) -> 0.3615449
A7: NPS E | B7: Equity | C7: 4.55 | D7: =2.82+3.17 -> 5.99 | E7: =3.01+3.39 -> 6.4 | F7: =2.763+3.096 -> 5.859 | G7: =2.74+3.06 -> 5.8 | H7: =2.97+3.32 -> 6.29 | I7: =3+3.349 -> 6.349 | J7: =3.044+3.3784 -> 6.4224 | K7: =3.2997+3.6962 -> 6.9959 | L7: =3.67+3.74 -> 7.41 | M7: =3.71+3.77 -> 7.48 | N7: =3.6+3.67 -> 7.27 | O7: =3.64+3.695 -> 7.335 | P7: =3.7+3.74 -> 7.44 | Q7: =3.41+3.46 -> 6.87 | R7: =3.55+3.59 -> 7.14 | S7: =3.484+3.53 -> 7.014 | T7: =3.4+3.39 -> 6.79 | U7: =3.276+3.244 -> 6.52 | V7: =3.56+3.55 -> 7.11 | W7: =4.02+3.67 -> 7.69 | X7: =3.92+3.59 -> 7.51 | Y7: =4.12+3.78 -> 7.9 | Z7: =4.239+3.877 -> 8.116 | AA7: =4.11+3.76 -> 7.87 | AB7: =4.027+3.672 -> 7.699 | AC7: =4.028+3.703 -> 7.731 | AD7: =3.986+3.654 -> 7.64 | AE7: =4.185+3.847 -> 8.032 | AF7: =4.332+3.993 -> 8.325 | AG7: =4.48+4.15 -> 8.63 | AH7: =4.946+4.994 -> 9.94 | AI7: =4.971+5.032 -> 10.003 | AJ7: =4.98+5.07 -> 10.05 | AK7: =4.93+5.03 -> 9.96 | AL7: =5.215+5.3138 -> 10.5288 | AM7: =5.574+5.694 -> 11.268 | AN7: =5.638+5.804 -> 11.442 | AO7: =5.837+5.992 -> 11.829 | AP7: =5.62+5.76 -> 11.38 | AQ7: =5.705+5.837 -> 11.542 | AR7: =5.766+5.905 -> 11.671 | AS7: =6.145+6.27 -> 12.415 | AT7: =6.77+6.506 -> 13.276 | AU7: =6.845+6.568 -> 13.413 | AV7: =7+6.66 -> 13.66 | AW7: =6.555+6.258 -> 12.813 | AX7: =6.555+6.295 -> 12.85 | AY7: =6.53+6.34 -> 12.87 | AZ7: =6.31+6.04 -> 12.35 | BA7: =5.9+5.62 -> 11.52 | BB7: =5.86+5.63 -> 11.49 | BC7: =6.21+5.92 -> 12.13 | BD7: =6.37+6.065 -> 12.435 | BE7: =6.57+6.29 -> 12.86 | BF7: =6.33+6.07 -> 12.4 | BG7: =6.33+6.01 -> 12.34 | BH7: =6.472+6.194 -> 12.666 | BI7: =6.772+6.77054 -> 13.54254 | BJ7: =6.88491+6.91288 -> 13.79779 | BK7: =6.872+6.905 -> 13.777 | BL7: =6.71+6.736 -> 13.446 | BM7: =6.77+6.77 -> 13.54 | BN7: =6.01+5.99 -> 12 | BO7: =6.11+6.18 -> 12.29 | BQ7: =((BO7/C7)^(12/$BQ$2)-1) -> 0.2047969
A8: NPS C | B8: Debt | C8: 0.45 | D8: =0.26+0.285 -> 0.545 | E8: =0.258+0.282 -> 0.54 | F8: =0.262+0.286 -> 0.548 | G8: =0.374+0.4188 -> 0.7928 | H8: =0.376+0.422 -> 0.798 | I8: =0.376+0.422 -> 0.798 | J8: =0.3783+0.4248 -> 0.8031 | K8: =0.38257+0.4293 -> 0.81187 | L8: =0.435+0.431 -> 0.866 | M8: =0.43+0.43 -> 0.86 | N8: =0.43+0.43 -> 0.86 | O8: =0.438+0.435 -> 0.873 | P8: =0.438+0.435 -> 0.873 | Q8: =0.439+0.437 -> 0.876 | R8: =0.44+0.44 -> 0.88 | S8: =0.469+0.476 -> 0.945 | T8: =0.461+0.467 -> 0.928 | U8: =0.463+0.47 -> 0.933 | V8: =0.468+0.475 -> 0.943 | W8: =0.524+0.481 -> 1.005 | X8: =0.534+0.498 -> 1.032 | Y8: =0.536+0.48 -> 1.016 | Z8: =0.541+0.487 -> 1.028 | AA8: =0.544+0.489 -> 1.033 | AB8: =0.547+0.492 -> 1.039 | AC8: =0.547+0.492 -> 1.039 | AD8: =0.531+0.485 -> 1.016 | AE8: =0.5385+0.4922 -> 1.0307 | AF8: =0.544+0.497 -> 1.041 | AG8: =0.5454+0.499 -> 1.0444 | AH8: =0.598+0.601 -> 1.199 | AI8: =0.602+0.604 -> 1.206 | AJ8: =0.604+0.607 -> 1.211 | AK8: =0.606+0.609 -> 1.215 | AL8: =0.6098+0.6119 -> 1.2217 | AM8: =0.614+0.617 -> 1.231 | AN8: =0.6211+0.6234 -> 1.2445 | AO8: =0.625+0.627 -> 1.252 | AP8: =0.744+0.761 -> 1.505 | AQ8: =0.745+0.763 -> 1.508 | AR8: =0.752+0.76958 -> 1.52158 | AS8: =0.757+0.7748 -> 1.5318 | AT8: =0.814+0.782 -> 1.596 | AU8: =0.82+0.787 -> 1.607 | AV8: =0.831+0.797 -> 1.628 | AW8: =0.837+0.803 -> 1.64 | AX8: =0.842+0.806 -> 1.648 | AY8: =0.848+0.812 -> 1.66 | AZ8: =0.852+0.818 -> 1.67 | BA8: =0.853+0.818 -> 1.671 | BB8: =0.939+0.901 -> 1.84 | BC8: =0.948+0.9098 -> 1.8578 | BD8: =0.96+0.92 -> 1.88 | BE8: =0.96+0.92 -> 1.88 | BF8: =0.968+0.928 -> 1.896 | BG8: =0.965+0.925 -> 1.89 | BH8: =0.972+0.932 -> 1.904 | BI8: =0.993+0.99683 -> 1.98983 | BJ8: =0.9998+1.00304 -> 2.00284 | BK8: =1+1.0044 -> 2.0044 | BL8: =0.998+1.001 -> 1.999 | BM8: =1.01+1.008 -> 2.018 | BN8: =1.01+1.008 -> 2.018 | BO8: =1.05+1.06 -> 2.11 | BQ8: =((BO8/C8)^(12/$BQ$2)-1) -> 0.33605893
A9: NPS G | B9: Debt | C9: 0.67 | D9: =0.392+0.421 -> 0.813 | E9: =0.379+0.401 -> 0.78 | F9: =0.386+0.415 -> 0.801 | G9: =0.5586+0.627 -> 1.1856 | H9: =0.5579+0.631 -> 1.1889 | I9: =0.5548+0.6298 -> 1.1846 | J9: =0.5555+0.63033 -> 1.18583 | K9: =0.5673+0.64075 -> 1.20805 | L9: =0.645+0.643 -> 1.288 | M9: =0.64+0.64 -> 1.28 | N9: =0.65+0.65 -> 1.3 | O9: =0.65+0.65 -> 1.3 | P9: =0.64+0.64 -> 1.28 | Q9: =0.644+0.644 -> 1.288 | R9: =0.6476+0.6469 -> 1.2945 | S9: =0.701+0.711 -> 1.412 | T9: =0.687+0.702 -> 1.389 | U9: =0.694+0.707 -> 1.401 | V9: =0.702+0.715 -> 1.417 | W9: =0.79+0.72 -> 1.51 | X9: =0.799+0.722 -> 1.521 | Y9: =0.802+0.726 -> 1.528 | Z9: =0.817+0.739 -> 1.556 | AA9: =0.816+0.739 -> 1.555 | AB9: =0.824+0.746 -> 1.57 | AC9: =0.824+0.745 -> 1.569 | AD9: =0.797+0.726 -> 1.523 | AE9: =0.809+0.7393 -> 1.5483 | AF9: =0.82+0.751 -> 1.571 | AG9: =0.817+0.748 -> 1.565 | AH9: =0.894+0.8988 -> 1.7928 | AI9: =0.901+0.906 -> 1.807 | AJ9: =0.901+0.905 -> 1.806 | AK9: =0.901+0.905 -> 1.806 | AL9: =0.905+0.91 -> 1.815 | AM9: =0.919+0.923 -> 1.842 | AN9: =0.941+0.9425 -> 1.8835 | AO9: =0.947+0.9487 -> 1.8957 | AP9: =1.11+1.138 -> 2.248 | AQ9: =1.109+1.135 -> 2.244 | AR9: =1.1304+1.1561 -> 2.2865 | AS9: =1.14+1.167 -> 2.307 | AT9: =1.227+1.1788 -> 2.4058 | AU9: =1.24+1.18 -> 2.42 | AV9: =1.26+1.21 -> 2.47 | AW9: =1.259+1.208 -> 2.467 | AX9: =1.262+1.2129 -> 2.4749 | AY9: =1.268+1.219 -> 2.487 | AZ9: =1.278+1.229 -> 2.507 | BA9: =1.273+1.227 -> 2.5 | BB9: =1.539+1.476 -> 3.015 | BC9: =1.562+1.4979 -> 3.0599 | BD9: =1.566+1.5057 -> 3.0717 | BE9: =1.54+1.49 -> 3.03 | BF9: =1.544+1.49 -> 3.034 | BG9: =1.505+1.459 -> 2.964 | BH9: =1.537+1.486 -> 3.023 | BI9: =1.551+1.57584 -> 3.12684 | BJ9: =1.551+1.57687 -> 3.12787 | BK9: =1.5586+1.58561 -> 3.14421 | BL9: =1.556+1.584 -> 3.14 | BM9: =1.567+1.5957 -> 3.1627 | BN9: =1.529+1.563 -> 3.092 | BO9: =1.865+1.871 -> 3.736 | BQ9: =((BO9/C9)^(12/$BQ$2)-1) -> 0.38018487
A10: PF | B10: Debt | C10: 13.39 | D10: 13.62 | E10: 14.09 | F10: 15.44 | G10: =15.67 -> 15.67 | H10: =15.903 -> 15.903 | I10: =H10+0.12273+0.11023 -> 16.13596 | J10: =I10+0.12273+0.11023 -> 16.36892 | K10: =J10+0.12273+0.11023 -> 16.60188 | L10: =K10+0.12273+0.11023 -> 16.83484 | M10: =L10+0.2753 -> 17.11014 | N10: =M10+0.1439+0.1314 -> 17.38544 | O10: =N10+0.1439+0.1314 -> 17.66074 | P10: =O10+0.1439+0.1314 -> 17.93604 | Q10: =P10+0.1439+0.1314 -> 18.21134 | R10: =Q10+0.1439+0.1314+1.52 -> 20.00664 | S10: =R10+0.1439+0.1314 -> 20.28194 | T10: =S10+0.1439+0.1314 -> 20.55724 | U10: =T10+0.1439+0.1314 -> 20.83254 | V10: =U10+0.1439+0.1314 -> 21.10784 | W10: =V10+0.1439+0.1314 -> 21.38314 | X10: =W10+0.1439+0.1314 -> 21.65844 | Y10: =X10+0.1439+0.1314 -> 21.93374 | Z10: =Y10+0.1655*2+0.153*2 -> 22.57074 | AA10: =Z10+0.1655+0.153 -> 22.88924 | AB10: =AA10+0.1655+0.153 -> 23.20774 | AC10: =AB10+0.1655+0.153 -> 23.52624 | AD10: =25.40307 -> 25.40307 | AE10: =AD10+0.1655+0.153 -> 25.72157 | AF10: =AE10+0.1655+0.153 -> 26.04007 | AG10: =AF10+0.1655+0.153 -> 26.35857 | AH10: =AG10+0.1655+0.153 -> 26.67707 | AI10: =AH10+0.1655+0.153 -> 26.99557 | AJ10: =AI10+0.1655+0.153 -> 27.31407 | AK10: =AJ10+0.18204+0.16954 -> 27.66565 | AL10: =AK10+0.18204+0.16954 -> 28.01723 | AM10: =AL10+0.18204+0.16954 -> 28.36881 | AN10: =AM10+0.18204+0.16954 -> 28.72039 | AO10: =AN10+0.18204+0.16954 -> 29.07197 | AP10: 31.73 | AQ10: =AP10+0.18204+0.16954 -> 32.08158 | AR10: =AQ10+0.18204+0.16954 -> 32.43316 | AS10: =AR10+0.18204+0.16954 -> 32.78474 | AT10: =AS10+0.18204+0.16954 -> 33.13632 | AU10: =AT10+0.18204+0.16954 -> 33.4879 | AV10: =AU10+0.18204+0.16954 -> 33.83948 | AW10: =AV10+0.20934+0.19684 -> 34.24566 | AX10: =AW10+0.20934+0.19684 -> 34.65184 | AY10: =AX10+0.20934+0.19684 -> 35.05802 | AZ10: =AY10+0.20934+0.19684 -> 35.4642 | BA10: =AZ10+0.20934+0.19684 -> 35.87038 | BB10: =BA10+0.20934+0.19684+2.92 -> 39.19656 | BC10: =BB10+0.20934+0.19684 -> 39.60274 | BD10: =BC10+0.20934+0.19684 -> 40.00892 | BE10: =BD10+0.20934+0.19684 -> 40.4151 | BF10: =BE10+0.20934+0.19684 -> 40.82128 | BG10: =BF10+0.20934+0.19684 -> 41.22746 | BH10: =BG10+0.20934+0.19684 -> 41.63364 | BI10: =BH10+0.24378+0.23128 -> 42.1087 | BJ10: =BI10+0.24378+0.23128 -> 42.58376 | BK10: =BJ10+0.24378+0.23128 -> 43.05882 | BL10: =BK10+0.24378+0.23128 -> 43.53388 | BM10: =BL10+0.24378+0.23128 -> 44.00894 | BN10: =BM10+0.24378+0.23128+3 -> 47.484 | BO10: =BN10+0.24378+0.23128 -> 47.95906 | BQ10: =((BO10/C10)^(12/$BQ$2)-1) -> 0.27025786
A11: PPF | B11: Debt | C11: 17.71 | D11: 17.71 | E11: 17.71 | F11: 18.92 | G11: =F11 -> 18.92 | H11: =F11 -> 18.92 | I11: =H11 -> 18.92 | J11: =F11 -> 18.92 | K11: =F11 -> 18.92 | L11: =K11+1.5 -> 20.42 | M11: =L11 -> 20.42 | N11: =L11 -> 20.42 | O11: =M11 -> 20.42 | P11: =O11 -> 20.42 | Q11: =O11 -> 20.42 | R11: =P11+1.4 -> 21.82 | S11: =R11 -> 21.82 | T11: =S11 -> 21.82 | U11: =T11 -> 21.82 | V11: =U11 -> 21.82 | W11: =T11+1.5 -> 23.32 | X11: =W11 -> 23.32 | Y11: =X11 -> 23.32 | Z11: =Y11 -> 23.32 | AA11: =Z11 -> 23.32 | AB11: =Z11 -> 23.32 | AC11: =AA11 -> 23.32 | AD11: 24.93 | AE11: 24.93 | AF11: 24.93 | AG11: 24.93 | AH11: =24.93+1.5 -> 26.43 | AI11: =AH11 -> 26.43 | AJ11: =AI11 -> 26.43 | AK11: =AJ11 -> 26.43 | AL11: =AK11 -> 26.43 | AM11: =AK11 -> 26.43 | AN11: =AK11 -> 26.43 | AO11: =AK11 -> 26.43 | AP11: =AO11+1.8408 -> 28.2708 | AQ11: =AP11 -> 28.2708 | AR11: =AQ11 -> 28.2708 | AS11: =AR11 -> 28.2708 | AT11: =AS11+1.5 -> 29.7708 | AU11: =AT11 -> 29.7708 | AV11: =AU11 -> 29.7708 | AW11: =AV11 -> 29.7708 | AX11: =AW11 -> 29.7708 | AY11: =AX11 -> 29.7708 | AZ11: =AY11 -> 29.7708 | BA11: =AZ11 -> 29.7708 | BB11: =AZ11+1.5+2.075 -> 33.3458 | BC11: =BB11 -> 33.3458 | BD11: =BC11 -> 33.3458 | BE11: =BD11 -> 33.3458 | BF11: =BE11 -> 33.3458 | BG11: =BF11 -> 33.3458 | BH11: =BG11 -> 33.3458 | BI11: =BH11 -> 33.3458 | BJ11: =BI11 -> 33.3458 | ... BM11: =BL11 -> 33.3458 | BN11: =BM11+2.36 -> 35.7058 | BO11: =BN11 -> 35.7058 | BQ11: =((BO11/C11)^(12/$BQ$2)-1) -> 0.14050591
A12: Cash | B12: Liquid | C12: 4.65 | D12: 3.2 | E12: 1 | F12: ='20210404 MF'!G4/100000 -> 1.0035016 | G12: ='20210505 MF'!G4/10^5 -> 3.5108187 | H12: ='20210605 MF'!G4/10^5 -> 3.5198853 | I12: ='20210704 MF'!$G4/10^5 -> 3.5291139 | J12: ='20210801 MF'!$G4/10^5 -> 2.538389 | K12: ='20210907 MF'!$G4/10^5 -> 2.0454896 | L12: ='20211002 MF'!$G4/10^5 -> 4.3487874 | M12: ='20211101 MF'!$G4/10^5 -> 3.3509365 | N12: ='20211204 MF'!$G4/10^5 -> 2.3510604 | O12: ='20220102 MF'!$G4/10^5 -> 2.8575657 | P12: ='20220202 MF'!$G4/10^5 -> 2.3574783 | Q12: ='20220305 MF'!$G4/10^5 -> 1.3439699 | R12: ='20220402 MF'!$G4/10^5 -> 1.347861 | S12: ='20220501 MF'!$G4/10^5 -> 1.3516378 | T12: ='20220605 MF'!$G4/10^5 -> 3.2196e-05 | U12: 0 | V12: 0 | W12: 4 | X12: 2.5 | Y12: 0 | Z12: 0 | AA12: 1.5 | AB12: 1.5 | AC12: 1.5 | AD12: 3 | AE12: 2 | AF12: 1 | AG12: 0 | AH12: 2 | AI12: 0 | AJ12: 0 | AK12: 0 | AL12: 0 | AM12: 2 | AN12: 4 | AO12: 0 | AP12: ='20240403 MF'!$G$5/10^5 -> 2.0134634 | AQ12: ='20240501 MF'!$G$5/10^5 -> 2.0247026 | AR12: 0 | AS12: 0 | AT12: ='20240802 MF'!$G5/10^5 -> 3.004973 | AU12: ='20240901 MF'!$G5/10^5 -> 3.0221236 | AV12: ='20241002 MF'!$G6/10^5 -> 3.0407111 | AW12: ='20241102 MF'!$G6/10^5 -> 1.0422222 | AX12: ='20241201 MF'!$G6/10^5 -> 0.52468656 | AY12: 0 | AZ12: 0 | BA12: 0 | BB12: 9 | BC12: ='20250502 MF'!F3/10^5 -> 6.0001144 | BD12: ='20250602 MF'!F3/10^5 -> 4.411282 | BE12: 0 | BF12: ='20250802 MF'!F6/10^5+3 -> 3.9999532 | BG12: 0 | BH12: 0 | BI12: 0 | BJ12: 0 | BK12: 0 | BL12: 0 | BM12: 0 | BN12: 0 | BO12: 0
A13: Crypto | B13: Alternate | C13: 0 | D13: 0 | E13: 0 | F13: 0 | G13: 0 | H13: 0 | I13: 0 | J13: 0 | K13: 0.10485 | L13: 0.54 | M13: 0.73 | N13: 0 | O13: 0 | P13: 0 | Q13: 0 | R13: 0 | S13: 0 | T13: 0 | U13: 0 | V13: 0 | W13: 0 | X13: 0 | Y13: 0 | Z13: 0 | AA13: 0 | AB13: 0 | AC13: 0 | AD13: 0 | AE13: 0 | AF13: 0 | AG13: 0 | AH13: 0 | AI13: 0 | AJ13: 0 | AK13: 0 | AL13: 0 | AM13: 0 | AN13: 0 | AO13: 0 | AP13: 0 | AQ13: 0 | AR13: 0 | AS13: 0 | AT13: 0 | AU13: 0 | AV13: 0 | AW13: 0 | AX13: 0 | AY13: 0 | AZ13: 0 | BA13: 0 | BB13: 0 | BC13: 0 | BD13: 0 | BE13: 0 | BF13: 0 | BG13: 0 | BH13: 0 | BI13: 0 | BJ13: 0 | BK13: 0 | BL13: 0 | BM13: 0 | BN13: 0 | BO13: 0
A14: Bonds | B14: Debt | C14: 0.31 | D14: 0.31 | E14: =D14 -> 0.31 | F14: =E14 -> 0.31 | G14: =F14 -> 0.31 | H14: =F14 -> 0.31 | I14: =H14 -> 0.31 | J14: =F14 -> 0.31 | K14: =F14 -> 0.31 | L14: =G14 -> 0.31 | M14: =G14 -> 0.31 | N14: =G14 -> 0.31 | O14: =M14 -> 0.31 | P14: =O14 -> 0.31 | Q14: =P14 -> 0.31 | R14: =O14 -> 0.31 | S14: =R14 -> 0.31 | T14: =O14 -> 0.31 | U14: =O14 -> 0.31 | V14: =('20220801 E'!$E2+'20220801 E'!$E76)/10^5 -> 0.333004 | W14: =('20220903 E'!$E2+'20220903 E'!$E76)/10^5 -> 0.33315 | X14: =('20221001 E'!$E2+'20221001 E'!$E75)/10^5 -> 0.329394 | Y14: =('20221103 E'!$E2+'20221103 E'!$E75)/10^5 -> 0.335502 | Z14: =('20221203 E'!$E2+'20221203 E'!$E73)/10^5 -> 0.31719 | AA14: =('20230101 E'!$E2+'20230101 E'!$E74)/10^5 -> 0.31979 | AB14: =('20230203 E'!$E2+'20230203 E'!$E73)/10^5 -> 0.3218 | AC14: =('20230303 E'!$E2+'20230303 E'!$E73)/10^5 -> 0.324582 | AD14: =('20230402 E'!$E2+'20230402 E'!$E73)/10^5 -> 0.3202 | AE14: =('20230501 E'!$E2+'20230501 E'!$E73)/10^5 -> 0.319202 | AF14: =('20230603 E'!$E2+'20230603 E'!$E71)/10^5 -> 0.3252 | AG14: =('20230701 E'!$E2+'20230701 E'!$E74)/10^5 -> 0.328076 | AH14: =('20230805 E'!$E2+'20230805 E'!$E74)/10^5 -> 0.3304 | AI14: 0.33 | AJ14: =('20231002 E'!$E2+'20231002 E'!$E74)/10^5 -> 0.33282 | AK14: =('20231104 E'!$E2+'20231104 E'!$E74)/10^5 -> 0.32857 | AL14: =('20231202 E'!$E2+'20231202 E'!$E74)/10^5 -> 0.317898 | AM14: =('20240101 E'!$E2+'20240101 E'!$E68)/10^5 -> 0.31473 | AN14: =('20240203 E'!$E2+'20240203 E'!$E68)/10^5 -> 0.323202 | AO14: =('20240303 E'!$E2+'20240303 E'!$E69)/10^5 -> 0.32424 | AP14: =('20240403 E'!$E2+'20240403 E'!$E72)/10^5 -> 0.318464 | AQ14: =('20240501 E'!$E2+'20240501 E'!$E72)/10^5 -> 0.31998 | AR14: =('20240603 E'!$E2+'20240603 E'!$E3)/10^5 -> 0.320254 | AS14: =('20240701 E'!$E2+'20240701 E'!$E71)/10^5 -> 0.31835 | AT14: =('20240802 E'!$E2+'20240802 E'!$E71)/10^5 -> 0.327166 | AU14: =('20240901 E'!$E2+'20240901 E'!$E71)/10^5 -> 0.33387 | AV14: =('20241002 E'!$E2+'20241002 E'!$E74)/10^5 -> 0.323 | AW14: =('20241102 E'!$E2+'20241102 E'!$E74)/10^5 -> 0.324 | AX14: =('20241201 E'!$E2+'20241201 E'!$E3)/10^5 -> 0.31085 | AY14: =('20250104 E'!$E2+'20250104 E'!$E3)/10^5 -> 0.31312 | AZ14: =('20250201 E'!$E2+'20250201 E'!$E3)/10^5 -> 0.31354 | BA14: =('20250302 E'!$F2+'20250302 E'!$F76)/10^5 -> 0.3157 | BB14: =('20250405 E'!$F2+'20250405 E'!$F3)/10^5 -> 0.3162 | BC14: =('20250502 E'!$F2+'20250502 E'!$F62)/10^5 -> 0.316002 | BD14: =('20250602 E'!$F2+'20250602 E'!$F3)/10^5 -> 0.315652 | BE14: =('20250707 E'!$F2+'20250707 E'!$F63)/10^5 -> 0.32137 | BF14: =('20250802 E'!$F2+'20250802 E'!$F64)/10^5 -> 0.32498 | BG14: =('20250901 E'!$F2+'20250901 E'!$F64)/10^5 -> 0.3275 | BH14: =('20251004 E'!$F2+'20251004 E'!$F3)/10^5 -> 0.316252 | BI14: =('20251101 E'!$F2+'20251101 E'!$F3)/10^5 -> 0.318536 | BJ14: =('20251201 E'!$F2+'20251201 E'!$F3)/10^5 -> 0.30475 | BK14: =('20260101 E'!$F2+'20260101 E'!$F3)/10^5 -> 0.31001 | BL14: =('20260201 E'!$F2+'20260201 E'!$F64)/10^5 -> 0.3059 | BM14: =('20260301 E'!$F2+'20260301 E'!$F64)/10^5 -> 0.3134 | BN14: =('20260402 E'!$F2+'20260402 E'!$F3)/10^5 -> 0.3151 | BO14: =('20260501 E'!$F2+'20260501 E'!$F64)/10^5 -> 0.31 | BQ14: =((BO14/C14)^(12/$BQ$2)-1) -> 0
A15: Total | C15: =SUM(C4:C14) -> 84.100595 | D15: =SUM(D4:D14) -> 87.27883 | E15: =SUM(E4:E14) -> 90.104912 | F15: =SUM(F4:F14) -> 93.824089 | G15: =SUM(G4:G14) -> 95.789428 | H15: =SUM(H4:H14) -> 102.4801 | I15: =SUM(I4:I14) -> 106.7007 | J15: =SUM(J4:J14) -> 109.81444 | ... BO15: =SUM(BO4:BO14) -> 347.66362 | BQ15: =((BO15/C15)^(12/$BQ$2)-1) -> 0.30487087
A17: CONTRIBUTION
A18: Stocks | C18: =C4/C$15 -> 0.22403916 | D18: =D4/D$15 -> 0.22833458 | E18: =E4/E$15 -> 0.22315519 | F18: =F4/F$15 -> 0.22429353 | G18: =G4/G$15 -> 0.23139669 | H18: =H4/H$15 -> 0.23774743 | I18: =I4/I$15 -> 0.2436789 | J18: =J4/J$15 -> 0.25243137 | ... BO18: =BO4/BO$15 -> 0.18818657
A19: Mutual Funds | C19: =C5/C$15 -> 0.26787882 | D19: =D5/D$15 -> 0.27424395 | E19: =E5/E$15 -> 0.31062023 | F19: =F5/F$15 -> 0.30624785 | G19: =G5/G$15 -> 0.27395823 | H19: =H5/H$15 -> 0.29248293 | I19: =I5/I$15 -> 0.30251177 | J19: =J5/J$15 -> 0.3128389 | ... BO19: =BO5/BO$15 -> 0.50319065
A20: Gold | C20: =C6/C$15 -> 0.011890522 | D20: =D6/D$15 -> 0.014051105 | E20: =E6/E$15 -> 0.013086135 | F20: =F6/F$15 -> 0.012417126 | G20: =G6/G$15 -> 0.012449704 | H20: =H6/H$15 -> 0.01182916 | I20: =I6/I$15 -> 0.011200489 | J20: =J6/J$15 -> 0.010845236 | ... BO20: =BO6/BO$15 -> 0.014916877
A21: NPS | C21: =(C7+C8+C9)/C$15 -> 0.067419262 | D21: =(D7+D8+D9)/D$15 -> 0.084189946 | E21: =(E7+E8+E9)/E$15 -> 0.085677904 | F21: =(F7+F8+F9)/F$15 -> 0.07682462 | G21: =(G7+G8+G9)/G$15 -> 0.081203116 | H21: =(H7+H8+H9)/H$15 -> 0.080765927 | I21: =(I7+I8+I9)/I$15 -> 0.078083836 | J21: =(J7+J8+J9)/J$15 -> 0.076595846 | ... BO21: =(BO7+BO8+BO9)/BO$15 -> 0.052165366
A22: PF | C22: =C10/C$15 -> 0.15921409 | D22: =D10/D$15 -> 0.15605159 | E22: =E10/E$15 -> 0.15637327 | F22: =F10/F$15 -> 0.16456328 | G22: =G10/G$15 -> 0.16358799 | H22: =H10/H$15 -> 0.15518135 | I22: =I10/I$15 -> 0.15122637 | J22: =J10/J$15 -> 0.14905981 | ... BO22: =BO10/BO$15 -> 0.13794673
A23: PPF | C23: =C11/C$15 -> 0.21058115 | D23: =D11/D$15 -> 0.20291289 | E23: =E11/E$15 -> 0.19654866 | F23: =F11/F$15 -> 0.20165397 | G23: =G11/G$15 -> 0.19751658 | H23: =H11/H$15 -> 0.18462122 | I23: =I11/I$15 -> 0.17731842 | J23: =J11/J$15 -> 0.17229064 | ... BO23: =BO11/BO$15 -> 0.10270215
A24: Cash | C24: =C12/C$15 -> 0.055290929 | D24: =D12/D$15 -> 0.036664103 | E24: =E12/E$15 -> 0.011098174 | F24: =F12/F$15 -> 0.010695565 | G24: =G12/G$15 -> 0.036651422 | H24: =H12/H$15 -> 0.034347014 | I24: =I12/I$15 -> 0.033074889 | J24: =J12/J$15 -> 0.023115257 | ... BO24: =BO12/BO$15 -> 0
A25: Crypto | C25: =C13/C$15 -> 0 | D25: =D13/D$15 -> 0 | E25: =E13/E$15 -> 0 | F25: =F13/F$15 -> 0 | G25: =G13/G$15 -> 0 | H25: =H13/H$15 -> 0 | I25: =I13/I$15 -> 0 | J25: =J13/J$15 -> 0 | ... BO25: =BO13/BO$15 -> 0
A26: Bonds | C26: =C14/C$15 -> 0.0036860619 | D26: =D14/D$15 -> 0.003551835 | E26: =E14/E$15 -> 0.003440434 | F26: =F14/F$15 -> 0.0033040555 | G26: =G14/G$15 -> 0.0032362653 | H26: =H14/H$15 -> 0.0030249776 | I26: =I14/I$15 -> 0.002905323 | J26: =J14/J$15 -> 0.0028229439 | ... BO26: =BO14/BO$15 -> 0.00089166648
A27: Total | C27: =SUM(C16:C26) -> 1 | D27: =SUM(D16:D26) -> 1 | E27: =SUM(E16:E26) -> 1 | F27: =SUM(F16:F26) -> 1 | G27: =SUM(G16:G26) -> 1 | H27: =SUM(H16:H26) -> 1 | I27: =SUM(I16:I26) -> 1 | J27: =SUM(J16:J26) -> 1 | ... V27: =SUM(V16:V26) -> 1 | W27: =SUM(W18:W26) -> 1 | X27: =SUM(X18:X26) -> 1 | Y27: =SUM(Y18:Y26) -> 1 | Z27: =SUM(Z18:Z26) -> 1 | AA27: =SUM(AA18:AA26) -> 1 | AB27: =SUM(AB18:AB26) -> 1 | AC27: =SUM(AC18:AC26) -> 1 | AD27: =SUM(AD18:AD26) -> 1 | ... BO27: =SUM(BO18:BO26) -> 1
A29: NEW INVESTMENT
A30: Stocks | B30: Equity | D30: =('20210131 E'!E72-'20201227 E'!E72)/100000 -> 0.84637083 | E30: =0.7-1.29 -> -0.59 | F30: 0.8 | G30: 0.55 | H30: 0.7 | I30: =0.7+0.73 -> 1.43 | J30: 0.8 | K30: 1.2 | L30: =('20211002 E'!E85-'20210907 E'!E82)/10^5 -> 1.2399348 | M30: =('20211101 E'!E85-'20211002 E'!E85)/10^5 -> 1.0273797 | N30: =('20211204 E'!E90-'20211101 E'!E85)/10^5 -> 1.5190124 | O30: =('20220102 E'!$E90-'20211204 E'!$E90)/10^5 -> 1.2934106 | P30: =('20220202 E'!$E92-'20220102 E'!$E90)/10^5 -> 1.1916834 | Q30: =('20220305 E'!$E92-'20220202 E'!$E92)/10^5 -> 0.6672175 | R30: =('20220402 E'!$E94-'20220305 E'!$E92)/10^5 -> 1.0094979 | S30: =(-'20220402 E'!$E94+'20220501 E'!$E94)/10^5 -> 0.850297 | T30: =('20220605 E'!$E94-'20220501 E'!$E94)/10^5 -> 0.4080755 | U30: =('20220702 E'!$E94-'20220605 E'!$E94)/10^5 -> -0.2032745 | V30: =('20220801 E'!$G104-'20220702 E'!$E94-'20220801 E'!$G83-'20220801 E'!$G82-'20220801 E'!$G81-'20220801 E'!$G2-'20220801 E'!$G76)/10^5 -> 0.0434097 | W30: =('20220903 E'!$G104-'20220801 E'!$G104)/10^5 -> 0.3831349 | X30: =('20221001 E'!$G104-'20220903 E'!$G104)/10^5 -> 0.7956837 | Y30: =('20221103 E'!$G104-'20221001 E'!$G104)/10^5 -> 0.7685982 | Z30: =('20221103 E'!$G104-'20221001 E'!$G104)/10^5 -> 0.7685982 | AA30: =('20230101 E'!$G104-'20221203 E'!$G104)/10^5 -> 0.686213 | AB30: =('20230203 E'!$G104-'20230101 E'!$G104)/10^5 -> 0.648364 | AC30: =('20230203 E'!$G104-'20230101 E'!$G104)/10^5 -> 0.648364 | AD30: =('20230402 E'!$G104-'20230303 E'!$G104)/10^5 -> 0.6116669 | AE30: =('20230501 E'!$G104-'20230402 E'!$G104)/10^5 -> 0.6105181 | AF30: =('20230603 E'!$G104-'20230501 E'!$G104)/10^5 -> -1.5387953 | AG30: =('20230701 E'!$G104-'20230603 E'!$G104)/10^5 -> 0.8634203 | AH30: =('20230805 E'!$G104-'20230701 E'!$G104)/10^5 -> 1.1549591 | AI30: 0.6 | AJ30: 0.3 | AK30: =('20231104 E'!$G104-'20231002 E'!$G104)/10^5 -> 0.0029332 | AL30: =('20231202 E'!$G104-'20231104 E'!$G104)/10^5 -> 0.2838831 | AM30: =('20240101 E'!$G104-'20231202 E'!$G104)/10^5 -> 0.2120653 | AN30: =('20240203 E'!$G104-'20240101 E'!$G104)/10^5 -> 0.002002 | AO30: =('20240303 E'!$G104-'20240203 E'!$G104)/10^5 -> 0.456483 | AP30: =('20240403 E'!$G104-'20240303 E'!$G104)/10^5 -> 1.35646 | AQ30: =('20240501 E'!$G104-'20240403 E'!$G104)/10^5 -> 0.43588 | AR30: =('20240603 E'!$G104-'20240501 E'!$G104)/10^5 -> 0.4308388 | AS30: =('20240701 E'!$G104-'20240603 E'!$G104)/10^5 -> 1.1988714 | AT30: =('20240802 E'!$G104-'20240701 E'!$G104)/10^5 -> 0.8402692 | AU30: =('20240901 E'!$G104-'20240802 E'!$G104)/10^5 -> 0.2491913 | AV30: =('20241002 E'!$G104-'20240901 E'!$G104)/10^5 -> 1.6167493 | AW30: =('20241102 E'!$G104-'20241002 E'!$G104)/10^5 -> 0.2625 | AX30: =('20241201 E'!$G104-'20241102 E'!$G104)/10^5 -> 0.24205 | AY30: =('20250104 E'!$G104-'20241201 E'!$G104)/10^5 -> 1.4323953 | AZ30: =('20250201 E'!$G104-'20250104 E'!$G104)/10^5 -> -1.8985225 | BA30: =('20250302 E'!$E104-'20250201 E'!$G104)/10^5 -> 1.3183539 | BB30: =('20250405 E'!$E104-'20250302 E'!$E104)/10^5 -> -8.8353283 | BC30: =('20250502 E'!$E104-'20250405 E'!$E104)/10^5 -> -0.0820553 | BD30: =('20250602 E'!$E104-'20250502 E'!$E104)/10^5 -> 0 | BE30: =('20250707 E'!$E104-'20250602 E'!$E104)/10^5 -> 0.0820553 | BF30: =('20250802 E'!$E104-'20250707 E'!$E104)/10^5-BF32 -> -0.0213924 | BG30: =('20250901 E'!$E104-'20250802 E'!$E104)/10^5-BG32 -> -0.2 | BH30: =('20251004 E'!$E104-'20250901 E'!$E104)/10^5-BH32 -> -1.1543273 | BI30: =('20251101 E'!$E104-'20251004 E'!$E104)/10^5-BI32 -> 0 | BJ30: =('20251201 E'!$E104-'20251101 E'!$E104)/10^5-BJ32 -> 0 | BK30: =('20260101 E'!$E104-'20251201 E'!$E104)/10^5-BK32 -> 0 | BL30: =('20260201 E'!$E104-'20260101 E'!$E104)/10^5-BL32 -> 0 | BM30: =('20260301 E'!$E104-'20260201 E'!$E104)/10^5-BM32 -> 0.4826553 | BN30: =('20260402 E'!$E104-'20260301 E'!$E104)/10^5-BN32 -> 0 | BO30: =('20260501 E'!$E104-'20260402 E'!$E104)/10^5-BO32 -> 0 | BP30: =SUM(D30:BO30) -> 20.797751 | BR30: =BP30/$BQ$2 -> 0.32496485
A31: Mutual Funds | B31: Equity | D31: 1 | E31: 1 | F31: 1.2 | G31: =0.85-3.13 -> -2.28 | H31: 1.2 | I31: 1 | J31: 0.8 | K31: 1.2 | L31: =('20211002 MF'!F13-'20210907 MF'!F13)/10^5-L38 -> 0.60046476 | M31: =('20211101 MF'!F14-'20211002 MF'!F13)/10^5-M38 -> 1.0105449 | N31: =('20211204 MF'!F14-'20211101 MF'!F14)/10^5-N38 -> 1.2016457 | O31: =('20220102 MF'!$F14-'20211204 MF'!$F14)/10^5-O38 -> 0.79343139 | P31: =('20220202 MF'!$F14-'20220102 MF'!$F14)/10^5-P38 -> 1.1975464 | Q31: =('20220305 MF'!$F14-'20220202 MF'!$F14)/10^5-Q38 -> 0.60840731 | R31: =('20220402 MF'!$F14-'20220305 MF'!$F14)/10^5-R38 -> 0.79606836 | S31: =(-'20220402 MF'!$F14+'20220501 MF'!$F14)/10^5-S38 -> 0.39620356 | T31: =('20220605 MF'!$F14-'20220501 MF'!$F14)/10^5-T38 -> 0.023737983 | U31: =('20220702 MF'!$F15-'20220605 MF'!$F14)/10^5-U38 -> 0.4999757 | V31: =('20220801 MF'!$F15-'20220702 MF'!$F15)/10^5-V38 -> 0.79995915 | W31: =('20220903 MF'!$F17-'20220801 MF'!$F15)/10^5 -> 0.61125513 | X31: =('20221001 MF'!$F17-'20220903 MF'!$F17)/10^5 -> 1.9998996 | Y31: =('20221103 MF'!$F17-'20221001 MF'!$F17)/10^5 -> 2.3998796 | Z31: =('20221103 MF'!$F17-'20221001 MF'!$F17)/10^5 -> 2.3998796 | AA31: =('20230101 MF'!$F18-'20221203 MF'!$F18)/10^5 -> 0.39988369 | AB31: =('20230203 MF'!$F18-'20230101 MF'!$F18)/10^5 -> 2.3998804 | AC31: =('20230203 MF'!$F18-'20230101 MF'!$F18)/10^5 -> 2.3998804 | AD31: =('20230402 MF'!$F18-'20230303 MF'!$F18)/10^5 -> 0.46544603 | AE31: =('20230501 MF'!$F18-'20230402 MF'!$F18)/10^5 -> 1.9999 | AF31: =('20230603 MF'!$F18-'20230501 MF'!$F18)/10^5 -> 1.9998993 | AG31: =('20230701 MF'!$F18-'20230603 MF'!$F18)/10^5 -> 2.0048995 | AH31: =('20230805 MF'!$F18-'20230701 MF'!$F18)/10^5 -> 2.5998705 | AI31: =('20230902 MF'!$F18-'20230805 MF'!$F18)/10^5 -> 1.4999249 | AJ31: =('20231002 MF'!$F18-'20230902 MF'!$F18)/10^5 -> 0.99995006 | AK31: =('20231104 MF'!$F18-'20231002 MF'!$F18)/10^5 -> 0.99995012 | AL31: =('20231202 MF'!$F18-'20231104 MF'!$F18)/10^5 -> 0.49997498 | AM31: =('20240101 MF'!$F18-'20231202 MF'!$F18)/10^5 -> 0.39997996 | AN31: =('20240203 MF'!$F18-'20240101 MF'!$F18)/10^5 -> 2.4998747 | AO31: =('20240303 MF'!$F18-'20240203 MF'!$F18)/10^5 -> 1.8999054 | AP31: =('20240403 MF'!$F18-'20240303 MF'!$F18)/10^5-AP38 -> 1.9863296 | AQ31: =('20240501 MF'!$F18-'20240403 MF'!$F18)/10^5-AQ38 -> 1.5886812 | AR31: =('20240603 MF'!$F18-'20240501 MF'!$F18)/10^5-AR38 -> 1.6247278 | AS31: =('20240701 MF'!$F18-'20240603 MF'!$F18)/10^5 -> 1.1999387 | AT31: =('20240802 MF'!$F18-'20240701 MF'!$F18)/10^5-(AT38) -> 1.1948261 | AU31: =('20240901 MF'!$F18-'20240802 MF'!$F18)/10^5-AU38 -> 2.4827247 | AV31: =('20241002 MF'!$F18-'20240901 MF'!$F18)/10^5-AV38 -> 1.7823224 | AW31: =('20241102 MF'!$F18-'20241002 MF'!$F18)/10^5-AW38 -> 1.7210252 | AX31: =('20241201 MF'!$F18-'20241102 MF'!$F18)/10^5-AX38 -> 1.7068855 | AY31: =('20250104 MF'!$F18-'20241201 MF'!$F18)/10^5-AY38 -> 2.9127305 | AZ31: =('20250201 MF'!$F18-'20250104 MF'!$F18)/10^5-AZ38 -> 1.1999403 | BA31: =('20250302 MF'!$F18-'20250201 MF'!$F18)/10^5-BA38 -> 1.5999207 | BB31: =('20250405 MF'!$F22-'20250302 MF'!$F18)/10^5 -> 3.3498322 | BC31: =('20250502 MF'!$F22-'20250405 MF'!$F22)/10^5-BC12 -> 3.2098401 | BD31: =('20250602 MF'!$F22-'20250502 MF'!$F22)/10^5-BD38 -> 2.6998651 | BE31: =('20250707 MF'!$F22-'20250602 MF'!$F22)/10^5-BE38 -> 2.6998659 | BF31: =('20250802 MF'!$F22-'20250707 MF'!$F22)/10^5-(BF38-3) -> 0.89995491 | BG31: =('20250901 MF'!$F22-'20250802 MF'!$F22)/10^5 -> 0.89995292 | BH31: =('20251004 MF'!$F22-'20250901 MF'!$F22)/10^5 -> 0.99466076 | BI31: =('20251101 MF'!$F22-'20251004 MF'!$F22)/10^5 -> 2.2000141 | BJ31: =('20251201 MF'!$F22-'20251101 MF'!$F22)/10^5 -> 1.0355612 | BK31: =('20260101 MF'!$F22-'20251201 MF'!$F22)/10^5 -> 1.3499335 | BL31: =('20260201 MF'!$F22-'20260101 MF'!$F22)/10^5 -> 0.33106128 | BM31: =('20260301 MF'!$F22-'20260201 MF'!$F22)/10^5 -> 0.31803432 | BN31: =('20260402 MF'!$F22-'20260301 MF'!$F22)/10^5 -> 1.4499266 | BO31: =('20260501 MF'!$F22-'20260402 MF'!$F22)/10^5 -> 0.050001218 | BP31: =SUM(D31:BO31) -> 86.016676 | BR31: =BP31/$BQ$2 -> 1.3440106
A32: Gold | B32: Gold | D32: 0.2475 | E32: 0 | F32: 0 | G32: 0 | H32: 0 | I32: 0 | J32: 0 | K32: 0 | L32: 0 | M32: 0 | N32: 0 | O32: 0 | P32: 0 | Q32: 0 | R32: =R6-Q6 -> -0.0197 | S32: =S6-R6 -> 0.04635 | T32: =T6-S6 -> -0.0353 | U32: =U6-T6 -> 0.0154 | V32: =V6-U6 -> -0.00159 | W32: 0 | X32: 0 | Y32: 0 | Z32: 0 | AA32: 0 | AB32: 0 | AC32: 0 | AD32: 0 | AE32: 0 | AF32: 0 | AG32: 0 | AH32: 0 | AI32: 0 | AJ32: 0 | AK32: 0 | AL32: 0 | AM32: 0 | AN32: 0 | AO32: 0 | AP32: 0 | AQ32: 0 | AR32: 0 | AS32: 0 | AT32: 0 | AU32: 0 | AV32: 0 | AW32: 0 | AX32: 0 | AY32: 0 | AZ32: 0 | BA32: 0 | BB32: 0 | BC32: 0 | BD32: 0 | BE32: 0 | BF32: 1 | BH32: 0 | BI32: 0 | BJ32: 0 | BK32: 0 | BL32: 0 | BM32: 0 | BN32: 0 | BO32: 0 | BP32: =SUM(D32:BO32) -> 1.25266 | BR32: =BP32/$BQ$2 -> 0.019572813
A33: NPS E | B33: Equity | D33: 0 | E33: 0 | F33: 0 | G33: 0 | H33: 0 | I33: 0 | J33: 0 | K33: 0 | L33: 0.35 | M33: 0 | N33: 0 | O33: 0 | P33: 0 | Q33: 0 | R33: 0 | S33: 0 | T33: 0 | U33: 0 | V33: 0 | W33: =0.35 -> 0.35 | X33: 0 | Y33: 0 | Z33: 0 | AA33: 0 | AB33: 0 | AC33: 0 | AD33: 0 | AE33: 0 | AF33: 0 | AG33: 0 | AH33: =0.75*1.5 -> 1.125 | AI33: 0 | AJ33: 0 | AK33: 0 | AL33: 0 | AM33: 0 | AN33: 0 | AO33: 0 | AP33: 0 | AQ33: 0 | AR33: 0 | AS33: 0 | AT33: 0.35 | AU33: 0 | AV33: 0 | AW33: 0 | AX33: 0 | AY33: 0 | AZ33: 0 | BA33: 0 | BB33: 0 | BC33: 0 | BD33: 0 | BE33: 0 | BF33: 0 | BH33: 0 | BI33: 0.45 | BJ33: 0 | BK33: 0 | BL33: 0 | BM33: 0 | BN33: 0 | BO33: 0 | BP33: =SUM(D33:BO33) -> 2.625 | BR33: =BP33/$BQ$2 -> 0.041015625
A34: NPS C | B34: Debt | D34: 0 | E34: 0 | F34: 0 | G34: 0 | H34: 0 | I34: 0 | J34: 0 | K34: 0 | L34: 0.1 | M34: 0 | N34: 0 | O34: 0 | P34: 0 | Q34: 0 | R34: =R8-Q8 -> 0.004 | S34: 0 | T34: 0 | U34: 0 | V34: 0 | W34: 0.1 | X34: 0 | Y34: 0 | Z34: 0 | AA34: 0 | AB34: 0 | AC34: 0 | AD34: 0 | AE34: 0 | AF34: 0 | AG34: 0 | AH34: =0.1*1.5 -> 0.15 | AI34: 0 | AJ34: 0 | AK34: 0 | AL34: 0 | AM34: 0 | AN34: 0 | AO34: 0 | AP34: 0 | AQ34: 0 | AR34: 0 | AS34: 0 | AT34: 0.05 | AU34: 0 | AV34: 0 | AW34: 0 | AX34: 0 | AY34: 0 | AZ34: 0 | BA34: 0 | BB34: 0 | BC34: 0 | BD34: 0 | BE34: 0 | BF34: 0 | BH34: 0 | BI34: 0.1 | BJ34: 0 | BK34: 0 | BL34: 0 | BM34: 0 | BN34: 0 | BO34: 0 | BP34: =SUM(D34:BO34) -> 0.504 | BR34: =BP34/$BQ$2 -> 0.007875
A35: NPS G | B35: Debt | D35: 0 | E35: 0 | F35: 0 | G35: 0 | H35: 0 | I35: 0 | J35: 0 | K35: 0 | L35: 0.05 | M35: 0 | N35: 0 | O35: 0 | P35: 0 | Q35: 0 | R35: =R9-Q9 -> 0.0065 | S35: 0 | T35: 0 | U35: 0 | V35: 0 | W35: 0.05 | X35: 0 | Y35: 0 | Z35: 0 | AA35: 0 | AB35: 0 | AC35: 0 | AD35: 0 | AE35: 0 | AF35: 0 | AG35: 0 | AH35: =0.15*1.5 -> 0.225 | AI35: 0 | AJ35: 0 | AK35: 0 | AL35: 0 | AM35: 0 | AN35: 0 | AO35: 0 | AP35: 0 | AQ35: 0 | AR35: 0 | AS35: 0 | AT35: 0.1 | AU35: 0 | AV35: 0 | AW35: 0 | AX35: 0 | AY35: 0 | AZ35: 0 | BA35: 0 | BB35: 0 | BC35: 0 | BD35: 0 | BE35: 0 | BF35: 0 | BH35: 0 | BI35: 0.15 | BJ35: 0 | BK35: 0 | BL35: 0 | BM35: 0 | BN35: 0 | BO35: 0 | BP35: =SUM(D35:BO35) -> 0.5815 | BR35: =BP35/$BQ$2 -> 0.0090859375
A36: PF | B36: Debt | D36: =D10-C10 -> 0.23 | E36: =E10-D10 -> 0.47 | F36: 0.2 | G36: =G10-F10 -> 0.23 | H36: =H10-G10 -> 0.233 | I36: =I10-H10 -> 0.23296 | J36: =J10-I10 -> 0.23296 | K36: =K10-J10 -> 0.23296 | L36: =L10-K10 -> 0.23296 | M36: =M10-L10 -> 0.2753 | N36: =N10-M10 -> 0.2753 | ... Q36: =Q10-P10 -> 0.2753 | R36: 0.2753 | S36: =S10-R10 -> 0.2753 | T36: =T10-S10 -> 0.2753 | U36: =U10-T10 -> 0.2753 | V36: =V10-U10 -> 0.2753 | W36: =W10-V10 -> 0.2753 | X36: =X10-W10 -> 0.2753 | Y36: =Y10-X10 -> 0.2753 | Z36: =Z10-Y10 -> 0.637 | ... AC36: =AC10-AB10 -> 0.3185 | AD36: 0.3 | AE36: =AE10-AD10 -> 0.3185 | AF36: =AF10-AE10 -> 0.3185 | AG36: =AG10-AF10 -> 0.3185 | AH36: =AH10-AG10 -> 0.3185 | AI36: =AI10-AH10 -> 0.3185 | AJ36: =AJ10-AI10 -> 0.3185 | AK36: =AK10-AJ10 -> 0.35158 | AL36: =AL10-AK10 -> 0.35158 | ... AO36: =AO10-AN10 -> 0.35158 | AP36: =AO36 -> 0.35158 | AQ36: =AQ10-AP10 -> 0.35158 | AR36: =AR10-AQ10 -> 0.35158 | AS36: =AS10-AR10 -> 0.35158 | AT36: =AT10-AS10 -> 0.35158 | AU36: =AU10-AT10 -> 0.35158 | AV36: =AV10-AU10 -> 0.35158 | AW36: =AW10-AV10 -> 0.40618 | AX36: =AX10-AW10 -> 0.40618 | ... BA36: =BA10-AZ10 -> 0.40618 | BB36: =BA36 -> 0.40618 | BC36: =BC10-BB10 -> 0.40618 | BD36: =BD10-BC10 -> 0.40618 | BE36: =BE10-BD10 -> 0.40618 | BF36: =BF10-BE10 -> 0.40618 | BG36: =BG10-BF10 -> 0.40618 | BH36: =BH10-BG10 -> 0.40618 | BI36: =BI10-BH10 -> 0.47506 | BJ36: =BJ10-BI10 -> 0.47506 | ... BM36: =BM10-BL10 -> 0.47506 | BN36: =BM36 -> 0.47506 | BO36: =BO10-BN10 -> 0.47506 | BP36: =SUM(D36:BO36) -> 22.09578 | BR36: =BP36/$BQ$2 -> 0.34524656
A37: PPF | B37: Debt | D37: =D11-C11 -> 0 | E37: =E11-D11 -> 0 | F37: 0 | G37: =G11-F11 -> 0 | H37: =H11-G11 -> 0 | I37: =I11-H11 -> 0 | J37: =J11-H11 -> 0 | K37: =K11-H11 -> 0 | L37: =L11-I11 -> 1.5 | M37: =M11-L11 -> 0 | N37: =N11-M11 -> 0 | O37: =O11-M11 -> 0 | P37: =P11-M11 -> 0 | Q37: =Q11-P11 -> 0 | R37: 0 | S37: =S11-R11 -> 0 | T37: =T11-R11 -> 0 | U37: =U11-S11 -> 0 | V37: =V11-T11 -> 0 | W37: =W11-V11 -> 1.5 | X37: =X11-W11 -> 0 | Y37: =Y11-X11 -> 0 | Z37: =Z11-Y11 -> 0 | AA37: =AA11-Z11 -> 0 | AB37: =AB11-Z11 -> 0 | AC37: =AC11-AA11 -> 0 | AD37: 0 | AE37: 0 | AF37: 0 | AG37: 0 | AH37: =AH11-AG11 -> 1.5 | AI37: =AI11-AH11 -> 0 | AJ37: =AJ11-AI11 -> 0 | AK37: =AK11-AJ11 -> 0 | AL37: =AL11-AK11 -> 0 | AM37: =AM11-AL11 -> 0 | AN37: =AN11-AH11 -> 0 | AO37: =AO11-AN11 -> 0 | AP37: 0 | AQ37: 0 | AR37: 0 | AS37: =AS11-AQ11 -> 0 | AT37: =AT11-AQ11 -> 1.5 | AU37: =AU11-AT11 -> 0 | AV37: =AV11-AU11 -> 0 | AW37: =AW11-AV11 -> 0 | AX37: =AX11-AW11 -> 0 | AY37: =AY11-AX11 -> 0 | AZ37: =AZ11-AY11 -> 0 | BA37: =BA11-AZ11 -> 0 | BB37: 1.5 | BC37: =BC11-BB11 -> 0 | BD37: =BD11-BC11 -> 0 | BE37: =BE11-BC11 -> 0 | BF37: =BF11-BC11 -> 0 | BG37: =BG11-BF11 -> 0 | BH37: =BH11-BG11 -> 0 | BI37: =BI11-BH11 -> 0 | BJ37: =BJ11-BH11 -> 0 | BK37: =BK11-BH11 -> 0 | BL37: =BL11-BH11 -> 0 | BM37: =BM11-BH11 -> 0 | BN37: 0 | BO37: 0 | BP37: =SUM(D37:BO37) -> 7.5 | BR37: =BP37/$BQ$2 -> 0.1171875
A38: Cash | B38: Liquid | D38: =D12-C12 -> -1.45 | E38: =E12-D12 -> -2.2 | F38: =F12-E12 -> 0.003501614 | G38: =G12-F12 -> 2.5073171 | H38: =H12-G12 -> 0.009066541 | I38: =I12-H12 -> 0.009228589 | J38: =J12-I12 -> -0.99072487 | K38: =K12-J12 -> -0.49289939 | ... BI38: =BI12-BH12 -> 0 | BJ38: =BJ12-BH12 -> 0 | BK38: =BK12-BH12 -> 0 | BL38: =BL12-BH12 -> 0 | BM38: =BM12-BH12 -> 0 | BN38: =BN12-BH12 -> 0 | BO38: =BO12-BI12 -> 0 | BP38: =SUM(D38:BO38) -> -4.65 | BR38: =BP38/$BQ$2 -> -0.07265625
A39: Crypto | B39: Alternate | D39: =D13-C13 -> 0 | E39: =E13-D13 -> 0 | F39: =F13-E13 -> 0 | G39: =G13-F13 -> 0 | H39: =H13-G13 -> 0 | I39: =I13-H13 -> 0 | J39: =J13-H13 -> 0 | K39: =K13-J13 -> 0.10485 | L39: =L13-K13 -> 0.43515 | M39: 0 | N39: =N13-M13 -> -0.73 | O39: =O13-N13 -> 0 | P39: =P13-N13 -> 0 | Q39: =Q13-O13 -> 0 | R39: =R13-Q13 -> 0 | S39: =S13-R13 -> 0 | T39: =T13-S13 -> 0 | U39: =U13-T13 -> 0 | V39: =V13-U13 -> 0 | W39: =W13-V13 -> 0 | X39: =X13-W13 -> 0 | Y39: =Y13-X13 -> 0 | ... AA39: =AA13-Z13 -> 0 | AB39: =AB13-Z13 -> 0 | AC39: =AC13-AA13 -> 0 | AD39: 0 | AE39: 0 | AF39: 0 | AG39: 0 | AH39: =AH13-AG13 -> 0 | AI39: =AI13-AH13 -> 0 | AJ39: =AJ13-AI13 -> 0 | AK39: =AK13-AJ13 -> 0 | AL39: =AL13-AK13 -> 0 | AM39: =AM13-AL13 -> 0 | AN39: =AN13-AH13 -> 0 | AO39: =AO13-AN13 -> 0 | AP39: =AP13-AN13 -> 0 | AQ39: =AQ13-AP13 -> 0 | AR39: =AR13-AP13 -> 0 | AS39: =AS13-AQ13 -> 0 | AT39: =AT13-AQ13 -> 0 | AU39: =AU13-AT13 -> 0 | AV39: =AV13-AT13 -> 0 | AW39: =AW13-AT13 -> 0 | AX39: =AX13-AT13 -> 0 | AY39: =AY13-AT13 -> 0 | AZ39: =AZ13-AU13 -> 0 | BA39: =BA13-AT13 -> 0 | BB39: =BB13-AT13 -> 0 | BC39: =BC13-AT13 -> 0 | BD39: =BD13-AT13 -> 0 | BE39: =BE13-AT13 -> 0 | BF39: =BF13-AT13 -> 0 | BG39: =BG13-BF13 -> 0 | BH39: =BH13-BG13 -> 0 | BI39: =BI13-BH13 -> 0 | BJ39: =BJ13-BH13 -> 0 | BK39: =BK13-BH13 -> 0 | BL39: =BL13-BH13 -> 0 | BM39: =BM13-BH13 -> 0 | BN39: =BN13-BH13 -> 0 | BO39: =BO13-BI13 -> 0 | BP39: =SUM(D39:BO39) -> -0.19 | BR39: =BP39/$BQ$2 -> -0.00296875
A40: Bonds | B40: Debt | D40: =D14-C14 -> 0 | E40: =E14-D14 -> 0 | F40: =F14-E14 -> 0 | G40: =G14-F14 -> 0 | H40: =H14-G14 -> 0 | I40: =I14-H14 -> 0 | J40: =J14-H14 -> 0 | K40: =K14-H14 -> 0 | L40: =L14-I14 -> 0 | M40: =M14-L14 -> 0 | N40: =N14-M14 -> 0 | O40: =O14-J14 -> 0 | P40: =P14-J14 -> 0 | Q40: =Q14-K14 -> 0 | R40: =R14-Q14 -> 0 | S40: =S14-R14 -> 0 | T40: =T14-S14 -> 0 | U40: =U14-T14 -> 0 | V40: =V14-U14 -> 0.023004 | W40: =W14-V14 -> 0.000146 | X40: =X14-W14 -> -0.003756 | Y40: =Y14-X14 -> 0.006108 | Z40: =Z14-Y14 -> -0.018312 | AA40: 0 | AB40: 0 | AC40: 0 | AD40: 0 | AE40: 0 | AF40: 0 | AG40: 0 | AH40: 0 | AI40: 0 | AJ40: 0 | AK40: 0 | AL40: 0 | AM40: 0 | AN40: 0 | AO40: 0 | AP40: 0 | AQ40: 0 | AR40: 0 | AS40: 0 | AT40: 0 | AU40: 0 | AV40: 0 | AW40: 0 | AX40: 0 | AY40: 0 | AZ40: 0 | BA40: 0 | BB40: 0 | BC40: 0 | BD40: 0 | BE40: 0 | BF40: 0 | BG40: 0 | BH40: 0 | BI40: 0 | BJ40: 0 | BK40: 0 | BL40: 0 | BM40: 0 | BN40: 0 | BO40: 0 | BP40: =SUM(D40:BO40) -> 0.00719 | BR40: =BP40/$BQ$2 -> 0.00011234375
A41: Total Investment | D41: =SUM(D30:D40) -> 0.87387083 | E41: =SUM(E30:E40) -> -1.32 | F41: =SUM(F30:F40) -> 2.2035016 | G41: =SUM(G30:G40) -> 1.0073171 | H41: =SUM(H30:H40) -> 2.1420665 | I41: =SUM(I30:I40) -> 2.6721886 | J41: =SUM(J30:J40) -> 0.84223513 | K41: =SUM(K30:K40) -> 2.2449106 | ... BO41: =SUM(BO30:BO40) -> 0.52506122 | BP41: =SUM(D41:BO41) -> 136.54056 | BR41: =BP41/$BQ$2 -> 2.1334462
A43: RETURNS
A44: Stocks | B44: Equity | D44: =D4-C4-D30 -> 0.24057767 | E44: =E4-D4-E30 -> 0.7686035 | F44: =F4-E4-F30 -> 0.136758 | G44: =G4-F4-G30 -> 0.57122 | H44: =H4-G4-H30 -> 1.4990225 | I44: =I4-H4-I30 -> 0.2063305 | J44: =J4-I4-J30 -> 0.9199 | K44: =K4-J4-K30 -> 1.109655 | ... BO44: =BO4-BN4-BO30 -> 4.5095287 | BP44: =SUM(D44:BO44) -> 25.786047 | BR44: =BP44/$BQ$2 -> 0.40290698
A45: Mutual Funds | B45: Equity | D45: =D5-C5-D31 -> 0.40692294 | E45: =E5-D5-E31 -> 3.0527171 | F45: =F5-E5-F31 -> -0.45498324 | G45: =G5-F5-G31 -> -0.21112256 | H45: =H5-G5-H31 -> 2.5313759 | I45: =I5-H5-I31 -> 1.3045393 | J45: =J5-I5-J31 -> 1.2760108 | K45: =K5-J5-K31 -> 2.3146836 | ... BO45: =BO5-BN5-BO31 -> 20.82576 | BP45: =SUM(D45:BO45) -> 66.395639 | BR45: =BP45/$BQ$2 -> 1.0374319
A46: Gold | B46: Gold | D46: =D6-C6-D32 -> -0.021136 | E46: =E6-D6-E32 -> -0.047239 | F46: =F6-E6-F32 -> -0.0140995 | G46: =G6-F6-G32 -> 0.0275245 | H46: =H6-G6-H32 -> 0.0197035 | I46: =I6-H6-I32 -> -0.0171535 | J46: =J6-I6-J32 -> -0.0041365 | K46: =K6-J6-K32 -> -0.0134655 | ... BO46: =BO6-BN6-BO32 -> 0.1314615 | BP46: =SUM(D46:BO46) -> 2.9333955 | BR46: =BP46/$BQ$2 -> 0.045834305
A47: NPS E | B47: Equity | D47: =D7-C7-D33 -> 1.44 | E47: =E7-D7-E33 -> 0.41 | F47: =F7-E7-F33 -> -0.541 | G47: =G7-F7-G33 -> -0.059 | H47: =H7-G7-H33 -> 0.49 | I47: =I7-H7-I33 -> 0.059 | J47: =J7-I7-J33 -> 0.0734 | K47: =K7-J7-K33 -> 0.5735 | ... BO47: =BO7-BN7-BO33 -> 0.29 | BP47: =SUM(D47:BO47) -> 5.115 | BR47: =BP47/$BQ$2 -> 0.079921875
A48: NPS C | B48: Debt | D48: =D8-C8-D34 -> 0.095 | E48: =E8-D8-E34 -> -0.005 | F48: =F8-E8-F34 -> 0.008 | G48: =G8-F8-G34 -> 0.2448 | H48: =H8-G8-H34 -> 0.0052 | I48: =I8-H8-I34 -> 0 | J48: =J8-I8-J34 -> 0.0051 | K48: =K8-J8-K34 -> 0.00877 | ... BO48: =BO8-BN8-BO34 -> 0.092 | BP48: =SUM(D48:BO48) -> 1.156 | BR48: =BP48/$BQ$2 -> 0.0180625
A49: NPS G | B49: Debt | D49: =D9-C9-D35 -> 0.143 | E49: =E9-D9-E35 -> -0.033 | F49: =F9-E9-F35 -> 0.021 | G49: =G9-F9-G35 -> 0.3846 | H49: =H9-G9-H35 -> 0.0033 | I49: =I9-H9-I35 -> -0.0043 | J49: =J9-I9-J35 -> 0.00123 | K49: =K9-J9-K35 -> 0.02222 | ... BO49: =BO9-BN9-BO35 -> 0.644 | BP49: =SUM(D49:BO49) -> 2.4845 | BR49: =BP49/$BQ$2 -> 0.038820312
A50: PF | B50: Debt | D50: =D10-C10-D36 -> 0 | E50: =E10-D10-E36 -> 0 | F50: =F10-E10-F36 -> 1.15 | G50: =G10-F10-G36 -> 0 | H50: =H10-G10-H36 -> 0 | I50: =I10-H10-I36 -> 0 | J50: =J10-I10-J36 -> 0 | K50: =K10-J10-K36 -> 0 | ... BA50: =BA10-AZ10-BA36 -> 0 | BB50: 2.92 | BC50: =BC10-BB10-BC36 -> 0 | BD50: =BD10-BC10-BD36 -> 0 | BE50: =BE10-BD10-BE36 -> 0 | BF50: =BF10-BE10-BF36 -> 0 | BG50: =BG10-BF10-BG36 -> 0 | BH50: =BH10-BG10-BH36 -> 0 | BI50: =BI10-BH10-BI36 -> 0 | BJ50: =BJ10-BI10-BJ36 -> 0 | ... BO50: =BO10-BN10-BO36 -> 0 | BP50: =SUM(D50:BO50) -> 12.47328 | BR50: =BP50/$BQ$2 -> 0.194895
A51: PPF | B51: Debt | D51: =D11-C11-D37 -> 0 | E51: =E11-D11-E37 -> 0 | F51: =F11-E11-F37 -> 1.21 | G51: =G11-F11-G37 -> 0 | H51: =H11-G11-H37 -> 0 | I51: =I11-H11-I37 -> 0 | J51: =J11-I11-J37 -> 0 | K51: =K11-J11-K37 -> 0 | ... AQ51: =AQ11-AP11-AQ37 -> 0 | AR51: =AR11-AP11-AR37 -> 0 | AS51: =AS11-AQ11-AS37 -> 0 | AT51: =AT11-AR11-AT37 -> 0 | AU51: =AU11-AT11-AU37 -> 0 | AV51: =AV11-AU11-AV37 -> 0 | AW51: =AW11-AV11-AW37 -> 0 | AX51: =AX11-AW11-AX37 -> 0 | AY51: =AY11-AX11-AY37 -> 0 | AZ51: =AZ11-AY11-AZ37 -> 0 | BA51: =BA11-AZ11-BA37 -> 0 | BB51: =BB11-BA11-BB37 -> 2.075 | ... BO51: =BO11-BN11-BO37 -> 0 | BP51: =SUM(D51:BO51) -> 10.4958 | BR51: =BP51/$BQ$2 -> 0.16399688
A52: Cash | B52: Liquid | D52: =D12-C12-D38 -> 0 | E52: =E12-D12-E38 -> 0 | F52: =F12-E12-F38 -> 0 | G52: =G12-F12-G38 -> 0 | H52: =H12-G12-H38 -> 0 | I52: =I12-H12-I38 -> 0 | J52: 0 | K52: =K12-J12-K38 -> 0 | L52: =L12-K12-L38 -> 0 | M52: =M12-L12-M38 -> 0 | N52: =N12-M12-N38 -> 0 | O52: =O12-N12-O38 -> 0 | P52: =P12-O12-P38 -> 0 | Q52: =Q12-P12-Q38 -> 0 | R52: =R12-Q12-R38 -> 0 | ... BB52: =BB12-BA12-BB38 -> 0 | BC52: 0 | BD52: 0 | BE52: 0 | BF52: 0 | BG52: 0 | BH52: 0 | BI52: 0 | BJ52: 0 | BK52: 0 | BL52: 0 | BM52: 0 | BN52: 0 | BO52: 0 | BP52: =SUM(D52:BO52) -> 0 | BR52: =BP52/$BQ$2 -> 0
A53: Crypto | B53: Alternate | D53: =D13-C13-D39 -> 0 | E53: =E13-D13-E39 -> 0 | F53: =F13-E13-F39 -> 0 | G53: =G13-F13-G39 -> 0 | H53: =H13-G13-H39 -> 0 | I53: =I13-H13-I39 -> 0 | J53: =J13-I13-J39 -> 0 | K53: =K13-J13-K39 -> 0 | ... AQ53: =AQ13-AP13-AQ39 -> 0 | AR53: =AR13-AP13-AR39 -> 0 | AS53: =AS13-AQ13-AS39 -> 0 | AT53: =AT13-AR13-AT39 -> 0 | AU53: =AU13-AT13-AU39 -> 0 | AV53: =AV13-AU13-AV39 -> 0 | AW53: =AW13-AV13-AW39 -> 0 | AX53: =AX13-AW13-AX39 -> 0 | AY53: =AY13-AX13-AY39 -> 0 | AZ53: =AZ13-AY13-AZ39 -> 0 | BA53: =BA13-AZ13-BA39 -> 0 | BB53: =BB13-BA13-BB39 -> 0 | BC53: =BC13-BA13-BC39 -> 0 | BD53: =BD13-BB13-BD39 -> 0 | BE53: =BE13-BC13-BE39 -> 0 | BF53: =BF13-BD13-BF39 -> 0 | BG53: =BG13-BE13-BG39 -> 0 | BH53: =BH13-BF13-BH39 -> 0 | BI53: =BI13-BG13-BI39 -> 0 | BJ53: =BJ13-BH13-BJ39 -> 0 | ... BO53: =BO13-BM13-BO39 -> 0 | BP53: =SUM(D53:BO53) -> 0.19 | BR53: =BP53/$BQ$2 -> 0.00296875
A54: Bonds | B54: Debt | D54: =D14-C14-D40 -> 0 | E54: =E14-D14-E40 -> 0 | F54: =F14-E14-F40 -> 0 | G54: =G14-F14-G40 -> 0 | H54: =H14-G14-H40 -> 0 | I54: =I14-H14-I40 -> 0 | J54: =J14-I14-J40 -> 0 | K54: =K14-J14-K40 -> 0 | L54: =L14-J14-L40 -> 0 | M54: =M14-L14-M40 -> 0 | N54: =N14-M14-N40 -> 0 | O54: =O14-N14-O40 -> 0 | P54: =P14-O14-P40 -> 0 | Q54: =Q14-P14-Q40 -> 0 | R54: =R14-Q14-R40 -> 0 | S54: =S14-R14-S40 -> 0 | T54: =T14-S14-T40 -> 0 | ... AQ54: =AQ14-AP14-AQ40 -> 0.001516 | AR54: =AR14-AP14-AR40 -> 0.00179 | AS54: =AS14-AQ14-AS40 -> -0.00163 | AT54: =AT14-AR14-AT40 -> 0.006912 | AU54: =AU14-AT14-AU40 -> 0.006704 | AV54: =AV14-AU14-AV40 -> -0.01087 | AW54: =AW14-AV14-AW40 -> 0.001 | AX54: =AX14-AW14-AX40 -> -0.01315 | AY54: =AY14-AX14-AY40 -> 0.00227 | AZ54: =AZ14-AY14-AZ40 -> 0.00042 | BA54: =BA14-AZ14-BA40 -> 0.00216 | BB54: =BB14-BA14-BB40 -> 0.0005 | BC54: =BC14-BA14-BC40 -> 0.000302 | BD54: =BD14-BB14-BD40 -> -0.000548 | BE54: =BE14-BC14-BE40 -> 0.005368 | BF54: =BF14-BD14-BF40 -> 0.009328 | BG54: =BG14-BE14-BG40 -> 0.00613 | BH54: =BH14-BF14-BH40 -> -0.008728 | BI54: =BI14-BG14-BI40 -> -0.008964 | BJ54: =BJ14-BH14-BJ40 -> -0.011502 | ... BO54: =BO14-BM14-BO40 -> -0.0034 | BP54: =SUM(D54:BO54) -> -0.007904 | BR54: =BP54/$BQ$2 -> -0.0001235
A55: Total Growth | D55: =SUM(D44:D54) -> 2.3043646 | E55: =SUM(E44:E54) -> 4.1460816 | F55: =SUM(F44:F54) -> 1.5156753 | G55: =SUM(G44:G54) -> 0.95802194 | H55: =SUM(H44:H54) -> 4.5486019 | I55: =SUM(I44:I54) -> 1.5484163 | J55: =SUM(J44:J54) -> 2.2715043 | K55: =SUM(K44:K54) -> 4.0153631 | ... BO55: =SUM(BO44:BO54) -> 26.48935 | BP55: =SUM(D55:BO55) -> 127.02176 | BR55: =BP55/$BQ$2 -> 1.984715
A57: NET CHANGE
A58: Stocks | B58: Equity | D58: =D30+D44 -> 1.0869485 | E58: =E30+E44 -> 0.1786035 | F58: =F30+F44 -> 0.936758 | G58: =G30+G44 -> 1.12122 | H58: =H30+H44 -> 2.1990225 | I58: =I30+I44 -> 1.6363305 | J58: =J30+J44 -> 1.7199 | K58: =K30+K44 -> 2.309655 | ... BP58: =BP30+BP44 -> 46.583797 | BR58: =BP58/$BQ$2 -> 0.72787183
A59: Mutual Funds | B59: Equity | D59: =D31+D45 -> 1.4069229 | E59: =E31+E45 -> 4.0527171 | F59: =F31+F45 -> 0.74501676 | G59: =G31+G45 -> -2.4911226 | H59: =H31+H45 -> 3.7313759 | I59: =I31+I45 -> 2.3045393 | J59: =J31+J45 -> 2.0760108 | K59: =K31+K45 -> 3.5146836 | ... BP59: =BP31+BP45 -> 152.41232 | BR59: =BP59/$BQ$2 -> 2.3814424
A60: Gold | B60: Gold | D60: =D32+D46 -> 0.226364 | E60: =E32+E46 -> -0.047239 | F60: =F32+F46 -> -0.0140995 | G60: =G32+G46 -> 0.0275245 | H60: =H32+H46 -> 0.0197035 | I60: =I32+I46 -> -0.0171535 | J60: =J32+J46 -> -0.0041365 | K60: =K32+K46 -> -0.0134655 | ... BP60: =BP32+BP46 -> 4.1860555 | BR60: =BP60/$BQ$2 -> 0.065407117
A61: NPS E | B61: Equity | D61: =D33+D47 -> 1.44 | E61: =E33+E47 -> 0.41 | F61: =F33+F47 -> -0.541 | G61: =G33+G47 -> -0.059 | H61: =H33+H47 -> 0.49 | I61: =I33+I47 -> 0.059 | J61: =J33+J47 -> 0.0734 | K61: =K33+K47 -> 0.5735 | ... BP61: =BP33+BP47 -> 7.74 | BR61: =BP61/$BQ$2 -> 0.1209375
A62: NPS C | B62: Debt | D62: =D34+D48 -> 0.095 | E62: =E34+E48 -> -0.005 | F62: =F34+F48 -> 0.008 | G62: =G34+G48 -> 0.2448 | H62: =H34+H48 -> 0.0052 | I62: =I34+I48 -> 0 | J62: =J34+J48 -> 0.0051 | K62: =K34+K48 -> 0.00877 | ... BP62: =BP34+BP48 -> 1.66 | BR62: =BP62/$BQ$2 -> 0.0259375
A63: NPS G | B63: Debt | D63: =D35+D49 -> 0.143 | E63: =E35+E49 -> -0.033 | F63: =F35+F49 -> 0.021 | G63: =G35+G49 -> 0.3846 | H63: =H35+H49 -> 0.0033 | I63: =I35+I49 -> -0.0043 | J63: =J35+J49 -> 0.00123 | K63: =K35+K49 -> 0.02222 | ... BP63: =BP35+BP49 -> 3.066 | BR63: =BP63/$BQ$2 -> 0.04790625
A64: PF | B64: Debt | D64: =D36+D50 -> 0.23 | E64: =E36+E50 -> 0.47 | F64: =F36+F50 -> 1.35 | G64: =G36+G50 -> 0.23 | H64: =H36+H50 -> 0.233 | I64: =I36+I50 -> 0.23296 | J64: =J36+J50 -> 0.23296 | K64: =K36+K50 -> 0.23296 | ... BP64: =BP36+BP50 -> 34.56906 | BR64: =BP64/$BQ$2 -> 0.54014156
A65: PPF | B65: Debt | D65: =D37+D51 -> 0 | E65: =E37+E51 -> 0 | F65: =F37+F51 -> 1.21 | G65: =G37+G51 -> 0 | H65: =H37+H51 -> 0 | I65: =I37+I51 -> 0 | J65: =J37+J51 -> 0 | K65: =K37+K51 -> 0 | ... BP65: =BP37+BP51 -> 17.9958 | BR65: =BP65/$BQ$2 -> 0.28118438
A66: Cash | B66: Liquid | D66: =D38+D52 -> -1.45 | E66: =E38+E52 -> -2.2 | F66: =F38+F52 -> 0.003501614 | G66: =G38+G52 -> 2.5073171 | H66: =H38+H52 -> 0.009066541 | I66: =I38+I52 -> 0.009228589 | J66: =J38+J52 -> -0.99072487 | K66: =K38+K52 -> -0.49289939 | ... BP66: =BP38+BP52 -> -4.65 | BR66: =BP66/$BQ$2 -> -0.07265625
A67: Crypto | B67: Alternate | D67: =D39+D53 -> 0 | E67: =E39+E53 -> 0 | F67: =F39+F53 -> 0 | G67: =G39+G53 -> 0 | H67: =H39+H53 -> 0 | I67: =I39+I53 -> 0 | J67: =J39+J53 -> 0 | K67: =K39+K53 -> 0.10485 | ... BP67: =BP39+BP53 -> 0 | BR67: =BP67/$BQ$2 -> 0
A68: Bonds | B68: Debt | D68: =D40+D54 -> 0 | E68: =E40+E54 -> 0 | F68: =F40+F54 -> 0 | G68: =G40+G54 -> 0 | H68: =H40+H54 -> 0 | I68: =I40+I54 -> 0 | J68: =J40+J54 -> 0 | K68: =K40+K54 -> 0 | ... BP68: =BP40+BP54 -> -0.000714 | BR68: =BP68/$BQ$2 -> -1.115625e-05
A69: Total Change | D69: =D41+D55 -> 3.1782354 | E69: =E41+E55 -> 2.8260816 | F69: =F41+F55 -> 3.7191769 | G69: =G41+G55 -> 1.9653391 | H69: =H41+H55 -> 6.6906684 | I69: =I41+I55 -> 4.2206049 | J69: =J41+J55 -> 3.1137395 | K69: =K41+K55 -> 6.2602737 | ... BP69: =BP41+BP55 -> 263.56231 | BR69: =BP69/$BQ$2 -> 4.1181612
A71: NET CASHFLOWS
A72: Stocks | B72: Equity | C72: =C4*-1 -> -18.841826 | D72: =-1*D30 -> -0.84637083 | E72: =-1*E30 -> 0.59 | F72: =-1*F30 -> -0.8 | G72: =-1*G30 -> -0.55 | H72: =-1*H30 -> -0.7 | I72: =-1*I30 -> -1.43 | J72: =-1*J30 -> -0.8 | K72: =-1*K30 -> -1.2 | ... BO72: =-1*BO30 -> 0 | BP72: =SUM(C72:BO72) -> -39.639577
A73: Mutual Funds | B73: Equity | C73: =C5*-1 -> -22.528768 | D73: =-1*D31 -> -1 | E73: =-1*E31 -> -1 | F73: =-1*F31 -> -1.2 | G73: =-1*G31 -> 2.28 | H73: =-1*H31 -> -1.2 | I73: =-1*I31 -> -1 | J73: =-1*J31 -> -0.8 | K73: =-1*K31 -> -1.2 | ... BO73: =-1*BO31 -> -0.050001218 | BP73: =SUM(C73:BO73) -> -108.54544
A74: Gold | B74: Gold | C74: =C6*-1 -> -1 | D74: =-1*D32 -> -0.2475 | E74: =-1*E32 -> 0 | F74: =-1*F32 -> 0 | G74: =-1*G32 -> 0 | H74: =-1*H32 -> 0 | I74: =-1*I32 -> 0 | J74: =-1*J32 -> 0 | K74: =-1*K32 -> 0 | ... BO74: =-1*BO32 -> 0 | BP74: =SUM(C74:BO74) -> -2.25266
A75: NPS E | B75: Equity | C75: =C7*-1 -> -4.55 | D75: =-1*D33 -> 0 | E75: =-1*E33 -> 0 | F75: =-1*F33 -> 0 | G75: =-1*G33 -> 0 | H75: =-1*H33 -> 0 | I75: =-1*I33 -> 0 | J75: =-1*J33 -> 0 | K75: =-1*K33 -> 0 | ... BO75: =-1*BO33 -> 0 | BP75: =SUM(C75:BO75) -> -7.175
A76: NPS C | B76: Debt | C76: =C8*-1 -> -0.45 | D76: =-1*D34 -> 0 | E76: =-1*E34 -> 0 | F76: =-1*F34 -> 0 | G76: =-1*G34 -> 0 | H76: =-1*H34 -> 0 | I76: =-1*I34 -> 0 | J76: =-1*J34 -> 0 | K76: =-1*K34 -> 0 | ... BO76: =-1*BO34 -> 0 | BP76: =SUM(C76:BO76) -> -0.954
A77: NPS G | B77: Debt | C77: =C9*-1 -> -0.67 | D77: =-1*D35 -> 0 | E77: =-1*E35 -> 0 | F77: =-1*F35 -> 0 | G77: =-1*G35 -> 0 | H77: =-1*H35 -> 0 | I77: =-1*I35 -> 0 | J77: =-1*J35 -> 0 | K77: =-1*K35 -> 0 | ... BO77: =-1*BO35 -> 0 | BP77: =SUM(C77:BO77) -> -1.2515
A78: PF | B78: Debt | C78: =C10*-1 -> -13.39 | D78: =-1*D36 -> -0.23 | E78: =-1*E36 -> -0.47 | F78: =-1*F36 -> -0.2 | G78: =-1*G36 -> -0.23 | H78: =-1*H36 -> -0.233 | I78: =-1*I36 -> -0.23296 | J78: =-1*J36 -> -0.23296 | K78: =-1*K36 -> -0.23296 | ... BO78: =-1*BO36 -> -0.47506 | BP78: =SUM(C78:BO78) -> -35.48578
A79: PPF | B79: Debt | C79: =C11*-1 -> -17.71 | D79: =-1*D37 -> 0 | E79: =-1*E37 -> 0 | F79: =-1*F37 -> 0 | G79: =-1*G37 -> 0 | H79: =-1*H37 -> 0 | I79: =-1*I37 -> 0 | J79: =-1*J37 -> 0 | K79: =-1*K37 -> 0 | ... BO79: =-1*BO37 -> 0 | BP79: =SUM(C79:BO79) -> -25.21
A80: Cash | B80: Liquid | C80: =C12*-1 -> -4.65 | D80: =-1*D38 -> 1.45 | E80: =-1*E38 -> 2.2 | F80: =-1*F38 -> -0.003501614 | G80: =-1*G38 -> -2.5073171 | H80: =-1*H38 -> -0.009066541 | I80: =-1*I38 -> -0.009228589 | J80: =-1*J38 -> 0.99072487 | K80: =-1*K38 -> 0.49289939 | ... BO80: =-1*BO38 -> 0 | BP80: =SUM(C80:BO80) -> 0
A81: Crypto | B81: Alternate | C81: =C13*-1 -> 0 | D81: =-1*D39 -> 0 | E81: =-1*E39 -> 0 | F81: =-1*F39 -> 0 | G81: =-1*G39 -> 0 | H81: =-1*H39 -> 0 | I81: =-1*I39 -> 0 | J81: =-1*J39 -> 0 | K81: =-1*K39 -> -0.10485 | ... BO81: =-1*BO39 -> 0 | BP81: =SUM(C81:BO81) -> 0.19
A82: Bonds | B82: Debt | C82: =C14*-1 -> -0.31 | D82: =-1*D40 -> 0 | E82: =-1*E40 -> 0 | F82: =-1*F40 -> 0 | G82: =-1*G40 -> 0 | H82: =-1*H40 -> 0 | I82: =-1*I40 -> 0 | J82: =-1*J40 -> 0 | K82: =-1*K40 -> 0 | ... BO82: =-1*BO40 -> 0 | BP82: =SUM(C82:BO82) -> -0.31719
A83: Total Change | C83: =SUM(C72:C82) -> -84.100595 | D83: =SUM(D72:D82) -> -0.87387083 | E83: =SUM(E72:E82) -> 1.32 | F83: =SUM(F72:F82) -> -2.2035016 | G83: =SUM(G72:G82) -> -1.0073171 | H83: =SUM(H72:H82) -> -2.1420665 | I83: =SUM(I72:I82) -> -2.6721886 | J83: =SUM(J72:J82) -> -0.84223513 | ... BP83: =SUM(BP72:BP82) -> -220.64115
A85: XIRR
A86: Stocks | B86: Equity | D86: {=XIRR(INDEX(IF(COLUMN($C72:D72)<COLUMN(D72),$C72:C72,D4),),$C$1:D$1)} -> 0.93549093 | E86: {=XIRR(INDEX(IF(COLUMN($C72:E72)<COLUMN(E72),$C72:D72,E4),),$C$1:E$1)} -> 0.14262484 | F86: {=XIRR(INDEX(IF(COLUMN($C72:F72)<COLUMN(F72),$C72:E72,F4),),$C$1:F$1)} -> 0.46098863 | G86: {=XIRR(INDEX(IF(COLUMN($C72:G72)<COLUMN(G72),$C72:F72,G4),),$C$1:G$1)} -> 0.38541067 | H86: {=XIRR(INDEX(IF(COLUMN($C72:H72)<COLUMN(H72),$C72:G72,H4),),$C$1:H$1)} -> 0.53693334 | I86: {=XIRR(INDEX(IF(COLUMN($C72:I72)<COLUMN(I72),$C72:H72,I4),),$C$1:I$1)} -> 0.54510666 | J86: {=XIRR(INDEX(IF(COLUMN($C72:J72)<COLUMN(J72),$C72:I72,J4),),$C$1:J$1)} -> 0.47965004 | K86: {=XIRR(INDEX(IF(COLUMN($C72:K72)<COLUMN(K72),$C72:J72,K4),),$C$1:K$1)} -> 0.50848431 | ... BO86: {=XIRR(INDEX(IF(COLUMN($C72:BO72)<COLUMN(BO72),$C72:BN72,BO4),),$C$1:BO$1)} -> 0.10770593
A87: Mutual Funds | B87: Equity | D87: {=XIRR(INDEX(IF(COLUMN($C73:D73)<COLUMN(D73),$C73:C73,D5),),$C$1:D$1)} -> 1.0406178 | E87: {=XIRR(INDEX(IF(COLUMN($C73:E73)<COLUMN(E73),$C73:D73,E5),),$C$1:E$1)} -> 1.9957614 | F87: {=XIRR(INDEX(IF(COLUMN($C73:F73)<COLUMN(F73),$C73:E73,F5),),$C$1:F$1)} -> 0.90677162 | G87: {=XIRR(INDEX(IF(COLUMN($C73:G73)<COLUMN(G73),$C73:F73,G5),),$C$1:G$1)} -> 0.064040926 | H87: {=XIRR(INDEX(IF(COLUMN($C73:H73)<COLUMN(H73),$C73:G73,H5),),$C$1:H$1)} -> 0.76427308 | I87: {=XIRR(INDEX(IF(COLUMN($C73:I73)<COLUMN(I73),$C73:H73,I5),),$C$1:I$1)} -> 0.72788275 | J87: {=XIRR(INDEX(IF(COLUMN($C73:J73)<COLUMN(J73),$C73:I73,J5),),$C$1:J$1)} -> 0.6966519 | K87: {=XIRR(INDEX(IF(COLUMN($C73:K73)<COLUMN(K73),$C73:J73,K5),),$C$1:K$1)} -> 0.75230132 | ... BO87: {=XIRR(INDEX(IF(COLUMN($C73:BO73)<COLUMN(BO73),$C73:BN73,BO5),),$C$1:BO$1)} -> 0.16374499
A88: Gold | B88: Gold | D88: {=XIRR(INDEX(IF(COLUMN($C74:D74)<COLUMN(D74),$C74:C74,D6),),$C$1:D$1)} -> 10.051517 | E88: {=XIRR(INDEX(IF(COLUMN($C74:E74)<COLUMN(E74),$C74:D74,E6),),$C$1:E$1)} -> -0.32288305 | F88: {=XIRR(INDEX(IF(COLUMN($C74:F74)<COLUMN(F74),$C74:E74,F6),),$C$1:F$1)} -> -0.24998089 | G88: {=XIRR(INDEX(IF(COLUMN($C74:G74)<COLUMN(G74),$C74:F74,G6),),$C$1:G$1)} -> -0.13025462 | H88: {=XIRR(INDEX(IF(COLUMN($C74:H74)<COLUMN(H74),$C74:G74,H6),),$C$1:H$1)} -> -0.06787329 | I88: {=XIRR(INDEX(IF(COLUMN($C74:I74)<COLUMN(I74),$C74:H74,I6),),$C$1:I$1)} -> -0.084309241 | J88: {=XIRR(INDEX(IF(COLUMN($C74:J74)<COLUMN(J74),$C74:I74,J6),),$C$1:J$1)} -> -0.078951982 | K88: {=XIRR(INDEX(IF(COLUMN($C74:K74)<COLUMN(K74),$C74:J74,K6),),$C$1:K$1)} -> -0.08314282 | ... BO88: {=XIRR(INDEX(IF(COLUMN($C74:BO74)<COLUMN(BO74),$C74:BN74,BO6),),$C$1:BO$1)} -> 0.24491323
A89: NPS E | B89: Equity | D89: {=XIRR(INDEX(IF(COLUMN($C75:D75)<COLUMN(D75),$C75:C75,D7),),$C$1:D$1)} -> 24.469495 | E89: {=XIRR(INDEX(IF(COLUMN($C75:E75)<COLUMN(E75),$C75:D75,E7),),$C$1:E$1)} -> 7.2534612 | F89: {=XIRR(INDEX(IF(COLUMN($C75:F75)<COLUMN(F75),$C75:E75,F7),),$C$1:F$1)} -> 1.6976337 | G89: {=XIRR(INDEX(IF(COLUMN($C75:G75)<COLUMN(G75),$C75:F75,G7),),$C$1:G$1)} -> 1.0431434 | H89: {=XIRR(INDEX(IF(COLUMN($C75:H75)<COLUMN(H75),$C75:G75,H7),),$C$1:H$1)} -> 1.1437925 | I89: {=XIRR(INDEX(IF(COLUMN($C75:I75)<COLUMN(I75),$C75:H75,I7),),$C$1:I$1)} -> 0.93655003 | J89: {=XIRR(INDEX(IF(COLUMN($C75:J75)<COLUMN(J75),$C75:I75,J7),),$C$1:J$1)} -> 0.81014775 | K89: {=XIRR(INDEX(IF(COLUMN($C75:K75)<COLUMN(K75),$C75:J75,K7),),$C$1:K$1)} -> 0.87875646 | ... BO89: {=XIRR(INDEX(IF(COLUMN($C75:BO75)<COLUMN(BO75),$C75:BN75,BO7),),$C$1:BO$1)} -> 0.1283282
A90: NPS C | B90: Debt | D90: {=XIRR(INDEX(IF(COLUMN($C76:D76)<COLUMN(D76),$C76:C76,D8),),$C$1:D$1)} -> 8.5372767 | E90: {=XIRR(INDEX(IF(COLUMN($C76:E76)<COLUMN(E76),$C76:D76,E8),),$C$1:E$1)} -> 2.0892288 | F90: {=XIRR(INDEX(IF(COLUMN($C76:F76)<COLUMN(F76),$C76:E76,F8),),$C$1:F$1)} -> 1.1668636 | G90: {=XIRR(INDEX(IF(COLUMN($C76:G76)<COLUMN(G76),$C76:F76,G8),),$C$1:G$1)} -> 4.296257 | H90: {=XIRR(INDEX(IF(COLUMN($C76:H76)<COLUMN(H76),$C76:G76,H8),),$C$1:H$1)} -> 2.8535519 | I90: {=XIRR(INDEX(IF(COLUMN($C76:I76)<COLUMN(I76),$C76:H76,I8),),$C$1:I$1)} -> 2.1154759 | J90: {=XIRR(INDEX(IF(COLUMN($C76:J76)<COLUMN(J76),$C76:I76,J8),),$C$1:J$1)} -> 1.7108495 | K90: {=XIRR(INDEX(IF(COLUMN($C76:K76)<COLUMN(K76),$C76:J76,K8),),$C$1:K$1)} -> 1.3749948 | ... BO90: {=XIRR(INDEX(IF(COLUMN($C76:BO76)<COLUMN(BO76),$C76:BN76,BO8),),$C$1:BO$1)} -> 0.20806598
A91: NPS G | B91: Debt | D91: {=XIRR(INDEX(IF(COLUMN($C77:D77)<COLUMN(D77),$C77:C77,D9),),$C$1:D$1)} -> 8.7547831 | E91: {=XIRR(INDEX(IF(COLUMN($C77:E77)<COLUMN(E77),$C77:D77,E9),),$C$1:E$1)} -> 1.5611061 | F91: {=XIRR(INDEX(IF(COLUMN($C77:F77)<COLUMN(F77),$C77:E77,F9),),$C$1:F$1)} -> 1.0155481 | G91: {=XIRR(INDEX(IF(COLUMN($C77:G77)<COLUMN(G77),$C77:F77,G9),),$C$1:G$1)} -> 4.3653477 | H91: {=XIRR(INDEX(IF(COLUMN($C77:H77)<COLUMN(H77),$C77:G77,H9),),$C$1:H$1)} -> 2.8594099 | I91: {=XIRR(INDEX(IF(COLUMN($C77:I77)<COLUMN(I77),$C77:H77,I9),),$C$1:I$1)} -> 2.0971239 | J91: {=XIRR(INDEX(IF(COLUMN($C77:J77)<COLUMN(J77),$C77:I77,J9),),$C$1:J$1)} -> 1.6723354 | K91: {=XIRR(INDEX(IF(COLUMN($C77:K77)<COLUMN(K77),$C77:J77,K9),),$C$1:K$1)} -> 1.3728804 | ... BO91: {=XIRR(INDEX(IF(COLUMN($C77:BO77)<COLUMN(BO77),$C77:BN77,BO9),),$C$1:BO$1)} -> 0.29364914
A92: PF | B92: Debt | D92: {=XIRR(INDEX(IF(COLUMN($C78:D78)<COLUMN(D78),$C78:C78,D10),),$C$1:D$1)} -> 0.22204776 | E92: {=XIRR(INDEX(IF(COLUMN($C78:E78)<COLUMN(E78),$C78:D78,E10),),$C$1:E$1)} -> 0.23583096 | F92: {=XIRR(INDEX(IF(COLUMN($C78:F78)<COLUMN(F78),$C78:E78,F10),),$C$1:F$1)} -> 0.44579334 | G92: {=XIRR(INDEX(IF(COLUMN($C78:G78)<COLUMN(G78),$C78:F78,G10),),$C$1:G$1)} -> 0.32259291 | H92: {=XIRR(INDEX(IF(COLUMN($C78:H78)<COLUMN(H78),$C78:G78,H10),),$C$1:H$1)} -> 0.24874637 | I92: {=XIRR(INDEX(IF(COLUMN($C78:I78)<COLUMN(I78),$C78:H78,I10),),$C$1:I$1)} -> 0.20396602 | J92: {=XIRR(INDEX(IF(COLUMN($C78:J78)<COLUMN(J78),$C78:I78,J10),),$C$1:J$1)} -> 0.17335926 | K92: {=XIRR(INDEX(IF(COLUMN($C78:K78)<COLUMN(K78),$C78:J78,K10),),$C$1:K$1)} -> 0.14430351 | ... BO92: {=XIRR(INDEX(IF(COLUMN($C78:BO78)<COLUMN(BO78),$C78:BN78,BO10),),$C$1:BO$1)} -> 0.089839163
A93: PPF | B93: Debt | D93: {=XIRR(INDEX(IF(COLUMN($C79:D79)<COLUMN(D79),$C79:C79,D11),),$C$1:D$1)} -> 2.9802322e-09 | E93: {=XIRR(INDEX(IF(COLUMN($C79:E79)<COLUMN(E79),$C79:D79,E11),),$C$1:E$1)} -> 2.9802322e-09 | F93: {=XIRR(INDEX(IF(COLUMN($C79:F79)<COLUMN(F79),$C79:E79,F11),),$C$1:F$1)} -> 0.29613392 | G93: {=XIRR(INDEX(IF(COLUMN($C79:G79)<COLUMN(G79),$C79:F79,G11),),$C$1:G$1)} -> 0.21475139 | H93: {=XIRR(INDEX(IF(COLUMN($C79:H79)<COLUMN(H79),$C79:G79,H11),),$C$1:H$1)} -> 0.16839563 | I93: {=XIRR(INDEX(IF(COLUMN($C79:I79)<COLUMN(I79),$C79:H79,I11),),$C$1:I$1)} -> 0.14008482 | J93: {=XIRR(INDEX(IF(COLUMN($C79:J79)<COLUMN(J79),$C79:I79,J11),),$C$1:J$1)} -> 0.12051367 | K93: {=XIRR(INDEX(IF(COLUMN($C79:K79)<COLUMN(K79),$C79:J79,K11),),$C$1:K$1)} -> 0.10172715 | ... BO93: {=XIRR(INDEX(IF(COLUMN($C79:BO79)<COLUMN(BO79),$C79:BN79,BO11),),$C$1:BO$1)} -> 0.078032038
A94: Cash | B94: Liquid | D94: 0 %
A95: Crypto | B95: Alternate | D95: 0 % | L95: {=XIRR(INDEX(IF(COLUMN($C81:L81)<COLUMN(L81),$C81:K81,L13),),$C$1:L$1)} -> 2.9802322e-09 | M95: {=XIRR(INDEX(IF(COLUMN($C81:M81)<COLUMN(M81),$C81:L81,M13),),$C$1:M$1)} -> 2.9802322e-09 | O95: {=XIRR(INDEX(IF(COLUMN($C81:O81)<COLUMN(O81),$C81:N81,O13),),$C$1:O$1)} -> 2.9802322e-09 | P95: {=XIRR(INDEX(IF(COLUMN($C81:P81)<COLUMN(P81),$C81:O81,P13),),$C$1:P$1)} -> 2.9802322e-09 | Q95: {=XIRR(INDEX(IF(COLUMN($C81:Q81)<COLUMN(Q81),$C81:P81,Q13),),$C$1:Q$1)} -> 2.9802322e-09 | R95: {=XIRR(INDEX(IF(COLUMN($C81:R81)<COLUMN(R81),$C81:Q81,R13),),$C$1:R$1)} -> 2.9802322e-09 | S95: {=XIRR(INDEX(IF(COLUMN($C81:S81)<COLUMN(S81),$C81:R81,S13),),$C$1:S$1)} -> 2.9802322e-09 | T95: {=XIRR(INDEX(IF(COLUMN($C81:T81)<COLUMN(T81),$C81:S81,T13),),$C$1:T$1)} -> 2.9802322e-09 | U95: {=XIRR(INDEX(IF(COLUMN($C81:U81)<COLUMN(U81),$C81:T81,U13),),$C$1:U$1)} -> 2.9802322e-09 | V95: {=XIRR(INDEX(IF(COLUMN($C81:V81)<COLUMN(V81),$C81:U81,V13),),$C$1:V$1)} -> 2.9802322e-09 | ... AU95: {=XIRR(INDEX(IF(COLUMN($C81:AU81)<COLUMN(AU81),$C81:AT81,AU13),),$C$1:AU$1)} -> 2.9802322e-09
A96: Bonds | B96: Debt | D96: {=XIRR(INDEX(IF(COLUMN($C82:D82)<COLUMN(D82),$C82:C82,D14),),$C$1:D$1)} -> 2.9802322e-09 | E96: {=XIRR(INDEX(IF(COLUMN($C82:E82)<COLUMN(E82),$C82:D82,E14),),$C$1:E$1)} -> 2.9802322e-09 | F96: {=XIRR(INDEX(IF(COLUMN($C82:F82)<COLUMN(F82),$C82:E82,F14),),$C$1:F$1)} -> 2.9802322e-09 | G96: {=XIRR(INDEX(IF(COLUMN($C82:G82)<COLUMN(G82),$C82:F82,G14),),$C$1:G$1)} -> 2.9802322e-09 | H96: {=XIRR(INDEX(IF(COLUMN($C82:H82)<COLUMN(H82),$C82:G82,H14),),$C$1:H$1)} -> 2.9802322e-09 | I96: {=XIRR(INDEX(IF(COLUMN($C82:I82)<COLUMN(I82),$C82:H82,I14),),$C$1:I$1)} -> 2.9802322e-09 | J96: {=XIRR(INDEX(IF(COLUMN($C82:J82)<COLUMN(J82),$C82:I82,J14),),$C$1:J$1)} -> 2.9802322e-09 | K96: {=XIRR(INDEX(IF(COLUMN($C82:K82)<COLUMN(K82),$C82:J82,K14),),$C$1:K$1)} -> 2.9802322e-09 | ... AU96: {=XIRR(INDEX(IF(COLUMN($C82:AU82)<COLUMN(AU82),$C82:AT82,AU14),),$C$1:AU$1)} -> 0.014143309
A97: Average | C97: =SUM(C86:C96) -> 0 | D97: =SUMPRODUCT(D4:D14,D86:D96)/(D15) -> 2.4890908 | E97: =SUMPRODUCT(E4:E14,E86:E96)/(E15) -> 1.2256394 | F97: =SUMPRODUCT(F4:F14,F86:F96)/(F15) -> 0.63256423 | G97: =SUMPRODUCT(G4:G14,G86:G96)/(G15) -> 0.35304521 | H97: =SUMPRODUCT(H4:H14,H86:H96)/(H15) -> 0.54567517 | I97: =SUMPRODUCT(I4:I14,I86:I96)/(I15) -> 0.50259568 | J97: =SUMPRODUCT(J4:J14,J86:J96)/(J15) -> 0.46271788 | K97: =SUMPRODUCT(K4:K14,K86:K96)/(K15) -> 0.49023386 | ... AN97: =SUMPRODUCT(AN4:AN14,AN86:AN96)/(AN15) -> 0.19324894 | AO97: {=XIRR(INDEX(IF(COLUMN($C83:AO83)<COLUMN(AO83),$C83:AN83,AO15),),$C$1:AO$1)} -> 0.17639888 | AP97: {=XIRR(INDEX(IF(COLUMN($C83:AP83)<COLUMN(AP83),$C83:AO83,AP15),),$C$1:AP$1)} -> 0.19368934 | AQ97: {=XIRR(INDEX(IF(COLUMN($C83:AQ83)<COLUMN(AQ83),$C83:AP83,AQ15),),$C$1:AQ$1)} -> 0.18692676 | AR97: {=XIRR(INDEX(IF(COLUMN($C83:AR83)<COLUMN(AR83),$C83:AR83,AR15),),$C$1:AR$1)} -> 0.18104244 | AS97: {=XIRR(INDEX(IF(COLUMN($C83:AS83)<COLUMN(AS83),$C83:AR83,AS15),),$C$1:AS$1)} -> 0.19996492 | AT97: {=XIRR(INDEX(IF(COLUMN($C83:AT83)<COLUMN(AT83),$C83:AS83,AT15),),$C$1:AT$1)} -> 0.21480778 | AU97: {=XIRR(INDEX(IF(COLUMN($C83:AU83)<COLUMN(AU83),$C83:AT83,AU15),),$C$1:AU$1)} -> 0.2058643 | AV97: {=XIRR(INDEX(IF(COLUMN($C83:AV83)<COLUMN(AV83),$C83:AU83,AV15),),$C$1:AV$1)} -> 0.20435154 | AW97: {=XIRR(INDEX(IF(COLUMN($C83:AW83)<COLUMN(AW83),$C83:AV83,AW15),),$C$1:AW$1)} -> 0.17635003 | AX97: {=XIRR(INDEX(IF(COLUMN($C83:AX83)<COLUMN(AX83),$C83:AW83,AX15),),$C$1:AX$1)} -> 0.17351411 | AY97: {=XIRR(INDEX(IF(COLUMN($C83:AY83)<COLUMN(AY83),$C83:AX83,AY15),),$C$1:AY$1)} -> 0.17221215 | AZ97: {=XIRR(INDEX(IF(COLUMN($C83:AZ83)<COLUMN(AZ83),$C83:AY83,AZ15),),$C$1:AZ$1)} -> 0.1465569 | ... BO97: {=XIRR(INDEX(IF(COLUMN($C83:BO83)<COLUMN(BO83),$C83:BN83,BO15),),$C$1:BO$1)} -> 0.12658898
A101: % RETURNS
A102: Stocks | B102: Equity | D102: =D44/(C4) -> 0.012768277 | E102: =E44/(D4) -> 0.038567524 | F102: =F44/(E4) -> 0.0068013839 | G102: =G44/(F4) -> 0.027143903 | H102: =H44/(G4) -> 0.067629072 | I102: =I44/(H4) -> 0.008468531 | J102: =J44/(I4) -> 0.035379804 | K102: =K44/(J4) -> 0.040029964 | ... BO102: =BO44/(BN4) -> 0.074028526 | BQ102: =AVERAGE(D102:BO102)*12 -> 0.12676874
A103: Mutual Funds | B103: Equity | D103: =D45/(C5) -> 0.01806237 | E103: =E45/(D5) -> 0.12753829 | F103: =F45/(E5) -> -0.016256131 | G103: =G45/(F5) -> -0.0073476293 | H103: =H45/(G5) -> 0.096461652 | I103: =I45/(H5) -> 0.04352283 | J103: =J45/(I5) -> 0.039531639 | K103: =K45/(J5) -> 0.067376963 | ... BO103: =BO45/(BN5) -> 0.13517487 | BQ103: =AVERAGE(D103:BO103)*12 -> 0.18184024
A104: Gold | B104: Gold | D104: =D46/(C6) -> -0.021136 | E104: =E46/(D6) -> -0.038519559 | F104: =F46/(E6) -> -0.011957596 | G104: =G46/(F6) -> 0.023625663 | H104: =H46/(G6) -> 0.016522158 | I104: =I46/(H6) -> -0.014150093 | J104: =J46/(I6) -> -0.0034612166 | K104: =K46/(J6) -> -0.011306392 | ... BO104: =BO46/(BN6) -> 0.02600832 | BQ104: =AVERAGE(D104:BO104)*12 -> 0.21354631
A105: NPS E | B105: Equity | D105: =D47/(C7) -> 0.31648352 | E105: =E47/(D7) -> 0.068447412 | F105: =F47/(E7) -> -0.08453125 | G105: =G47/(F7) -> -0.010069978 | H105: =H47/(G7) -> 0.084482759 | I105: =I47/(H7) -> 0.0093799682 | J105: =J47/(I7) -> 0.011560876 | K105: =K47/(J7) -> 0.089296836 | ... BO105: =BO47/(BN7) -> 0.024166667 | BQ105: =AVERAGE(D105:BO105)*12 -> 0.15268522
A106: NPS C | B106: Debt | D106: =D48/(C8) -> 0.21111111 | E106: =E48/(D8) -> -0.0091743119 | F106: =F48/(E8) -> 0.014814815 | G106: =G48/(F8) -> 0.44671533 | H106: =H48/(G8) -> 0.0065590313 | I106: =I48/(H8) -> 0 | J106: =J48/(I8) -> 0.0063909774 | K106: =K48/(J8) -> 0.010920184 | ... BO106: =BO48/(BN8) -> 0.045589693 | BQ106: =AVERAGE(D106:BO106)*12 -> 0.22956719
A107: NPS G | B107: Debt | D107: =D49/(C9) -> 0.21343284 | E107: =E49/(D9) -> -0.040590406 | F107: =F49/(E9) -> 0.026923077 | G107: =G49/(F9) -> 0.48014981 | H107: =H49/(G9) -> 0.0027834008 | I107: =I49/(H9) -> -0.0036167886 | J107: =J49/(I9) -> 0.0010383252 | K107: =K49/(J9) -> 0.01873793 | ... BO107: =BO49/(BN9) -> 0.20827943 | BQ107: =AVERAGE(D107:BO107)*12 -> 0.29720906
A108: PF | B108: Debt | D108: =D50/(C10) -> 0 | E108: =E50/(D10) -> 0 | F108: =F50/(E10) -> 0.081618169 | G108: =G50/(F10) -> 0 | H108: =H50/(G10) -> 0 | I108: =I50/(H10) -> 0 | J108: =J50/(I10) -> 0 | K108: =K50/(J10) -> 0 | ... BO108: =BO50/(BN10) -> 0 | BQ108: =AVERAGE(D108:BO108)*12 -> 0.086440314
A109: PPF | B109: Debt | D109: =D51/(C11) -> 0 | E109: =E51/(D11) -> 0 | F109: =F51/(E11) -> 0.068322981 | G109: =G51/(F11) -> 0 | H109: =H51/(G11) -> 0 | I109: =I51/(H11) -> 0 | J109: =J51/(I11) -> 0 | K109: =K51/(J11) -> 0 | ... BO109: =BO51/(BN11) -> 0 | BQ109: =AVERAGE(D109:BO109)*12 -> 0.078008155
...

Sheet 20260501 E
A1: Instrument | B1: Qty. | C1: Avg. cost | D1: LTP | E1: Invested | F1: Cur. val | G1: P&L | H1: Gain %
A2: 716GS2050-GS | B2: 100 | C2: 109.73 | D2: 99 | E2: 10972.5 | F2: 9900 | G2: -1072.5 | H2: =G2/E2 -> -0.097744361
A3: AJANTPHARM | B3: 19 | C3: 489.54 | D3: 2824.6 | E3: 9301.2 | F3: 53667.4 | G3: 44366.2 | H3: 0
A4: APOLLOTYRE | B4: 250 | C4: 183.59 | D4: 408.45 | E4: 45897.5 | F4: 102112.5 | G4: 56215 | H4: =G4/E4 -> 1.2247944
A5: AXISBANK | B5: 62 | C5: 708.24 | D5: 1268.3 | E5: 43910.6 | F5: 78634.6 | G5: 34724 | H5: =G5/E5 -> 0.79078856
A6: BAJAJ-AUTO | B6: 19 | C6: 3076.33 | D6: 9997.75 | E6: 58450.25 | F6: 189957.25 | G6: 131507 | H6: =G6/E6 -> 2.2498963
A7: BAJFINANCE | B7: 80 | C7: 673.1 | D7: 937 | E7: 53848.35 | F7: 74960 | G7: 21111.65 | H7: =G7/E7 -> 0.39205751
A8: BALKRISIND | B8: 15 | C8: 2427.47 | D8: 2160.8 | E8: 36412 | F8: 32412 | G8: -4000 | H8: =G8/E8 -> -0.10985389
A9: BANKBARODA | B9: 184 | C9: 188.19 | D9: 263.5 | E9: 34627.15 | F9: 48484 | G9: 13856.85 | H9: =G9/E9 -> 0.40017299
A10: BANKIETF | B10: 8500 | C10: 50.47 | D10: 56.18 | E10: 429035.72 | F10: 477530 | G10: 48494.28 | H10: =G10/E10 -> 0.11303087
A11: BHARTIARTL | B11: 180 | C11: 322.89 | D11: 1886.8 | E11: 58120 | F11: 339624 | G11: 281504 | H11: =G11/E11 -> 4.8434962
A12: BRIGADE | B12: 40 | C12: 446.04 | D12: 790 | E12: 17841.6 | F12: 31600 | G12: 13758.4 | H12: =G12/E12 -> 0.7711416
A13: BRITANNIA | B13: 14 | C13: 3489.94 | D13: 5726 | E13: 48859.1 | F13: 80164 | G13: 31304.9 | H13: =G13/E13 -> 0.6407179
A14: CASTROLIND | B14: 180 | C14: 155.25 | D14: 184.85 | E14: 27945 | F14: 33273 | G14: 5328 | H14: =G14/E14 -> 0.19066023
A15: CIEINDIA | B15: 88 | C15: 373.58 | D15: 473.75 | E15: 32874.85 | F15: 41690 | G15: 8815.15 | H15: 0
A16: CIPLA | B16: 45 | C16: 990.66 | D16: 1309.9 | E16: 44579.85 | F16: 58945.5 | G16: 14365.65 | H16: =G16/E16 -> 0.32224536
A17: COALINDIA | B17: 470 | C17: 194.39 | D17: 481.45 | E17: 91363.5 | F17: 226281.5 | G17: 134918 | H17: =G17/E17 -> 1.4767166
A18: COFORGE | B18: 65 | C18: 909.05 | D18: 1195.95 | E18: 59088.4 | F18: 77736.75 | G18: 18648.35 | H18: =G18/E18 -> 0.31560086
A19: COLPAL | B19: 21 | C19: 1503.03 | D19: 2096.75 | E19: 31563.7 | F19: 44031.75 | G19: 12468.05 | H19: =G19/E19 -> 0.39501231
A20: DLF | B20: 66 | C20: 557.49 | D20: 587.15 | E20: 36794.1 | F20: 38751.9 | G20: 1957.8 | H20: =G20/E20 -> 0.053209618
A21: DMART | B21: 12 | C21: 3474.64 | D21: 4590.7 | E21: 41695.7 | F21: 55088.4 | G21: 13392.7 | H21: =G21/E21 -> 0.32120099
A22: DRREDDY | B22: 60 | C22: 992.6 | D22: 1322.95 | E22: 59555.95 | F22: 79377 | G22: 19821.05 | H22: =G22/E22 -> 0.33281393
A23: EICHERMOT | B23: 7 | C23: 3506.83 | D23: 7110.4 | E23: 24547.8 | F23: 49772.8 | G23: 25225 | H23: =G23/E23 -> 1.027587
A24: EMBASSY-RR | B24: 92 | C24: 359.33 | D24: 424.76 | E24: 33058.28 | F24: 39077.92 | G24: 6019.64 | H24: =G24/E24 -> 0.18209175
A25: ENDURANCE | B25: 24 | C25: 2007.86 | D25: 2331.2 | E25: 48188.7 | F25: 55948.8 | G25: 7760.1 | H25: =G25/E25 -> 0.16103568
A26: ENRIN | B26: 35 | C26: 234.44 | D26: 3282.3 | E26: 8205.53 | F26: 114880.5 | G26: 106674.97 | H26: =G26/E26 -> 13.000375
A27: ERIS | B27: 42 | C27: 664.74 | D27: 1322.9 | E27: 27918.9 | F27: 55561.8 | G27: 27642.9 | H27: =G27/E27 -> 0.99011422
... A63: PRESTIGE | B63: 33 | C63: 761.09 | D63: 1414.4 | E63: 25116 | F63: 46675.2 | G63: 21559.2 | H63: =G63/E63 -> 0.85838509
A64: 738REC27TF | B64: 20 | C64: 0 | D64: 1055 | E64: 0 | F64: 21100 | G64: 0
A65: SBILIFE | B65: 54 | C65: 1278.86 | D65: 1819.8 | E65: 69058.3 | F65: 98269.2 | G65: 29210.9 | H65: =G65/E65 -> 0.42298898
A66: SBIN | B66: 66 | C66: 426.28 | D66: 1068.45 | E66: 28134.5 | F66: 70517.7 | G66: 42383.2 | H66: =G66/E66 -> 1.5064494
A67: SGBAUG28V | B67: 10 | C67: 5284 | D67: 14843.62 | E67: 52840 | F67: 148436.2 | G67: 95596.2 | H67: =G67/E67 -> 1.8091635
A68: SGBJUL28IV-GB | B68: 5 | C68: 4802 | D68: 14815.81 | E68: 24010 | F68: 74079.05 | G68: 50069.05 | H68: =G68/E68 -> 2.0853415
A69: SGBSEP28VI-GB | B69: 10 | C69: 5002.45 | D69: 14797.43 | E69: 50024.5 | F69: 147974.3 | G69: 97949.8 | H69: =G69/E69 -> 1.9580366
A70: SIEMENS | B70: 35 | C70: 749.79 | D70: 3817.8 | E70: 26242.52 | F70: 133623 | G70: 107380.48 | H70: =G70/E70 -> 4.0918509
A71: SUNPHARMA | B71: 139 | C71: 582.57 | D71: 1808.3 | E71: 80977.15 | F71: 251353.7 | G71: 170376.55 | H71: =G71/E71 -> 2.1040077
A72: SYNGENE | B72: 75 | C72: 581.84 | D72: 467.9 | E72: 43638 | F72: 35092.5 | G72: -8545.5 | H72: =G72/E72 -> -0.19582703
A73: TATACONSUM | B73: 46 | C73: 794.51 | D73: 1144.6 | E73: 36547.3 | F73: 52651.6 | G73: 16104.3 | H73: =G73/E73 -> 0.44064267
A74: TATASTEEL | B74: 1050 | C74: 40.48 | D74: 211.36 | E74: 42500.25 | F74: 221928 | G74: 179427.75 | H74: =G74/E74 -> 4.2218046
A75: TCS | B75: 33 | C75: 3575.9 | D75: 2473.9 | E75: 118004.55 | F75: 81638.7 | G75: -36365.85 | H75: =G75/E75 -> -0.30817329
A76: TITAN | B76: 24 | C76: 2584.4 | D76: 4385.95 | E76: 62025.6 | F76: 105262.8 | G76: 43237.2 | H76: =G76/E76 -> 0.69708636
A77: TVSMNCRPS | B77: 56 | C77: 0 | D77: 10.21 | E77: 0 | F77: 571.76 | G77: 571.76 | H77: 0
A78: TVSMOTOR | B78: 14 | C78: 2306.82 | D78: 3492.9 | E78: 32295.45 | F78: 48900.6 | G78: 16605.15 | H78: =G78/E78 -> 0.51416376
A79: UNOMINDA | B79: 30 | C79: 373.77 | D79: 1112.8 | E79: 11213.05 | F79: 33384 | G79: 22170.95 | H79: =G79/E79 -> 1.9772453
A80: VBL | B80: 110 | C80: 130.18 | D80: 514.15 | E80: 14319.65 | F80: 56556.5 | G80: 42236.85 | H80: =G80/E80 -> 2.9495728
A81: ZYDUSLIFE | B81: 54 | C81: 896.15 | D81: 891.9 | E81: 48392.1 | F81: 48162.6 | G81: -229.5 | H81: =G81/E81 -> -0.0047425096
A104: Total | B104: =SUM(B2:B103) -> 18788 | E104: =SUM(E2:E103) -> 4069211 | F104: =SUM(F2:F103) -> 7092167.9 | G104: =SUM(G2:G103) -> 3001857 | H104: =G104/E104 -> 0.73770001

Sheet 20260501 MF
A1: Scheme | B1: Scheme Type | C1: Quantity | D1: Current Price | E1: Average Buy NAV | F1: Amount Invested | G1: Current Valuation | H1: Unrealised Gain/Loss | I1: Gain/ Loss %
A2: Axis Greater China Equity FoF Direct-Growth | B2: Equity : International | C2: 90243.51 | D2: 12.32 | E2: 8.8656 | F2: 800059.99 | G2: 1111800 | H2: =G2-F2 -> 311740.05 | I2: =H2/F2 -> 0.38964584
A3: Axis Midcap Direct Plan-Growth | B3: Equity : Mid Cap | C3: 4080.966 | D3: 134.97 | E3: 68.6078 | F3: 279986.11 | G3: 550807.98 | H3: =G3-F3 -> 270821.87 | I3: =H3/F3 -> 0.96726895
A4: Axis Small Cap Fund Direct-Growth | B4: Equity : Small Cap | C4: 14235.332 | D4: 123.36 | E4: 47.7661 | F4: 679966.93 | G4: 1756070.6 | H4: =G4-F4 -> 1076103.6 | I4: =H4/F4 -> 1.5825823
A5: Canara Robeco Small Cap Fund Direct - Growth | B5: Equity : Small Cap | C5: 30844.641 | D5: 42.83 | E5: 33.2294 | F5: 1024948.8 | G5: 1321076 | H5: =G5-F5 -> 296127.22 | I5: =H5/F5 -> 0.28891905
A6: Edelweiss US Technology Equity FoF Direct - Growth | B6: Equity : International | C6: 16944.232 | D6: 36.8142 | E6: 28.9171 | F6: 489977.93 | G6: 623788.35 | H6: =G6-F6 -> 133810.41 | I6: =H6/F6 -> 0.27309477
A7: HDFC BSE Sensex Index Fund Direct-Growth | B7: Equity : Large Cap | C7: 1057.322 | D7: 736.8909 | E7: 390.4791 | F7: 412862.15 | G7: 779130.96 | H7: =G7-F7 -> 366268.81 | I7: =H7/F7 -> 0.88714555
A8: HDFC Small Cap Fund Direct- Growth | B8: Equity : Small Cap | C8: 4306.576 | D8: 151.518 | E8: 44.3917 | F8: 191176.23 | G8: 652523.78 | H8: =G8-F8 -> 461347.55 | I8: =H8/F8 -> 2.4132056
A9: Kotak Midcap Fund Direct-Growth | B9: Equity : Mid Cap | C9: 6304.493 | D9: 162.407 | E9: 51.3112 | F9: 323491.23 | G9: 1023893.8 | H9: =G9-F9 -> 700402.56 | I9: =H9/F9 -> 2.1651361
A10: Motilal Oswal Nasdaq 100 FOF Direct - Growth | B10: Equity : International | C10: 13136.35 | D10: 63.5657 | E10: 29.6871 | F10: 389980.45 | G10: 835021.28 | H10: =G10-F10 -> 445040.84 | I10: =H10/F10 -> 1.1411876
A11: Navi Nasdaq100 US Specific Equity Passive FoF Direct - Growth | B11: Equity : International | C11: 82131.044 | D11: 22.9994 | E11: 9.9227 | F11: 814959.24 | G11: 1888964.7 | H11: =G11-F11 -> 1074005.5 | I11: =H11/F11 -> 1.317864
A12: Navi Nifty 50 Index Fund Direct - Growth | B12: Equity : Large Cap | C12: 84098.659 | D12: 15.8551 | E12: 13.2042 | F12: 1110455 | G12: 1333392.6 | H12: =G12-F12 -> 222937.62 | I12: =H12/F12 -> 0.2007624
A13: Navi Nifty Next 50 Index Fund Direct - Growth | B13: Equity : Large Cap | C13: 46779.584 | D13: 16.7677 | E13: 14.1187 | F13: 660466.98 | G13: 784386.03 | H13: =G13-F13 -> 123919.05 | I13: =H13/F13 -> 0.18762339
... A19: UTI Nifty Next 50 Index Fund Direct - Growth | B19: Equity : Large Cap | C19: 18996.168 | D19: 26.125 | E19: 9.47 | F19: 179893.71 | G19: 496274.89 | H19: =G19-F19 -> 316381.18 | I19: =H19/F19 -> 1.7587117
A22: Total | C22: =SUM(C2:C21) -> 499884.03 | F22: =SUM(F2:F21) -> 10470404 | G22: =SUM(G2:G21) -> 17494108 | H22: =SUM(H2:H21) -> 7023704.3 | I22: =H22/F22 -> 0.67081502

Sheet 20260402 E
A1: Instrument | B1: Qty. | C1: Avg. cost | D1: LTP | E1: Invested | F1: Cur. val | G1: P&L | H1: Gain %
A2: 716GS2050-GS | B2: 100 | C2: 109.73 | D2: 104.9 | E2: 10972.5 | F2: 10490 | G2: -482.5 | H2: =G2/E2 -> -0.04397357
A3: 738REC27TF-N2 | B3: 20 | C3: 0 | D3: 1051 | E3: 0 | F3: 21020 | G3: 0 | H3: 0
A4: AJANTPHARM | B4: 19 | C4: 489.54 | D4: 2821.35 | E4: 9301.2 | F4: 53605.65 | G4: 44304.45 | H4: =G4/E4 -> 4.7633047
A5: APOLLOTYRE | B5: 250 | C5: 183.59 | D5: 415.25 | E5: 45897.5 | F5: 103812.5 | G5: 57915 | H5: =G5/E5 -> 1.2618334
A6: AXISBANK | B6: 62 | C6: 708.24 | D6: 1193.1 | E6: 43910.6 | F6: 73972.2 | G6: 30061.6 | H6: =G6/E6 -> 0.68460918
A7: BAJAJ-AUTO | B7: 19 | C7: 3076.33 | D7: 8899 | E7: 58450.25 | F7: 169081 | G7: 110630.75 | H7: =G7/E7 -> 1.8927336
A8: BAJFINANCE | B8: 80 | C8: 673.1 | D8: 817.3 | E8: 53848.35 | F8: 65384 | G8: 11535.65 | H8: =G8/E8 -> 0.21422476
A9: BALKRISIND | B9: 15 | C9: 2427.47 | D9: 2127.6 | E9: 36412 | F9: 31914 | G9: -4498 | H9: =G9/E9 -> -0.1235307
A10: BANKBARODA | B10: 184 | C10: 188.19 | D10: 252.05 | E10: 34627.15 | F10: 46377.2 | G10: 11750.05 | H10: =G10/E10 -> 0.33933055
A11: BANKIETF | B11: 8500 | C11: 50.47 | D11: 52.89 | E11: 429035.72 | F11: 449565 | G11: 20529.28 | H11: =G11/E11 -> 0.047849815
A12: BHARTIARTL | B12: 180 | C12: 322.89 | D12: 1782 | E12: 58120 | F12: 320760 | G12: 262640 | H12: =G12/E12 -> 4.5189264
A13: BRIGADE | B13: 40 | C13: 446.04 | D13: 672.6 | E13: 17841.6 | F13: 26904 | G13: 9062.4 | H13: =G13/E13 -> 0.50793651
A14: BRITANNIA | B14: 14 | C14: 3489.94 | D14: 5476.05 | E14: 48859.1 | F14: 76664.7 | G14: 27805.6 | H14: =G14/E14 -> 0.56909767
A15: CASTROLIND | B15: 180 | C15: 155.25 | D15: 176.5 | E15: 27945 | F15: 31770 | G15: 3825 | H15: 0
A16: CIEINDIA | B16: 88 | C16: 373.58 | D16: 455.1 | E16: 32874.85 | F16: 40048.8 | G16: 7173.95 | H16: =G16/E16 -> 0.21822001
A17: CIPLA | B17: 45 | C17: 990.66 | D17: 1195.9 | E17: 44579.85 | F17: 53815.5 | G17: 9235.65 | H17: =G17/E17 -> 0.20717095
A18: COALINDIA | B18: 470 | C18: 194.39 | D18: 449.4 | E18: 91363.5 | F18: 211218 | G18: 119854.5 | H18: =G18/E18 -> 1.3118423
A19: COFORGE | B19: 65 | C19: 909.05 | D19: 1153.9 | E19: 59088.4 | F19: 75003.5 | G19: 15915.1 | H19: =G19/E19 -> 0.2693439
A20: COLPAL | B20: 21 | C20: 1503.03 | D20: 1819.7 | E20: 31563.7 | F20: 38213.7 | G20: 6650 | H20: =G20/E20 -> 0.21068506
A21: DLF | B21: 66 | C21: 557.49 | D21: 509.75 | E21: 36794.1 | F21: 33643.5 | G21: -3150.6 | H21: =G21/E21 -> -0.085627859
A22: DMART | B22: 12 | C22: 3474.64 | D22: 4271.6 | E22: 41695.7 | F22: 51259.2 | G22: 9563.5 | H22: =G22/E22 -> 0.22936418
A23: DRREDDY | B23: 60 | C23: 992.6 | D23: 1209.6 | E23: 59555.95 | F23: 72576 | G23: 13020.05 | H23: =G23/E23 -> 0.21861879
A24: EICHERMOT | B24: 7 | C24: 3506.83 | D24: 6825.65 | E24: 24547.8 | F24: 47779.55 | G24: 23231.75 | H24: =G24/E24 -> 0.94638827
A25: EMBASSY-RR | B25: 92 | C25: 359.33 | D25: 420.9 | E25: 33058.28 | F25: 38722.8 | G25: 5664.52 | H25: =G25/E25 -> 0.17134951
A26: ENDURANCE | B26: 24 | C26: 2007.86 | D26: 2252 | E26: 48188.7 | F26: 54048 | G26: 5859.3 | H26: =G26/E26 -> 0.12159075
A27: ENRIN | B27: 35 | C27: 234.44 | D27: 2615.55 | E27: 8205.53 | F27: 91544.25 | G27: 83338.72 | H27: =G27/E27 -> 10.156409
... A63: PIDILITIND | B63: 60 | C63: 1249.57 | D63: 1307 | E63: 74974.35 | F63: 78420 | G63: 3445.65 | H63: =G63/E63 -> 0.045957718
A64: PRESTIGE | B64: 33 | C64: 761.09 | D64: 1145 | E64: 25116 | F64: 37785 | G64: 12669
A65: SBILIFE | B65: 54 | C65: 1278.86 | D65: 1790.5 | E65: 69058.3 | F65: 96687 | G65: 27628.7 | H65: =G65/E65 -> 0.40007791
A66: SBIN | B66: 66 | C66: 426.28 | D66: 1017.9 | E66: 28134.5 | F66: 67181.4 | G66: 39046.9 | H66: =G66/E66 -> 1.3878654
A67: SGBAUG28V | B67: 10 | C67: 5284 | D67: 14305.14 | E67: 52840 | F67: 143051.4 | G67: 90211.4 | H67: =G67/E67 -> 1.7072559
A68: SGBJUL28IV-GB | B68: 5 | C68: 4802 | D68: 14270.1 | E68: 24010 | F68: 71350.5 | G68: 47340.5 | H68: =G68/E68 -> 1.9716993
A69: SGBSEP28VI-GB | B69: 10 | C69: 5002.45 | D69: 14301.35 | E69: 50024.5 | F69: 143013.5 | G69: 92989 | H69: =G69/E69 -> 1.8588692
A70: SIEMENS | B70: 35 | C70: 749.79 | D70: 3017 | E70: 26242.52 | F70: 105595 | G70: 79352.48 | H70: =G70/E70 -> 3.0238133
A71: SUNPHARMA | B71: 139 | C71: 582.57 | D71: 1728.5 | E71: 80977.15 | F71: 240261.5 | G71: 159284.35 | H71: =G71/E71 -> 1.9670284
A72: SYNGENE | B72: 75 | C72: 581.84 | D72: 396.4 | E72: 43638 | F72: 29730 | G72: -13908 | H72: =G72/E72 -> -0.31871305
A73: TATACONSUM | B73: 46 | C73: 794.51 | D73: 1023.8 | E73: 36547.3 | F73: 47094.8 | G73: 10547.5 | H73: =G73/E73 -> 0.28859861
A74: TATASTEEL | B74: 1050 | C74: 40.48 | D74: 194.7 | E74: 42500.25 | F74: 204435 | G74: 161934.75 | H74: =G74/E74 -> 3.810207
A75: TCS | B75: 33 | C75: 3575.9 | D75: 2408.3 | E75: 118004.55 | F75: 79473.9 | G75: -38530.65 | H75: =G75/E75 -> -0.32651834
A76: TITAN | B76: 24 | C76: 2584.4 | D76: 4065.5 | E76: 62025.6 | F76: 97572 | G76: 35546.4 | H76: =G76/E76 -> 0.5730924
A77: TVSMNCRPS-P1 | B77: 56 | C77: 0 | D77: 10.15 | E77: 0 | F77: 568.4 | G77: 568.4 | H77: 0
A78: TVSMOTOR | B78: 14 | C78: 2306.82 | D78: 3425.8 | E78: 32295.45 | F78: 47961.2 | G78: 15665.75 | H78: =G78/E78 -> 0.48507607
A79: UNOMINDA | B79: 30 | C79: 373.77 | D79: 1044.9 | E79: 11213.05 | F79: 31347 | G79: 20133.95 | H79: =G79/E79 -> 1.7955819
A80: VBL | B80: 110 | C80: 130.18 | D80: 401.85 | E80: 14319.65 | F80: 44203.5 | G80: 29883.85 | H80: =G80/E80 -> 2.086912
A81: ZYDUSLIFE | B81: 54 | C81: 896.15 | D81: 863.45 | E81: 48392.1 | F81: 46626.3 | G81: -1765.8 | H81: =G81/E81 -> -0.036489427
A104: Total | B104: =SUM(B2:B103) -> 18788 | E104: =SUM(E2:E103) -> 4069211 | F104: =SUM(F2:F103) -> 6628578.9 | G104: =SUM(G2:G103) -> 2538347.9 | H104: =G104/E104 -> 0.62379365

Sheet 20260402 MF
A1: Scheme | B1: Scheme Type | C1: Quantity | D1: Current Price | E1: Average Buy NAV | F1: Amount Invested | G1: Current Valuation | H1: Unrealised Gain/Loss | I1: Gain/ Loss %
A2: Axis Greater China Equity FoF Direct-Growth | B2: Equity : International | C2: 90243.51 | D2: 10.91 | E2: 8.8656 | F2: 800059.99 | G2: 984556.69 | H2: =G2-F2 -> 184496.7 | I2: =H2/F2 -> 0.23060358
A3: Axis Midcap Direct Plan-Growth | B3: Equity : Mid Cap | C3: 4080.966 | D3: 120.14 | E3: 68.6078 | F3: 279986.11 | G3: 490287.26 | H3: =G3-F3 -> 210301.15 | I3: =H3/F3 -> 0.75111278
A4: Axis Small Cap Fund Direct-Growth | B4: Equity : Small Cap | C4: 14235.332 | D4: 108.18 | E4: 47.7661 | F4: 679966.93 | G4: 1539978.2 | H4: =G4-F4 -> 860011.29 | I4: =H4/F4 -> 1.264784
A5: Canara Robeco Small Cap Fund Direct - Growth | B5: Equity : Small Cap | C5: 30844.641 | D5: 37.37 | E5: 33.2294 | F5: 1024948.8 | G5: 1152664.2 | H5: =G5-F5 -> 127715.48 | I5: =H5/F5 -> 0.1246067
A6: Edelweiss US Technology Equity FoF Direct - Growth | B6: Equity : International | C6: 16800.385 | D6: 31.1521 | E6: 28.8671 | F6: 484977.81 | G6: 523367.27 | H6: =G6-F6 -> 38389.461 | I6: =H6/F6 -> 0.079157149
A7: HDFC BSE Sensex Index Fund Direct-Growth | B7: Equity : Large Cap | C7: 1057.322 | D7: 684.0718 | E7: 390.4791 | F7: 412862.15 | G7: 723284.16 | H7: =G7-F7 -> 310422.02 | I7: =H7/F7 -> 0.75187813
A8: HDFC Small Cap Fund Direct- Growth | B8: Equity : Small Cap | C8: 4306.576 | D8: 135.383 | E8: 44.3917 | F8: 191176.23 | G8: 583037.18 | H8: =G8-F8 -> 391860.95 | I8: =H8/F8 -> 2.0497368
A9: Kotak Midcap Fund Direct-Growth | B9: Equity : Mid Cap | C9: 6304.493 | D9: 142.194 | E9: 51.3112 | F9: 323491.23 | G9: 896461.08 | H9: =G9-F9 -> 572969.84 | I9: =H9/F9 -> 1.7712067
A10: Motilal Oswal Nasdaq 100 FOF Direct - Growth | B10: Equity : International | C10: 13136.35 | D10: 48.8762 | E10: 29.6871 | F10: 389980.45 | G10: 642054.87 | H10: =G10-F10 -> 252074.42 | I10: =H10/F10 -> 0.64637709
A11: Navi Nasdaq100 US Specific Equity Passive FoF Direct - Growth | B11: Equity : International | C11: 82131.044 | D11: 19.4144 | E11: 9.9227 | F11: 814959.24 | G11: 1594524.9 | H11: =G11-F11 -> 779565.7 | I11: =H11/F11 -> 0.95657016
A12: Navi Nifty 50 Index Fund Direct - Growth | B12: Equity : Large Cap | C12: 84098.659 | D12: 14.6427 | E12: 13.2042 | F12: 1110455 | G12: 1231431.4 | H12: =G12-F12 -> 120976.4 | I12: =H12/F12 -> 0.10894309
A13: Navi Nifty Next 50 Index Fund Direct - Growth | B13: Equity : Large Cap | C13: 46779.584 | D13: 14.3514 | E13: 14.1187 | F13: 660466.98 | G13: 671352.52 | H13: =G13-F13 -> 10885.544 | I13: =H13/F13 -> 0.016481587
... A19: UTI Nifty Next 50 Index Fund Direct - Growth | B19: Equity : Large Cap | C19: 18996.168 | D19: 22.3606 | E19: 9.47 | F19: 179893.71 | G19: 424765.71 | H19: =G19-F19 -> 244872 | I19: =H19/F19 -> 1.3612038
A22: Total | C22: =SUM(C2:C21) -> 499740.18 | F22: =SUM(F2:F21) -> 10465404 | G22: =SUM(G2:G21) -> 15406532 | H22: =SUM(H2:H21) -> 4941128.3 | I22: =H22/F22 -> 0.47213929

Sheet 20260301 E
A1: Instrument | B1: Qty. | C1: Avg. cost | D1: LTP | E1: Total Investment | F1: Cur. val | G1: P&L | H1: Gain %
A2: 716GS2050-GS | B2: 100 | C2: 109.73 | D2: 104.9 | E2: 10972.5 | F2: 10490 | G2: -482.5 | H2: =G2/E2 -> -0.04397357
A3: AJANTPHARM | B3: 19 | C3: 489.54 | D3: 2979.2 | E3: 9301.2 | F3: 56604.8 | G3: 47303.6 | H3: =G3/E3 -> 5.0857524
A4: APOLLOTYRE | B4: 250 | C4: 183.59 | D4: 454.2 | E4: 45897.5 | F4: 113550 | G4: 67652.5 | H4: =G4/E4 -> 1.473991
A5: AXISBANK | B5: 62 | C5: 708.24 | D5: 1383.9 | E5: 43910.6 | F5: 85801.8 | G5: 41891.2 | H5: =G5/E5 -> 0.9540111
A6: BAJAJ-AUTO | B6: 19 | C6: 3076.33 | D6: 9972.5 | E6: 58450.25 | F6: 189477.5 | G6: 131027.25 | H6: =G6/E6 -> 2.2416884
A7: BAJFINANCE | B7: 80 | C7: 673.1 | D7: 996.5 | E7: 53848.35 | F7: 79720 | G7: 25871.65 | H7: =G7/E7 -> 0.4804539
A8: BALKRISIND | B8: 15 | C8: 2427.47 | D8: 2375 | E8: 36412 | F8: 35625 | G8: -787 | H8: =G8/E8 -> -0.021613754
A9: BANKBARODA | B9: 184 | C9: 188.19 | D9: 321.95 | E9: 34627.15 | F9: 59238.8 | G9: 24611.65 | H9: =G9/E9 -> 0.71076164
A10: BANKIETF | B10: 8500 | C10: 50.47 | D10: 61.93 | E10: 429035.72 | F10: 526405 | G10: 97369.28 | H10: =G10/E10 -> 0.22694912
A11: BHARTIARTL | B11: 180 | C11: 322.89 | D11: 1879.75 | E11: 58120 | F11: 338355 | G11: 280235 | H11: =G11/E11 -> 4.8216621
A12: BRIGADE | B12: 40 | C12: 446.04 | D12: 694.05 | E12: 17841.6 | F12: 27762 | G12: 9920.4 | H12: =G12/E12 -> 0.55602637
A13: BRITANNIA | B13: 14 | C13: 3489.94 | D13: 6002.5 | E13: 48859.1 | F13: 84035 | G13: 35175.9 | H13: =G13/E13 -> 0.71994572
A14: CASTROLIND | B14: 180 | C14: 155.25 | D14: 187.35 | E14: 27945 | F14: 33723 | G14: 5778 | H14: =G14/E14 -> 0.20676329
A15: CIEINDIA | B15: 88 | C15: 373.58 | D15: 471.8 | E15: 32874.85 | F15: 41518.4 | G15: 8643.55 | H15: 0
A16: CIPLA | B16: 45 | C16: 990.66 | D16: 1348.2 | E16: 44579.85 | F16: 60669 | G16: 16089.15 | H16: =G16/E16 -> 0.36090633
A17: COALINDIA | B17: 470 | C17: 194.39 | D17: 430.7 | E17: 91363.5 | F17: 202429 | G17: 111065.5 | H17: =G17/E17 -> 1.2156441
A18: COFORGE | B18: 65 | C18: 909.05 | D18: 1186.35 | E18: 59088.4 | F18: 77112.75 | G18: 18024.35 | H18: =G18/E18 -> 0.30504041
A19: COLPAL | B19: 21 | C19: 1503.03 | D19: 2254.5 | E19: 31563.7 | F19: 47344.5 | G19: 15780.8 | H19: =G19/E19 -> 0.49996673
A20: DLF | B20: 66 | C20: 557.49 | D20: 604.15 | E20: 36794.1 | F20: 39873.9 | G20: 3079.8 | H20: =G20/E20 -> 0.083703637
A21: DMART | B21: 12 | C21: 3474.64 | D21: 3847.6 | E21: 41695.7 | F21: 46171.2 | G21: 4475.5 | H21: =G21/E21 -> 0.10733721
A22: DRREDDY | B22: 60 | C22: 992.6 | D22: 1287.2 | E22: 59555.95 | F22: 77232 | G22: 17676.05 | H22: =G22/E22 -> 0.29679738
A23: EICHERMOT | B23: 7 | C23: 3506.83 | D23: 8015.7 | E23: 24547.8 | F23: 56109.9 | G23: 31562.1 | H23: =G23/E23 -> 1.2857405
A24: EMBASSY-RR | B24: 92 | C24: 359.33 | D24: 425.03 | E24: 33058.28 | F24: 39102.76 | G24: 6044.48 | H24: =G24/E24 -> 0.18284315
A25: ENDURANCE | B25: 24 | C25: 2007.86 | D25: 2661.7 | E25: 48188.7 | F25: 63880.8 | G25: 15692.1 | H25: =G25/E25 -> 0.32563858
A26: ENRIN | B26: 35 | C26: 234.44 | D26: 2930.9 | E26: 8205.53 | F26: 102581.5 | G26: 94375.97 | H26: =G26/E26 -> 11.501508
A27: ERIS | B27: 42 | C27: 664.74 | D27: 1361 | E27: 27918.9 | F27: 57162 | G27: 29243.1 | H27: =G27/E27 -> 1.0474302
... A63: PRESTIGE | B63: 33 | C63: 761.09 | D63: 1393 | E63: 25116 | F63: 45969 | G63: 20853 | H63: =G63/E63 -> 0.83026756
A64: 738REC27TF-N2 | B64: 20 | C64: 0 | D64: 1042.5 | E64: 0 | F64: 20850 | G64: 0
A65: SBILIFE | B65: 54 | C65: 1278.86 | D65: 2037.2 | E65: 69058.3 | F65: 110008.8 | G65: 40950.5 | H65: =G65/E65 -> 0.59298448
A66: SBIN | B66: 66 | C66: 426.28 | D66: 1202 | E66: 28134.5 | F66: 79332 | G66: 51197.5 | H66: =G66/E66 -> 1.8197409
A67: SGBAUG28V | B67: 10 | C67: 5284 | D67: 15715 | E67: 52840 | F67: 157150 | G67: 104310 | H67: =G67/E67 -> 1.9740727
A68: SGBJUL28IV-GB | B68: 5 | C68: 4802 | D68: 15697 | E68: 24010 | F68: 78485 | G68: 54475 | H68: =G68/E68 -> 2.2688463
A69: SGBSEP28VI-GB | B69: 10 | C69: 5002.45 | D69: 15740 | E69: 50024.5 | F69: 157400 | G69: 107375.5 | H69: =G69/E69 -> 2.1464582
A70: SIEMENS | B70: 35 | C70: 749.79 | D70: 3430 | E70: 26242.52 | F70: 120050 | G70: 93807.48 | H70: =G70/E70 -> 3.5746369
A71: SUNPHARMA | B71: 139 | C71: 582.57 | D71: 1738.1 | E71: 80977.15 | F71: 241595.9 | G71: 160618.75 | H71: =G71/E71 -> 1.9835071
A72: SYNGENE | B72: 75 | C72: 581.84 | D72: 422.35 | E72: 43638 | F72: 31676.25 | G72: -11961.75 | H72: =G72/E72 -> -0.27411316
A73: TATACONSUM | B73: 46 | C73: 794.51 | D73: 1141.15 | E73: 36547.3 | F73: 52492.9 | G73: 15945.6 | H73: =G73/E73 -> 0.43630036
A74: TATASTEEL | B74: 1050 | C74: 40.48 | D74: 212.35 | E74: 42500.25 | F74: 222967.5 | G74: 180467.25 | H74: =G74/E74 -> 4.2462633
A75: TCS | B75: 33 | C75: 3575.9 | D75: 2637.4 | E75: 118004.55 | F75: 87034.2 | G75: -30970.35 | H75: =G75/E75 -> -0.26245047
A76: TITAN | B76: 24 | C76: 2584.4 | D76: 4325.6 | E76: 62025.6 | F76: 103814.4 | G76: 41788.8 | H76: =G76/E76 -> 0.67373472
... A80: ZYDUSLIFE | B80: 54 | C80: 896.15 | D80: 922.85 | E80: 48392.1 | F80: 49833.9 | G80: 1441.8 | H80: =G80/E80 -> 0.029794119
A104: Total | B104: =SUM(B2:B103) -> 18732 | E104: =SUM(E2:E103) -> 4069211 | F104: =SUM(F2:F103) -> 7287025.5 | G104: =SUM(G2:G103) -> 3196964.5 | H104: =G104/E104 -> 0.78564728

Sheet 20260301 MF
A1: Scheme | B1: Scheme Type | C1: Quantity | D1: Current Price | E1: Average Buy NAV | F1: Amount Invested | G1: Current Valuation | H1: Unrealised Gain/Loss | I1: Gain/ Loss %
A2: Axis Greater China Equity FoF Direct-Growth | B2: Equity : International | C2: 85853.914 | D2: 11.45 | E2: 8.7365 | F2: 750062.49 | G2: 983027.32 | H2: 232964.82 | I2: =H2/F2 -> 0.31059388
A3: Axis Midcap Direct Plan-Growth | B3: Equity : Mid Cap | C3: 4080.966 | D3: 133.22 | E3: 68.6078 | F3: 279986.11 | G3: 543666.29 | H3: 263680.18 | I3: =H3/F3 -> 0.94176165
A4: Axis Small Cap Fund Direct-Growth | B4: Equity : Small Cap | C4: 14235.332 | D4: 118.52 | E4: 47.7661 | F4: 679966.93 | G4: 1687171.5 | H4: 1007204.6 | I4: =H4/F4 -> 1.4812553
A5: Canara Robeco Small Cap Fund Direct - Growth | B5: Equity : Small Cap | C5: 30844.641 | D5: 41.49 | E5: 33.2294 | F5: 1024948.8 | G5: 1279744.2 | H5: 254795.4 | I5: =H5/F5 -> 0.2485933
A6: Edelweiss US Technology Equity FoF Direct - Growth | B6: Equity : International | C6: 16645.964 | D6: 32.088 | E6: 28.8345 | F6: 479978.08 | G6: 534135.69 | H6: 54157.615 | I6: =H6/F6 -> 0.11283352
A7: HDFC BSE Sensex Index Fund Direct-Growth | B7: Equity : Large Cap | C7: 1057.322 | D7: 773.1637 | E7: 390.4791 | F7: 412862.15 | G7: 817482.99 | H7: 404620.84 | I7: =H7/F7 -> 0.98003861
A8: HDFC Small Cap Fund Direct- Growth | B8: Equity : Small Cap | C8: 4306.576 | D8: 153.001 | E8: 44.3917 | F8: 191176.23 | G8: 658910.43 | H8: 467734.2 | I8: =H8/F8 -> 2.4466128
A9: Kotak Midcap Fund Direct-Growth | B9: Equity : Mid Cap | C9: 6304.493 | D9: 159.422 | E9: 51.3112 | F9: 323491.23 | G9: 1005074.9 | H9: 681583.65 | I9: =H9/F9 -> 2.1069617
A10: Motilal Oswal Nasdaq 100 FOF Direct - Growth | B10: Equity : International | C10: 13136.35 | D10: 47.5402 | E10: 29.6871 | F10: 389980.45 | G10: 624504.71 | H10: 234524.26 | I10: =H10/F10 -> 0.60137441
A11: Navi Nasdaq100 US Specific Equity Passive FoF Direct - Growth | B11: Equity : International | C11: 82131.044 | D11: 20.2455 | E11: 9.9227 | F11: 814959.24 | G11: 1662784.1 | H11: 847824.81 | I11: =H11/F11 -> 1.0403279
A12: Navi Nifty 50 Index Fund Direct - Growth | B12: Equity : Large Cap | C12: 84098.659 | D12: 16.5101 | E12: 13.2042 | F12: 1110455 | G12: 1388477.3 | H12: 278022.24 | I12: =H12/F12 -> 0.25036785
A13: Navi Nifty Next 50 Index Fund Direct - Growth | B13: Equity : Large Cap | C13: 46779.584 | D13: 16.5614 | E13: 14.1187 | F13: 660466.98 | G13: 774735.4 | H13: 114268.42 | I13: =H13/F13 -> 0.17301156
... A19: UTI Nifty Next 50 Index Fund Direct - Growth | B19: Equity : Large Cap | C19: 18996.168 | D19: 25.7835 | E19: 9.47 | F19: 179893.71 | G19: 489787.7 | H19: 309893.99 | I19: =H19/F19 -> 1.7226505
A22: Total | C22: =SUM(C2:C21) -> 488932.88 | F22: =SUM(F2:F21) -> 10320411 | G22: =SUM(G2:G21) -> 16538530 | H22: =SUM(H2:H21) -> 6218118.9 | I22: =H22/F22 -> 0.6025069

Sheet 20260201 E
A1: Instrument | B1: Qty. | C1: Avg. cost | D1: LTP | E1: Total Investment | F1: Cur. val | G1: P&L | H1: Gain %
A2: 716GS2050 | B2: 100 | C2: 109.73 | D2: 97.1 | E2: 10972.5 | F2: 9710 | G2: -1262.5 | H2: =G2/E2 -> -0.11506038
A3: AIRTELPP-E1 | B3: 13 | C3: 133.75 | D3: 1564.1 | E3: 1738.75 | F3: 20333.3 | G3: 18594.55 | H3: =G3/E3 -> 10.694206
A4: AJANTPHARM | B4: 19 | C4: 489.54 | D4: 2783.95 | E4: 9301.2 | F4: 52895.05 | G4: 43593.85 | H4: =G4/E4 -> 4.686906
A5: APOLLOTYRE | B5: 250 | C5: 183.59 | D5: 492.15 | E5: 45897.5 | F5: 123037.5 | G5: 77140 | H5: =G5/E5 -> 1.6807016
A6: AXISBANK | B6: 62 | C6: 708.24 | D6: 1370.4 | E6: 43910.6 | F6: 84964.8 | G6: 41054.2 | H6: =G6/E6 -> 0.93494965
A7: BAJAJ-AUTO | B7: 19 | C7: 3076.33 | D7: 9597.5 | E7: 58450.25 | F7: 182352.5 | G7: 123902.25 | H7: =G7/E7 -> 2.1197899
A8: BAJFINANCE | B8: 80 | C8: 673.1 | D8: 930.55 | E8: 53848.35 | F8: 74444 | G8: 20595.65 | H8: =G8/E8 -> 0.38247504
A9: BALKRISIND | B9: 15 | C9: 2427.47 | D9: 2305.85 | E9: 36412 | F9: 34587.75 | G9: -1824.25 | H9: =G9/E9 -> -0.050100242
A10: BANKBARODA | B10: 184 | C10: 188.19 | D10: 299.4 | E10: 34627.15 | F10: 55089.6 | G10: 20462.45 | H10: =G10/E10 -> 0.59093659
A11: BANKIETF | B11: 8500 | C11: 50.47 | D11: 61.08 | E11: 429035.72 | F11: 519180 | G11: 90144.28 | H11: =G11/E11 -> 0.21010903
A12: BHARTIARTL | B12: 180 | C12: 322.89 | D12: 1968.7 | E12: 58120 | F12: 354366 | G12: 296246 | H12: =G12/E12 -> 5.0971438
A13: BRIGADE | B13: 40 | C13: 446.04 | D13: 752.25 | E13: 17841.6 | F13: 30090 | G13: 12248.4 | H13: =G13/E13 -> 0.68650794
A14: BRITANNIA | B14: 14 | C14: 3489.94 | D14: 5860.5 | E14: 48859.1 | F14: 82047 | G14: 33187.9 | H14: =G14/E14 -> 0.67925729
A15: CASTROLIND | B15: 180 | C15: 155.25 | D15: 184.15 | E15: 27945 | F15: 33147 | G15: 5202 | H15: 0
A16: CIEINDIA | B16: 88 | C16: 373.58 | D16: 418.2 | E16: 32874.85 | F16: 36801.6 | G16: 3926.75 | H16: =G16/E16 -> 0.11944541
A17: CIPLA | B17: 45 | C17: 990.66 | D17: 1324 | E17: 44579.85 | F17: 59580 | G17: 15000.15 | H17: =G17/E17 -> 0.33647825
A18: COALINDIA | B18: 470 | C18: 194.39 | D18: 440.75 | E18: 91363.5 | F18: 207152.5 | G18: 115789 | H18: =G18/E18 -> 1.2673442
A19: COFORGE | B19: 65 | C19: 909.05 | D19: 1653.8 | E19: 59088.4 | F19: 107497 | G19: 48408.6 | H19: =G19/E19 -> 0.81925725
A20: COLPAL | B20: 21 | C20: 1503.03 | D20: 2114.2 | E20: 31563.7 | F20: 44398.2 | G20: 12834.5 | H20: =G20/E20 -> 0.40662216
A21: DLF | B21: 66 | C21: 557.49 | D21: 635.75 | E21: 36794.1 | F21: 41959.5 | G21: 5165.4 | H21: =G21/E21 -> 0.14038664
A22: DMART | B22: 12 | C22: 3474.64 | D22: 3689.5 | E22: 41695.7 | F22: 44274 | G22: 2578.3 | H22: =G22/E22 -> 0.061836113
A23: DRREDDY | B23: 60 | C23: 992.6 | D23: 1218.4 | E23: 59555.95 | F23: 73104 | G23: 13548.05 | H23: =G23/E23 -> 0.22748441
A24: EICHERMOT | B24: 7 | C24: 3506.83 | D24: 7122.5 | E24: 24547.8 | F24: 49857.5 | G24: 25309.7 | H24: =G24/E24 -> 1.0310374
A25: EMBASSY-RR | B25: 92 | C25: 359.33 | D25: 434.26 | E25: 33058.28 | F25: 39951.92 | G25: 6893.64 | H25: =G25/E25 -> 0.20852991
A26: ENDURANCE | B26: 24 | C26: 2007.86 | D26: 2427.9 | E26: 48188.7 | F26: 58269.6 | G26: 10080.9 | H26: =G26/E26 -> 0.20919635
A27: ENRIN | B27: 35 | C27: 234.44 | D27: 2491.3 | E27: 8205.53 | F27: 87195.5 | G27: 78989.97 | H27: =G27/E27 -> 9.6264312
... A63: PRESTIGE | B63: 33 | C63: 761.09 | D63: 1461.5 | E63: 25116 | F63: 48229.5 | G63: 23113.5 | H63: =G63/E63 -> 0.92026995
A64: 738REC27TF | B64: 20 | C64: 0 | D64: 1044 | E64: 0 | F64: 20880 | G64: 0
A65: SBILIFE | B65: 54 | C65: 1278.86 | D65: 1998.5 | E65: 69058.3 | F65: 107919 | G65: 38860.7 | H65: =G65/E65 -> 0.56272309
A66: SBIN | B66: 66 | C66: 426.28 | D66: 1077.55 | E66: 28134.5 | F66: 71118.3 | G66: 42983.8 | H66: =G66/E66 -> 1.5277968
A67: SGBAUG28V | B67: 10 | C67: 5284 | D67: 17717.88 | E67: 52840 | F67: 177178.8 | G67: 124338.8 | H67: =G67/E67 -> 2.3531188
A68: SGBJUL28IV | B68: 5 | C68: 4802 | D68: 17517.33 | E68: 24010 | F68: 87586.65 | G68: 63576.65 | H68: =G68/E68 -> 2.6479238
A69: SGBSEP28VI | B69: 10 | C69: 5002.45 | D69: 17568.18 | E69: 50024.5 | F69: 175681.8 | G69: 125657.3 | H69: =G69/E69 -> 2.5119152
A70: SIEMENS | B70: 35 | C70: 749.79 | D70: 3101.3 | E70: 26242.52 | F70: 108545.5 | G70: 82302.98 | H70: =G70/E70 -> 3.1362453
A71: SUNPHARMA | B71: 139 | C71: 582.57 | D71: 1595.3 | E71: 80977.15 | F71: 221746.7 | G71: 140769.55 | H71: =G71/E71 -> 1.7383861
A72: SYNGENE | B72: 75 | C72: 581.84 | D72: 473.7 | E72: 43638 | F72: 35527.5 | G72: -8110.5 | H72: =G72/E72 -> -0.18585866
A73: TATACONSUM | B73: 46 | C73: 794.51 | D73: 1133.9 | E73: 36547.3 | F73: 52159.4 | G73: 15612.1 | H73: =G73/E73 -> 0.42717519
A74: TATASTEEL | B74: 1050 | C74: 40.48 | D74: 193.13 | E74: 42500.25 | F74: 202786.5 | G74: 160286.25 | H74: =G74/E74 -> 3.771419
A75: TCS | B75: 33 | C75: 3575.9 | D75: 3125.05 | E75: 118004.55 | F75: 103126.65 | G75: -14877.9 | H75: =G75/E75 -> -0.12607904
A76: TITAN | B76: 24 | C76: 2584.4 | D76: 3977.45 | E76: 62025.6 | F76: 95458.8 | G76: 33433.2 | H76: =G76/E76 -> 0.5390226
... A80: ZYDUSLIFE | B80: 54 | C80: 896.15 | D80: 885.3 | E80: 48392.1 | F80: 47806.2 | G80: -585.9 | H80: =G80/E80 -> -0.012107348
A104: Total | B104: =SUM(B2:B103) -> 17805 | E104: =SUM(E2:E103) -> 4020945.4 | F104: =SUM(F2:F103) -> 7273433.9 | G104: =SUM(G2:G103) -> 3231608.5 | H104: =G104/E104 -> 0.80369369

Sheet 20260201 MF
A1: Scheme | B1: Scheme Type | C1: Quantity | D1: Current Price | E1: Average Buy NAV | F1: Amount Invested | G1: Current Valuation | H1: Unrealised Gain/Loss | I1: Gain/ Loss %
A2: Axis Greater China Equity FoF Direct-Growth | B2: Equity : International | C2: 81460.461 | D2: 11.89 | E2: 8.5939 | F2: 700065 | G2: 968564.88 | H2: 268499.88 | I2: =H2/F2 -> 0.38353565
A3: Axis Midcap Direct Plan-Growth | B3: Equity : Mid Cap | C3: 4080.966 | D3: 128.71 | E3: 68.6078 | F3: 279986.11 | G3: 525261.13 | H3: 245275.02 | I3: =H3/F3 -> 0.87602569
A4: Axis Small Cap Fund Direct-Growth | B4: Equity : Small Cap | C4: 14235.332 | D4: 116.75 | E4: 47.7661 | F4: 679966.93 | G4: 1661975 | H4: 982008.09 | I4: =H4/F4 -> 1.4441998
A5: Canara Robeco Small Cap Fund Direct - Growth | B5: Equity : Small Cap | C5: 30844.641 | D5: 41.31 | E5: 33.2294 | F5: 1024948.8 | G5: 1274192.1 | H5: 249243.36 | I5: =H5/F5 -> 0.24317641
A6: Edelweiss US Technology Equity FoF Direct - Growth | B6: Equity : International | C6: 16487.02 | D6: 34.9056 | E6: 28.8092 | F6: 474978.32 | G6: 575489.33 | H6: 100511.01 | I6: =H6/F6 -> 0.21161178
A7: HDFC BSE Sensex Index Fund Direct-Growth | B7: Equity : Large Cap | C7: 1246.686 | D7: 782.325 | E7: 381.8556 | F7: 476054.05 | G7: 975313.62 | H7: 499259.58 | I7: =H7/F7 -> 1.0487456
A8: HDFC Small Cap Fund Direct- Growth | B8: Equity : Small Cap | C8: 4306.576 | D8: 152.905 | E8: 44.3917 | F8: 191176.23 | G8: 658497 | H8: 467320.77 | I8: =H8/F8 -> 2.4444502
A9: Kotak Midcap Fund Direct-Growth | B9: Equity : Mid Cap | C9: 6304.493 | D9: 153.607 | E9: 51.3112 | F9: 323491.23 | G9: 968414.26 | H9: 644923.02 | I9: =H9/F9 -> 1.9936337
A10: Motilal Oswal Nasdaq 100 FOF Direct - Growth | B10: Equity : International | C10: 13136.35 | D10: 48.6877 | E10: 29.6871 | F10: 389980.45 | G10: 639578.67 | H10: 249598.22 | I10: =H10/F10 -> 0.64002753
A11: Navi Nasdaq100 US Specific Equity Passive FoF Direct - Growth | B11: Equity : International | C11: 82131.044 | D11: 21.2109 | E11: 9.9227 | F11: 814959.24 | G11: 1742073.4 | H11: 927114.12 | I11: =H11/F11 -> 1.1376202
A12: Navi Nifty 50 Index Fund Direct - Growth | B12: Equity : Large Cap | C12: 84098.659 | D12: 16.5953 | E12: 13.2042 | F12: 1110455 | G12: 1395642.5 | H12: 285187.45 | I12: =H12/F12 -> 0.25682035
A13: Navi Nifty Next 50 Index Fund Direct - Growth | B13: Equity : Large Cap | C13: 46779.584 | D13: 16.1042 | E13: 14.1187 | F13: 660466.98 | G13: 753347.78 | H13: 92880.799 | I13: =H13/F13 -> 0.14062898
... A19: UTI Nifty Next 50 Index Fund Direct - Growth | B19: Equity : Large Cap | C19: 18996.168 | D19: 25.0741 | E19: 9.47 | F19: 179893.71 | G19: 476311.82 | H19: 296418.11 | I19: =H19/F19 -> 1.6477402
A22: Total | C22: =SUM(C2:C21) -> 484417.87 | F22: =SUM(F2:F21) -> 10288608 | G22: =SUM(G2:G21) -> 16784013 | H22: =SUM(H2:H21) -> 6495405 | I22: =H22/F22 -> 0.63132011

Sheet 20260101 E
A1: Instrument | B1: Qty. | C1: Avg. cost | D1: LTP | E1: Total Investment | F1: Cur. val | G1: P&L | H1: Gain %
A2: 716GS2050-GS | B2: 100 | C2: 109.73 | D2: 101.01 | E2: 10972.5 | F2: 10101 | G2: =F2-E2 -> -871.5 | H2: =G2/E2 -> -0.079425837
A3: 738REC27TF-N2 | B3: 20 | C3: 0 | D3: 1045 | E3: 0 | F3: 20900 | G3: =F3-E3 -> 20900 | H3: =G3/E3 -> #DIV/0!
A4: AIRTELPP-E1 | B4: 13 | C4: 133.75 | D4: 1697.65 | E4: 1738.75 | F4: 22069.45 | G4: =F4-E4 -> 20330.7 | H4: =G4/E4 -> 11.69271
A5: AJANTPHARM | B5: 19 | C5: 489.54 | D5: 2936.55 | E5: 9301.2 | F5: 55794.45 | G5: =F5-E5 -> 46493.25 | H5: =G5/E5 -> 4.9986292
A6: APOLLOTYRE | B6: 250 | C6: 183.59 | D6: 494.2 | E6: 45897.5 | F6: 123550 | G6: =F6-E6 -> 77652.5 | H6: =G6/E6 -> 1.6918677
A7: AXISBANK | B7: 62 | C7: 708.24 | D7: 1274.4 | E7: 43910.6 | F7: 79012.8 | G7: =F7-E7 -> 35102.2 | H7: =G7/E7 -> 0.79940151
A8: BAJAJ-AUTO | B8: 19 | C8: 3076.33 | D8: 9560.6 | E8: 58450.25 | F8: 181651.4 | G8: =F8-E8 -> 123201.15 | H8: =G8/E8 -> 2.1077951
A9: BAJFINANCE | B9: 80 | C9: 673.1 | D9: 973.1 | E9: 53848.35 | F9: 77848 | G9: =F9-E9 -> 23999.65 | H9: =G9/E9 -> 0.44568961
A10: BALKRISIND | B10: 15 | C10: 2427.47 | D10: 2316.3 | E10: 36412 | F10: 34744.5 | G10: =F10-E10 -> -1667.5 | H10: =G10/E10 -> -0.045795342
A11: BANKBARODA | B11: 184 | C11: 188.19 | D11: 300.75 | E11: 34627.15 | F11: 55338 | G11: =F11-E11 -> 20710.85 | H11: =G11/E11 -> 0.59811015
A12: BANKIETF | B12: 8500 | C12: 50.47 | D12: 61 | E12: 429035.72 | F12: 518500 | G12: =F12-E12 -> 89464.28 | H12: =G12/E12 -> 0.20852408
A13: BHARTIARTL | B13: 180 | C13: 322.89 | D13: 2110.2 | E13: 58120 | F13: 379836 | G13: =F13-E13 -> 321716 | H13: =G13/E13 -> 5.5353751
A14: BRIGADE | B14: 40 | C14: 446.04 | D14: 896.65 | E14: 17841.6 | F14: 35866 | G14: =F14-E14 -> 18024.4 | H14: =G14/E14 -> 1.0102457
A15: BRITANNIA | B15: 14 | C15: 3489.94 | D15: 6009.5 | E15: 48859.1 | F15: 84133 | G15: =F15-E15 -> 35273.9 | H15: 0
A16: CASTROLIND | B16: 180 | C16: 155.25 | D16: 190.79 | E16: 27945 | F16: 34342.2 | G16: =F16-E16 -> 6397.2 | H16: =G16/E16 -> 0.2289211
A17: CIEINDIA | B17: 88 | C17: 373.58 | D17: 433.35 | E17: 32874.85 | F17: 38134.8 | G17: =F17-E17 -> 5259.95 | H17: =G17/E17 -> 0.15999921
A18: CIPLA | B18: 45 | C18: 990.66 | D18: 1500.9 | E18: 44579.85 | F18: 67540.5 | G18: =F18-E18 -> 22960.65 | H18: =G18/E18 -> 0.51504547
A19: COALINDIA | B19: 470 | C19: 194.39 | D19: 400.35 | E19: 91363.5 | F19: 188164.5 | G19: =F19-E19 -> 96801 | H19: =G19/E19 -> 1.059515
A20: COFORGE | B20: 65 | C20: 909.05 | D20: 1655.8 | E20: 59088.4 | F20: 107627 | G20: =F20-E20 -> 48538.6 | H20: =G20/E20 -> 0.82145734
A21: COLPAL | B21: 21 | C21: 1503.03 | D21: 2093.65 | E21: 31563.7 | F21: 43966.65 | G21: =F21-E21 -> 12402.95 | H21: =G21/E21 -> 0.39294981
A22: DLF | B22: 66 | C22: 557.49 | D22: 691.7 | E22: 36794.1 | F22: 45652.2 | G22: =F22-E22 -> 8858.1 | H22: =G22/E22 -> 0.24074784
A23: DMART | B23: 12 | C23: 3474.64 | D23: 3716.1 | E23: 41695.7 | F23: 44593.2 | G23: =F23-E23 -> 2897.5 | H23: =G23/E23 -> 0.069491578
A24: DRREDDY | B24: 60 | C24: 992.6 | D24: 1253.4 | E24: 59555.95 | F24: 75204 | G24: =F24-E24 -> 15648.05 | H24: =G24/E24 -> 0.26274537
A25: EICHERMOT | B25: 7 | C25: 3506.83 | D25: 7348 | E25: 24547.8 | F25: 51436 | G25: =F25-E25 -> 26888.2 | H25: =G25/E25 -> 1.0953405
A26: EMBASSY-RR | B26: 92 | C26: 359.33 | D26: 435.69 | E26: 33058.28 | F26: 40083.48 | G26: =F26-E26 -> 7025.2 | H26: =G26/E26 -> 0.21250954
A27: ENDURANCE | B27: 24 | C27: 2007.86 | D27: 2542.2 | E27: 48188.7 | F27: 61012.8 | G27: =F27-E27 -> 12824.1 | H27: =G27/E27 -> 0.26612256
... A63: PIDILITIND | B63: 60 | C63: 1249.57 | D63: 1469.3 | E63: 74974.35 | F63: 88158 | G63: =F63-E63 -> 13183.65 | H63: =G63/E63 -> 0.17584214
A64: PRESTIGE | B64: 33 | C64: 761.09 | D64: 1604.1 | E64: 25116 | F64: 52935.3 | G64: =F64-E64 -> 27819.3
A65: SBILIFE | B65: 54 | C65: 1278.86 | D65: 2040.4 | E65: 69058.3 | F65: 110181.6 | G65: =F65-E65 -> 41123.3 | H65: =G65/E65 -> 0.59548671
A66: SBIN | B66: 66 | C66: 426.28 | D66: 984.7 | E66: 28134.5 | F66: 64990.2 | G66: =F66-E66 -> 36855.7 | H66: =G66/E66 -> 1.3099824
A67: SGBAUG28V-GB | B67: 10 | C67: 5284 | D67: 14634.04 | E67: 52840 | F67: 146340.4 | G67: =F67-E67 -> 93500.4 | H67: =G67/E67 -> 1.7695004
A68: SGBJUL28IV | B68: 5 | C68: 4802 | D68: 14376 | E68: 24010 | F68: 71880 | G68: =F68-E68 -> 47870 | H68: =G68/E68 -> 1.9937526
A69: SGBSEP28VI | B69: 10 | C69: 5002.45 | D69: 14411 | E69: 50024.5 | F69: 144110 | G69: =F69-E69 -> 94085.5 | H69: =G69/E69 -> 1.8807884
A70: SIEMENS | B70: 35 | C70: 749.79 | D70: 3091.3 | E70: 26242.52 | F70: 108195.5 | G70: =F70-E70 -> 81952.98 | H70: =G70/E70 -> 3.1229082
A71: SUNPHARMA | B71: 139 | C71: 582.57 | D71: 1726.8 | E71: 80977.15 | F71: 240025.2 | G71: =F71-E71 -> 159048.05 | H71: =G71/E71 -> 1.9641102
A72: SYNGENE | B72: 75 | C72: 581.84 | D72: 650.2 | E72: 43638 | F72: 48765 | G72: =F72-E72 -> 5127 | H72: =G72/E72 -> 0.11748934
A73: TATACONSUM | B73: 46 | C73: 794.51 | D73: 1177.15 | E73: 36547.3 | F73: 54148.9 | G73: =F73-E73 -> 17601.6 | H73: =G73/E73 -> 0.4816115
A74: TATASTEEL | B74: 1050 | C74: 40.48 | D74: 181.89 | E74: 42500.25 | F74: 190984.5 | G74: =F74-E74 -> 148484.25 | H74: =G74/E74 -> 3.4937265
A75: TCS | B75: 33 | C75: 3575.9 | D75: 3227.4 | E75: 118004.55 | F75: 106504.2 | G75: =F75-E75 -> -11500.35 | H75: =G75/E75 -> -0.097456835
A76: TITAN | B76: 24 | C76: 2584.4 | D76: 4049.3 | E76: 62025.6 | F76: 97183.2 | G76: =F76-E76 -> 35157.6 | H76: =G76/E76 -> 0.56682402
... A80: ZYDUSLIFE | B80: 54 | C80: 896.15 | D80: 914.55 | E80: 48392.1 | F80: 49385.7 | G80: =F80-E80 -> 993.6 | H80: =G80/E80 -> 0.020532277
A104: Total | B104: =SUM(B2:B103) -> 17577 | E104: =SUM(E2:E103) -> 4020945.4 | F104: =SUM(F2:F103) -> 7368802.1 | G104: =SUM(G2:G103) -> 3347856.7 | H104: =G104/E104 -> 0.83260437

Sheet 20260101 MF
A1: Scheme | B1: Scheme Type | C1: Quantity | D1: Current Price | E1: Average Buy NAV | F1: Amount Invested | G1: Current Valuation | H1: Unrealised Gain/Loss | I1: Gain/ Loss %
A2: Axis Greater China Equity FoF Direct-Growth | B2: Equity : International | C2: 76822.474 | D2: 10.53 | E2: 8.4619 | F2: 650067.5 | G2: 808940.65 | H2: 158873.15 | I2: =H2/F2 -> 0.24439486
A3: Axis Midcap Direct Plan-Growth | B3: Equity : Mid Cap | C3: 4080.966 | D3: 132.07 | E3: 68.6078 | F3: 279986.11 | G3: 538973.18 | H3: 258987.07 | I3: =H3/F3 -> 0.92499971
